Workbook

Sheet Rúbrica Resultados Globales
A2: A) | B2: Definiciones a nivel micro (rúbrica)
C4: Nivel de logro
C5: Óptimo | D5: Satisfactorio | E5: Base | F5: Por Mejorar | G5: No observado
C6: (4 puntos) | D6: (3 puntos) | E6: (2 puntos) | F6: (1 punto) | G6: (0 punto)
C7: El desempeño descrito se logra completamente | D7: El desempeño descrito se logra, sin embargo, presenta algunas imprecisiones. | E7: El desempeño descrito se logra de forma mínima | F7: El desempeño descrito se presenta de forma errónea y/o no se ajusta a lo solicitado | G7: El desempeño descrito no es observado dada la ausencia de acciones o productos
A9: B) | B9: Definiciones a nivel macro (EPI)
B10: El presente documento tiene por objetivo especificar los criterios que dan origen a las definiciones del indicador global de EPI. Entendemos que la EPI es una evaluación formativa, donde existe una diversidad de instrumentos y exigencias asociadas a ellos que responde a la especificidad de cada disciplina. Sin embargo, desde el nivel central el foco se sitúa fundamentalmente en detectar las necesidades de apoyo necesarias que requeriría el estudiantado para continuar su ciclo de profundización, y, en otro casos, para detectar los niveles de autonomía que presentan los/las estudiantes para transitar al ciclo de profundización. En este contexto, los términos utilizados la columna “Justificación” de la siguiente tabla, como; “buen nivel”, “apropiado”,” mínimo”, deben entenderse en el contexto específico y situado de cada evaluación.
C15: Categorías
C16: Óptimo | D16: Satisfactorio | E16: Base | F16: Por Mejorar
B17: Porcentajes | C17: 100%-85% | D17: 84% - 65% | E17: 64% - 50% | F17: 0% - 49%
B18: Definiciones | C18: Los resultados obtenidos por el/la estudiante en la Evaluación de Perfil Intermedio evidencian que ha logrado los aprendizajes clave del Ciclo Básico de formación que le permiten continuar con su trayectoria formativa en el Ciclo de Profundización y/ Especialización, con autonomía, avanzando en el desarrollo de los desempeños evidenciados. | D18: Los resultados obtenidos por el/la estudiante en la Evaluación de Perfil Intermedio evidencian que ha logrado los aprendizajes clave del Ciclo Básico de formación que le permiten continuar con su trayectoria formativa en el Ciclo de Profundización y/o Especialización, con autonomía. Sin embargo, se evidencian aspectos específicos y acotados en que es necesario fortalecer los desempeños. | E18: Los resultados obtenidos por el/la estudiante en la Evaluación de Perfil Intermedio evidencian que el logro de los aprendizajes clave del Ciclo Básico de formación se cumplen de manera mínimay requieren ser fortalecidos durante el Ciclo de Profundización y/o Especialización, para apoyar la continuidad de la trayectoria formativa. | F18: Los resultados obtenidos por el/la estudiante en la Evaluación de Perfil Intermedio evidencian que no se han logrado los aprendizajes clave del Ciclo Básico de formación , requiriendo de acciones de apoyo en el Ciclo de Profundización y/o Especialización que favorezcan el desarrollo de los desempeños evaluados y aseguren la continuidad de la trayectoria formativa. | H18: El/la estudiante en la Evaluación de Perfil Intermedio no presenta respuestas, lo que no permite evidenciar el logro de los aprendizajes clave del Ciclo Básico de formación.
C19: El/la estudiante avanza con autonomía al Ciclo de Profundización y/o Especialización. Cuenta con desempeños relevantes para la continuidad de su trayectoria formativa | E19: El/la estudiante avanza al Ciclo de Profundización y/o Especialización con apoyos adicionales para desarrollar los aprendizajes prioritarios que permiten dar continuidad a su trayectoria formativa
C20: Acciones de fortalecimiento de las trayectorias formativas
B21: Justificación | C21: Dado el carácter formativo de esta evaluación, se define este nivel a partir del 85% ya que a partir de este porcentaje se evidencia con claridad un buen nivel de conocimientos teórico-disciplinares de los contenidos, así como un muy buen manejo metodológico/práctico de estos, sin necesitar apoyos especificos. | D21: Dado el carácter formativo de esta evaluación, se define este nivel a partir del 65% y no del 70% en función del criterio de la autonomía para poder continuar hacia el ciclo de profundización, siendo el 65% un nivel de solidez suficiente para aquello, demostrando un conocimiento apropiado de los conocimientos teórico-disciplinares y un manejo apropiado metodológico/práctico de estos. Esto también obedece a la diversidad de EPIs existentes y a los distintos niveles de exigencia de los distintos instrumentos. | E21: Dado el carácter formativo de la evaluación, se define este nivel a partir del 50% ya que el/la estudiante demuestra un conocimiento/manejo básico de los contenidos/habilidades esenciales, sin embargo el nivel de profundidad de este manejo es superficial/parcial/insuficiente. logrando solo a mitad del puntaje. El nivel de profundidad de los aprendizajes logrados y la consecuente necesidad de apoyos predominan para definir los porcentajes de logro de este nivel. | F21: Dado el carácter formativo de la evaluación, se define este nivel como porcentajes de logro menores al 50%, ya que el/la estudiante no alcanza un mínimo de conocimiento ni manejo de contenidos y habilidades esperadas, evidenciando la necesidad de apoyos para poder transitar al ciclo de profundización.

Sheet Rúbrica situación evaluativa 
V136: *

Sheet Resultados Individuales
A1: DATOS DE ESTUDIANTES DE LA COHORTE | K1: Actividad problema 1 Nivel de logro 1: 1 punto Nivel de logro 2 : 2 puntos Nivel del logro 3 : 3 puntos Nivel de logro 4 : 4 puntos | O1: Actividad Problema 2 Nivel de logro 1: 1 punto Nivel de logro 2 : 2 puntos Nivel del logro 3 : 3 puntos Nivel de logro 4 : 4 puntos | S1: Resultado General por estudiante
V2: COMENTARIOS GENERALES POR ESTUDIANTE
A3: RUT ESTUDIANTE | B3: DV | D3: PRIMER APELLIDO (Apellido paterno) | E3: SEGUNDO APELLIDO (Apellido materno) | F3: NOMBRES | G3: ESTADO DE HABILITACIÓN PARA RENDIR | H3: ESTATUS DE RENDICIÓN | I3: FECHA DE RENDICIÓN | J3: JUSTIFICACIÓN DE NO RENDICIÓN | K3: Toma de posición respecto de la idoneidad de la acción de precario. | L3: Posicionamiento crítico en torno a elementos éticos y de justicia social incluidos en el caso. | M3: Identificación de razonamientos jurídicos y sus posibles correlaciones. (Razonamiento jurisdiccional y razonamiento académico) | N3: Uso del lenguaje jurídico apropiado con el caso y postura en el rol de abogado. | O3: Análisis enfoque del de género en el proyecto de ley | P3: Reflexión sobre desigualdades estructurales en el contexto procesal de familia | Q3: Perspectiva interseccional en el análisis | R3: Uso del lenguaje jurídico apropiado con el caso y postura en el rol de abogado/a | S3: PUNTAJE TOTAL ESTUDIANTE | T3: PORCENTAJE DE LOGRO | U3: CATEGORÍA RESULTADO GLOBAL ESTUDIANTE
A4: 8915103 | B4: 1 | C4: ALEJANDRO ROBERTO ROJAS SANTANDER | D4: ROJAS | E4: SANTANDER | F4: ALEJANDRO ROBERTO | G4: Avance curricular suficiente o adecuado para evaluar ciclo básico | H4: No rendida | I4: no aplica | S4: =SUM(K4:R4) -> 0 | T4: =S4/40 -> 0 | U4: =IF(H4="Rendida ",IF('Resultados Individuales'!T4<49.5%,"Por Mejorar",IF('Resultados Individuales'!T4<64.5%,"Base",IF('Resultados Individuales'!T4<84.5%,"Satisfactorio","Óptimo"))),"No rendida o no válida") -> No rendida o no válida
A5: 11828211 | B5: 6 | C5: MICHELE LOUISSETTE HIRIART LAULIE | D5: HIRIART | E5: LAULIE | F5: MICHELE LOUISSETTE | G5: Avance curricular suficiente o adecuado para evaluar ciclo básico | H5: Rendida | I5: 45758 | K5: 3 | L5: 4 | M5: 4 | N5: 4 | O5: 3 | P5: 3 | Q5: 2 | R5: 4 | S5: =SUM(K5:R5) -> 27 | T5: =S5/40 -> 0.675 | U5: =IF(H5="Rendida ",IF('Resultados Individuales'!T5<49.5%,"Por Mejorar",IF('Resultados Individuales'!T5<64.5%,"Base",IF('Resultados Individuales'!T5<84.5%,"Satisfactorio","Óptimo"))),"No rendida o no válida") -> Satisfactorio | V5: El desempeño evidenciado en ambas actividades refleja un nivel de análisis jurídico sobresaliente, caracterizado por el uso preciso y riguroso del lenguaje técnico, la identificación clara de instituciones y categorías relevantes, así como por la capacidad de integrar razonamientos normativos con dimensiones éticas y sociales. En la primera actividad, se observa un análisis crítico excepcional que aborda con profundidad la tensión entre equidad y seguridad jurídica, vinculando con maestría el pensamiento de Finnis con el razonamiento judicial, lo que demuestra madurez conceptual y un dominio sólido del derecho contemporáneo. En la segunda actividad, se visibiliza un manejo claro de las innovaciones procesales y del enfoque de derechos de niñez y género, destacando medidas concretas como la participación efectiva de NNA y la incorporación de representaciones jurídicas especializadas, junto con una acertada reflexión sobre el rol del proceso judicial en la protección de derechos desde una mirada interseccional. Para alcanzar un nivel óptimo en todas las dimensiones, se sugiere como proyección futura reforzar la referencia explícita a normas específicas —citando artículos del proyecto de ley analizado— e integrar el marco internacional aplicable, como la CEDAW o la Convención sobre los Derechos del Niño. Asimismo, sería valioso profundizar en el análisis interseccional, considerando cómo variables como clase social y pertenencia étnica inciden en el acceso a la justicia. Esta consolidación permitiría elevar aún más la calidad ya destacada del trabajo
A6: 15166536 | B6: 5 | C6: CAMILA YITSEN ALVAREZ ARUCUTIPA | D6: ALVAREZ | E6: ARUCUTIPA | F6: CAMILA YITSEN | G6: Avance curricular suficiente o adecuado para evaluar ciclo básico | H6: Rendida | I6: 45758 | K6: 1 | L6: 2 | M6: 3 | N6: 3 | O6: 3 | P6: 3 | Q6: 3 | R6: 3 | S6: =SUM(K6:R6) -> 21 | T6: =S6/40 -> 0.525 | U6: =IF(H6="Rendida ",IF('Resultados Individuales'!T6<49.5%,"Por Mejorar",IF('Resultados Individuales'!T6<64.5%,"Base",IF('Resultados Individuales'!T6<84.5%,"Satisfactorio","Óptimo"))),"No rendida o no válida") -> Base | V6: El desempeño en las dos actividades refleja contrastes claros en el logro de competencias del perfil intermedio de Derecho. En la primera actividad, si bien se desarrollan las tres preguntas y se hace referencia expresa al art. 2195 del Código Civil, así como a la teoría de Finnis y al valor del matrimonio como institución, se observa una confusión conceptual grave: la consigna exigía argumentar la postura opuesta a la del tribunal (defender la procedencia del precario), pero la respuesta se alinea con el razonamiento judicial, afectando la coherencia de todo el análisis. Esta omisión impide un desarrollo técnico sólido de los elementos del precario y resta profundidad al análisis ético, que se mantiene en un nivel superficial sin incorporar categorías centrales como seguridad jurídica, interpretación extensiva o incorrecta aplicación del derecho. Se requiere también mayor precisión en la relación entre jurisprudencia y derecho positivo, así como un desarrollo más completo de los dos elementos constitutivos del matrimonio según Finnis. En contraste, en la segunda actividad se aprecia un manejo mucho más maduro de las herramientas jurídicas y del análisis crítico. Destacan la identificación precisa de los mecanismos de participación de NNA —audiencias específicas, obligación de fundamentación judicial y vínculo con autonomía progresiva— y un análisis competente del enfoque de género que reconoce medidas como la protección reforzada en casos de violencia intrafamiliar, la corresponsabilidad en la tuición y la capacitación judicial. Asimismo, se contextualizan acertadamente motivaciones legislativas relevantes (crisis del ex-SENAME, estallido social 2019, proceso constituyente), y la relación con el debido proceso se fundamenta de manera ejemplar mediante la Convención Americana de Derechos Humanos y la jurisprudencia de la Corte IDH. Aun con estas fortalezas, para alcanzar un nivel óptimo se sugiere profundizar en la relevancia normativa específica, vincular más explícitamente las medidas con estándares internacionales concretos (CEDAW, Convención sobre los Derechos del Niño) y ampliar el tratamiento de la interseccionalidad, analizando cómo variables como género, edad, clase y etnia se entrecruzan en el acceso a la justicia.
A7: 16071809 | B7: 9 | C7: VANESSA ELENA CARRASCO MUÑOZ | D7: CARRASCO | E7: MUÑOZ | F7: VANESSA ELENA | G7: Avance curricular suficiente o adecuado para evaluar ciclo básico | H7: Rendida | I7: 45758 | K7: 3 | L7: 4 | M7: 4 | N7: 4 | O7: 2 | P7: 2 | Q7: 2 | R7: 3 | S7: =SUM(K7:R7) -> 24 | T7: =S7/40 -> 0.6 | U7: =IF(H7="Rendida ",IF('Resultados Individuales'!T7<49.5%,"Por Mejorar",IF('Resultados Individuales'!T7<64.5%,"Base",IF('Resultados Individuales'!T7<84.5%,"Satisfactorio","Óptimo"))),"No rendida o no válida") -> Base | V7: El desempeño en ambas actividades refleja un manejo sólido del razonamiento jurídico y del uso de un lenguaje técnico especializado, con especial fortaleza en el desarrollo conceptual y crítico. En la primera actividad, el análisis del precario es coherente y bien estructurado, demostrando comprensión de la figura y de la ausencia de nexo jurídico como fundamento central de la acción. Destaca un posicionamiento ético original y profundo, que problematiza con rigor las tensiones entre justicia social y seguridad jurídica, utilizando categorías avanzadas como interpretación extensiva, analogía e incorrecta aplicación del derecho. Asimismo, la correlación con la filosofía de Finnis se desarrolla con solvencia académica, estableciendo límites críticos a las obligaciones derivadas del matrimonio y proponiendo una ponderación entre instituciones jurídicas. El lenguaje técnico utilizado refleja madurez formativa y proyección profesional. Para fortalecer aún más este desempeño, se sugiere citar directamente el art. 2195 del Código Civil y sistematizar de manera más clara los tres requisitos del precario, junto con mejorar ciertos detalles formales de construcción sintáctica. En la segunda actividad, se evidencia un buen manejo del tema, destacando la identificación precisa de los mecanismos de participación de niños, niñas y adolescentes —derecho a ser oídos, audiencias adaptadas y obligación de fundamentación judicial— y su correcta vinculación con la autonomía progresiva. También es pertinente la valoración de la coordinación intersectorial como herramienta clave para la garantía de derechos. Sin embargo, el análisis del enfoque de género requiere mayor profundidad, dado que no se distinguen medidas concretas orientadas a mujeres, niñas o adolescentes ni se articulan normas internacionales relevantes. La interseccionalidad aparece mencionada, pero sin integrar un examen crítico de variables múltiples que incidan en el acceso a la justicia. Como proyección de mejora, se recomienda incorporar referencias a instrumentos internacionales sobre igualdad y no discriminación (CEDAW, Convención de Belém do Pará), así como profundizar el análisis en torno a fenómenos sociales nacionales recientes (crisis del SENAME, estallido social de 2019, proceso constituyente) y desarrollar una mirada interseccional más completa, incluyendo género, clase y etnia.
A8: 17879125 | B8: 7 | C8: FELIPE IGNACIO PARRA OROPESA | D8: PARRA | E8: OROPESA | F8: FELIPE IGNACIO | G8: Interrupción voluntaria (no rinde EPI 2025) | S8: =SUM(K8:R8) -> 0 | T8: =S8/40 -> 0 | U8: =IF(H8="Rendida ",IF('Resultados Individuales'!T8<49.5%,"Por Mejorar",IF('Resultados Individuales'!T8<64.5%,"Base",IF('Resultados Individuales'!T8<84.5%,"Satisfactorio","Óptimo"))),"No rendida o no válida") -> No rendida o no válida
A9: 18502526 | B9: 8 | C9: JORGE RODRIGO GALLEGUILLOS MOTA | D9: GALLEGUILLOS | E9: MOTA | F9: JORGE RODRIGO | G9: Avance curricular suficiente o adecuado para evaluar ciclo básico | H9: No rendida | I9: no aplica | S9: =SUM(K9:R9) -> 0 | T9: =S9/40 -> 0 | U9: =IF(H9="Rendida ",IF('Resultados Individuales'!T9<49.5%,"Por Mejorar",IF('Resultados Individuales'!T9<64.5%,"Base",IF('Resultados Individuales'!T9<84.5%,"Satisfactorio","Óptimo"))),"No rendida o no válida") -> No rendida o no válida
A10: 18956008 | B10: 7 | C10: NICOLÁS ALEJANDRO CATALÁN ARTIGAS | D10: CATALÁN | E10: ARTIGAS | F10: NICOLÁS ALEJANDRO | G10: Avance curricular suficiente o adecuado para evaluar ciclo básico | H10: Rendida | I10: 45758 | K10: 4 | L10: 4 | M10: 4 | N10: 4 | O10: 3 | P10: 4 | Q10: 4 | R10: 3 | S10: =SUM(K10:R10) -> 30 | T10: =S10/40 -> 0.75 | U10: =IF(H10="Rendida ",IF('Resultados Individuales'!T10<49.5%,"Por Mejorar",IF('Resultados Individuales'!T10<64.5%,"Base",IF('Resultados Individuales'!T10<84.5%,"Satisfactorio","Óptimo"))),"No rendida o no válida") -> Satisfactorio | V10: El desempeño alcanzado en ambas actividades refleja un nivel sobresaliente de análisis jurídico, técnico y ético, propio de un perfil intermedio consolidado con proyección hacia niveles avanzados. En la primera actividad, se observa un desarrollo sistemático y riguroso de la institución del precario, abordando con precisión los tres requisitos copulativos del art. 2195 del Código Civil y destacando con fundamentación sólida la inexistencia de nexo jurídico entre las partes. El posicionamiento ético trasciende lo meramente formal al incorporar múltiples dimensiones —justicia social, perspectiva de género e interés superior del menor— ofreciendo una comprensión holística de la problemática. La referencia a la teoría de John Finnis se articula de modo académico y pertinente, integrando los elementos constitutivos del matrimonio (fides y procreación) y vinculándolos con el considerando quinto de la sentencia, lo que revela madurez en el razonamiento teórico y práctico. El lenguaje jurídico empleado es técnico, preciso y profesional. En la segunda actividad, se constata un manejo conceptual igualmente sólido sobre el proyecto de ley, destacando la identificación clara de innovaciones procesales y el análisis profundo del enfoque de género, con énfasis en la corresponsabilidad parental, medidas de protección en contextos de violencia intrafamiliar y la creación de unidades técnicas especializadas para fortalecer la protección integral. Su reflexión crítica sobre desigualdades estructurales es consistente y se complementa con una adecuada integración de la perspectiva interseccional, considerando género, edad y situación socioeconómica. El uso del lenguaje jurídico es preciso, articulando correctamente estándares de debido proceso y principios rectores como el interés superior del niño. Para avanzar hacia un nivel de excelencia, se sugiere enriquecer el análisis con citas y referencias directas a instrumentos internacionales sobre derechos humanos (por ejemplo, Convención sobre los Derechos del Niño, CEDAW y Convención de Belém do Pará), y profundizar en la fundamentación normativa de las medidas de género a la luz del derecho comparado y las obligaciones internacionales del Estado
A11: 19126017 | B11: 1 | C11: ANGELA ESTEFANÍA JEREZ SILVA | D11: JEREZ | E11: SILVA | F11: ANGELA ESTEFANÍA | G11: Avance curricular suficiente o adecuado para evaluar ciclo básico | H11: No aplica | I11: no aplica | J11: No aplica | S11: =SUM(K11:R11) -> 0 | T11: =S11/40 -> 0 | U11: =IF(H11="Rendida ",IF('Resultados Individuales'!T11<49.5%,"Por Mejorar",IF('Resultados Individuales'!T11<64.5%,"Base",IF('Resultados Individuales'!T11<84.5%,"Satisfactorio","Óptimo"))),"No rendida o no válida") -> No rendida o no válida
A12: 19429710 | B12: 6 | C12: GABRIEL FERNANDO VALLEJOS MANRIQUEZ | D12: VALLEJOS | E12: MANRIQUEZ | F12: GABRIEL FERNANDO | G12: Avance curricular suficiente o adecuado para evaluar ciclo básico | H12: Rendida | I12: 45758 | K12: 2 | L12: 2 | M12: 3 | N12: 2 | O12: 2 | P12: 2 | Q12: 1 | R12: 2 | S12: =SUM(K12:R12) -> 16 | T12: =S12/40 -> 0.4 | U12: =IF(H12="Rendida ",IF('Resultados Individuales'!T12<49.5%,"Por Mejorar",IF('Resultados Individuales'!T12<64.5%,"Base",IF('Resultados Individuales'!T12<84.5%,"Satisfactorio","Óptimo"))),"No rendida o no válida") -> Por Mejorar | V12: El desempeño en ambas actividades muestra logros parciales en la aplicación del razonamiento jurídico y en la expresión argumentativa, aunque con diferencias marcadas entre los dos trabajos. En la primera actividad, se reconoce una comprensión general de los requisitos del precario y del valor institucional del matrimonio dentro del razonamiento judicial, pero la respuesta evidencia debilidades importantes en la construcción argumentativa y en la claridad conceptual, confundiendo elementos como herencia y posesión. El análisis ético y social es superficial y no logra profundizar en problemas claves como la justicia social o el uso de la analogía. El lenguaje jurídico empleado es básico e impreciso, acompañado de una redacción desordenada con errores de construcción que afectan la fluidez. Como proyección de mejora, resulta fundamental consolidar los aspectos técnicos de la institución del precario, trabajar un análisis crítico más robusto de las consecuencias jurídicas y sociales, y reforzar la expresión escrita formal y la argumentación sistemática. En la segunda actividad, se observa un mejor manejo de los contenidos, destacando la descripción de los mecanismos de participación de NNA —derecho a ser oídos, audiencias adaptadas y obligación de fundamentación judicial— así como su vinculación con la autonomía progresiva y las medidas de capacitación judicial. Del mismo modo, se identifica el avance hacia la corresponsabilidad parental y la protección reforzada ante violencia intrafamiliar. Sin embargo, el análisis resulta limitado en lo relativo al enfoque de género al no incorporar normas específicas, y la perspectiva interseccional solo se menciona de manera general a través de la referencia a niñas en contextos de vulnerabilidad, sin un desarrollo crítico más amplio. El lenguaje jurídico es funcional, pero el trabajo ganaría solidez con citas expresas a la Ley 21.430, la Convención sobre los Derechos del Niño, así como a disposiciones concretas del Código Civil y de Procedimiento Civil.
A13: 19522830 | B13: 2 | C13: PABLO VICENTE PARRY ARROYO | D13: PARRY | E13: ARROYO | F13: PABLO VICENTE | G13: Avance curricular suficiente o adecuado para evaluar ciclo básico | H13: Rendida | I13: 45758 | K13: 3 | L13: 4 | M13: 4 | N13: 4 | O13: 2 | P13: 3 | Q13: 3 | R13: 3 | S13: =SUM(K13:R13) -> 26 | T13: =S13/40 -> 0.65 | U13: =IF(H13="Rendida ",IF('Resultados Individuales'!T13<49.5%,"Por Mejorar",IF('Resultados Individuales'!T13<64.5%,"Base",IF('Resultados Individuales'!T13<84.5%,"Satisfactorio","Óptimo"))),"No rendida o no válida") -> Satisfactorio | V13: El desempeño en ambas actividades refleja un nivel jurídico avanzado, con proyección hacia estándares superiores al perfil intermedio esperado. En la primera actividad, se evidencia un posicionamiento ético crítico excepcional, que incorpora con precisión todos los conceptos técnicos solicitados —seguridad jurídica, incorrecta aplicación del derecho, orden público y protección constitucional—. La correlación conceptual es sobresaliente, identificando y vinculando las motivaciones de Finnis como contenidos implícitos del razonamiento judicial. Se desarrolla brillantemente la idea del matrimonio como bien humano intrínsecamente inteligible, conectando este valor con la decisión del tribunal de resguardar no solo los derechos legales, sino también las emociones y la salud mental de los cónyuges. El lenguaje jurídico es técnico y preciso, la estructura metodológica impecable y la redacción de excelencia, lo que proyecta un alto dominio conceptual y profesional. La única oportunidad de mejora se encuentra en profundizar aún más en el análisis de idoneidad del precario, desarrollando exhaustivamente los tres requisitos copulativos del art. 2195 CC en conexión explícita con los elementos del matrimonio según Finnis. En la segunda actividad, se articula de manera clara y rigurosa la relación entre los mecanismos de participación de los NNA (derecho a ser oídos, audiencias adaptadas y motivación judicial) con los principios rectores de autonomía progresiva e interés superior del niño. Asimismo, se destaca la obligación de coordinación intersectorial como herramienta esencial de protección. El análisis de género reconoce medidas concretas como la protección reforzada en contextos de violencia intrafamiliar, aunque carece de referencias normativas más específicas que lo robustezcan. La reflexión sobre desigualdades estructurales y la perspectiva interseccional es pertinente, integrando variables de edad, género y vulnerabilidad socioeconómica, y proyectando un rol activo de la representación y capacitación especializada. El lenguaje jurídico es profesional y fundamentado en la Ley N° 21.430 y en la Convención sobre los Derechos del Niño, lo que refuerza la solidez argumentativa.
A14: 19636454 | B14: 4 | C14: BRYAM ROY PARADA DURÁN | D14: PARADA | E14: DURÁN | F14: BRYAM ROY | G14: Interrupción voluntaria (no rinde EPI 2025) | S14: =SUM(K14:R14) -> 0 | T14: =S14/40 -> 0 | U14: =IF(H14="Rendida ",IF('Resultados Individuales'!T14<49.5%,"Por Mejorar",IF('Resultados Individuales'!T14<64.5%,"Base",IF('Resultados Individuales'!T14<84.5%,"Satisfactorio","Óptimo"))),"No rendida o no válida") -> No rendida o no válida
A15: 19645915 | B15: 4 | C15: LISANDRO ARTURO BUSTAMANTE DONOSO | D15: BUSTAMANTE | E15: DONOSO | F15: LISANDRO ARTURO | G15: Avance curricular suficiente o adecuado para evaluar ciclo básico | H15: No rendida | I15: no aplica | S15: =SUM(K15:R15) -> 0 | T15: =S15/40 -> 0 | U15: =IF(H15="Rendida ",IF('Resultados Individuales'!T15<49.5%,"Por Mejorar",IF('Resultados Individuales'!T15<64.5%,"Base",IF('Resultados Individuales'!T15<84.5%,"Satisfactorio","Óptimo"))),"No rendida o no válida") -> No rendida o no válida
A16: 19647397 | B16: 1 | C16: BELEN SOLANGE ARCE VALENZUELA | D16: ARCE | E16: VALENZUELA | F16: BELEN SOLANGE | G16: Avance curricular suficiente o adecuado para evaluar ciclo básico | H16: Rendida | I16: 45758 | K16: 3 | L16: 2 | M16: 2 | N16: 2 | O16: 1 | P16: 1 | Q16: 1 | R16: 2 | S16: =SUM(K16:R16) -> 14 | T16: =S16/40 -> 0.35 | U16: =IF(H16="Rendida ",IF('Resultados Individuales'!T16<49.5%,"Por Mejorar",IF('Resultados Individuales'!T16<64.5%,"Base",IF('Resultados Individuales'!T16<84.5%,"Satisfactorio","Óptimo"))),"No rendida o no válida") -> Por Mejorar | V16: El desempeño en las dos actividades evidencia un logro limitado de las competencias esperadas para el perfil intermedio de la carrera de Derecho, con importantes diferencias de nivel entre ambas. En la primera actividad, el estudiante demuestra una comprensión inicial de la institución del precario, pero incurre en confusiones conceptuales relevantes, en particular al no distinguir correctamente entre el contrato de compraventa y la relación jurídica entre la nueva dueña y la demandada. Su posicionamiento ético es pertinente, aunque superficial, y no incorpora categorías jurídicas avanzadas ni desarrolla con solidez el análisis crítico que se solicitaba. La correlación con la teoría de Finnis es básica y carece de profundidad académica. Como proyección de mejora, se sugiere profundizar los elementos copulativos del art. 2195 CC, enriquecer el análisis ético con nociones como justicia social y seguridad jurídica, y trabajar expresamente la relación con Finnis a un nivel doctrinario más consistente. Además, debe perfeccionar la presentación escrita formal para proyectar un estilo más profesional y riguroso. En la segunda actividad, las deficiencias son más graves, afectando dimensiones centrales de la evaluación. En la pregunta sobre enfoque de género, se confunden completamente conceptos, sustituyendo el análisis de género por una descripción de criterios vinculados al interés superior del niño, lo que impide cualquier reflexión significativa sobre desigualdades estructurales o interseccionalidad. Esto conlleva la omisión de aspectos críticos solicitados: no se identifican medidas específicas aplicables a mujeres, niñas y adolescentes, no se analiza cómo el proceso judicial puede reproducir o transformar desigualdades, y no se incorpora un enfoque interseccional. A ello se suman problemas severos de expresión escrita académica —frases extensas, confusas y errores ortográficos— que comprometen la claridad y calidad comunicativa. En la pregunta sobre debido proceso, no se desarrolla ningún estándar concreto, lo cual afecta gravemente el cumplimiento de la consigna. Si bien se observa la identificación de algunos elementos positivos, como la autonomía progresiva, la articulación interinstitucional y una referencia a cifras del SENAME 2016, estos son insuficientes para compensar las falencias conceptuales principales.
A17: 19829527 | B17: 2 | C17: DIEGO IGNACIO NAVARRO GUTIERREZ | D17: NAVARRO | E17: GUTIERREZ | F17: DIEGO IGNACIO | G17: Avance curricular suficiente o adecuado para evaluar ciclo básico | H17: Rendida | I17: 12.08.2025 | K17: 3 | L17: 4 | M17: 2 | N17: 3 | O17: 2 | P17: 2 | Q17: 3 | R17: 4 | S17: =SUM(K17:R17) -> 23 | T17: =S17/40 -> 0.575 | U17: =IF(H17="Rendida ",IF('Resultados Individuales'!T17<49.5%,"Por Mejorar",IF('Resultados Individuales'!T17<64.5%,"Base",IF('Resultados Individuales'!T17<84.5%,"Satisfactorio","Óptimo"))),"No rendida o no válida") -> Base | V17: El desempeño observado en las actividades muestra una base de conocimiento que permite avanzar, pero aún con importantes aspectos por mejorar para responder de manera adecuada a las competencias propias del perfil intermedio en Derecho.
A18: 19853952 | B18: K | C18: HÉCTOR MAXIMILIANO MORENO SALAZAR | D18: MORENO | E18: SALAZAR | F18: HÉCTOR MAXIMILIANO | S18: =SUM(K18:R18) -> 0 | T18: =S18/40 -> 0 | U18: =IF(H18="Rendida ",IF('Resultados Individuales'!T18<49.5%,"Por Mejorar",IF('Resultados Individuales'!T18<64.5%,"Base",IF('Resultados Individuales'!T18<84.5%,"Satisfactorio","Óptimo"))),"No rendida o no válida") -> No rendida o no válida | V18: En la primera actividad, se aprecia un esfuerzo por abordar la institución del precario, pero el análisis resulta incompleto y poco preciso. La argumentación carece de una línea lógica clara y no logra sostener conclusiones sólidas. Es necesario trabajar en la correcta identificación de los elementos normativos y en la estructuración del razonamiento jurídico, de modo que las ideas se presenten con mayor coherencia y claridad. Además, los problemas de redacción y ortografía afectan la presentación formal del trabajo y deben ser revisados cuidadosamente.
A19: 19903160 | B19: 0 | C19: POULETTE CONSTANZA FUENTEALBA GONZALEZ | D19: FUENTEALBA | E19: GONZALEZ | F19: POULETTE CONSTANZA | G19: Avance curricular suficiente o adecuado para evaluar ciclo básico | H19: No rendida | I19: no aplica | S19: =SUM(K19:R19) -> 0 | T19: =S19/40 -> 0 | U19: =IF(H19="Rendida ",IF('Resultados Individuales'!T19<49.5%,"Por Mejorar",IF('Resultados Individuales'!T19<64.5%,"Base",IF('Resultados Individuales'!T19<84.5%,"Satisfactorio","Óptimo"))),"No rendida o no válida") -> No rendida o no válida | V19: En la segunda actividad, se reconocen avances en la identificación de principios relevantes, como el derecho a ser oído de los NNA y la obligación de fundamentación judicial. Sin embargo, el análisis tiende a ser descriptivo y no logra alcanzar un nivel crítico ni de profundización. La perspectiva de género se incorpora de manera superficial y el uso de la terminología jurídica presenta imprecisiones que limitan la calidad del escrito. También se echa en falta una mayor referencia a medidas normativas concretas y a la forma en que estas buscan abordar desigualdades estructurales.
A20: 19954513 | B20: 2 | C20: EMILIA ELIZABETH JORQUERA CUEVAS | D20: JORQUERA | E20: CUEVAS | F20: EMILIA ELIZABETH | G20: Avance curricular suficiente o adecuado para evaluar ciclo básico | H20: No rendida | I20: no aplica | S20: =SUM(K20:R20) -> 0 | T20: =S20/40 -> 0 | U20: =IF(H20="Rendida ",IF('Resultados Individuales'!T20<49.5%,"Por Mejorar",IF('Resultados Individuales'!T20<64.5%,"Base",IF('Resultados Individuales'!T20<84.5%,"Satisfactorio","Óptimo"))),"No rendida o no válida") -> No rendida o no válida | V20: En términos generales, se recomienda fortalecer la argumentación jurídica, mejorar la precisión conceptual y trabajar en la claridad de la expresión escrita. Avanzar en estos aspectos permitirá que el desempeño sea más consistente y cercano a lo esperado en esta etapa de la formación.
A21: 20244309 | B21: 5 | C21: CONSTANZA JAVIERA MUÑOZ ADASME | D21: MUÑOZ | E21: ADASME | F21: CONSTANZA JAVIERA | G21: Avance curricular suficiente o adecuado para evaluar ciclo básico | H21: No rendida | I21: no aplica | S21: =SUM(K21:R21) -> 0 | T21: =S21/40 -> 0 | U21: =IF(H21="Rendida ",IF('Resultados Individuales'!T21<49.5%,"Por Mejorar",IF('Resultados Individuales'!T21<64.5%,"Base",IF('Resultados Individuales'!T21<84.5%,"Satisfactorio","Óptimo"))),"No rendida o no válida") -> No rendida o no válida
A22: 20391016 | B22: 9 | C22: DIEGO IGNACIO CORADA JULIO | D22: CORADA | E22: JULIO | F22: DIEGO IGNACIO | G22: Avance curricular suficiente o adecuado para evaluar ciclo básico | H22: Rendida | I22: 45758 | K22: 4 | L22: 3 | M22: 3 | N22: 4 | O22: 2 | P22: 3 | Q22: 2 | R22: 3 | S22: =SUM(K22:R22) -> 24 | T22: =S22/40 -> 0.6 | U22: =IF(H22="Rendida ",IF('Resultados Individuales'!T22<49.5%,"Por Mejorar",IF('Resultados Individuales'!T22<64.5%,"Base",IF('Resultados Individuales'!T22<84.5%,"Satisfactorio","Óptimo"))),"No rendida o no válida") -> Base | V22: El desempeño en ambas actividades refleja un manejo sólido de las competencias del perfil intermedio de Derecho, con un estilo argumentativo técnico y organizado, aunque aún con oportunidades de profundización normativa y de análisis crítico. En la primera actividad, se destaca un análisis sistemático y riguroso de la institución del precario: el estudiante desarrolla con claridad los tres requisitos del art. 2195 del Código Civil, incorporando una fundamentación técnica sobresaliente y un análisis fáctico detallado. Su posicionamiento ético es equilibrado, ya que contrasta los aspectos positivos y negativos de la sentencia, integrando adecuadamente nociones como la seguridad jurídica, aunque podría enriquecerse mediante el uso de categorías más específicas solicitadas en la pauta. La correlación con la teoría de Finnis es correcta al reconocer la centralidad del matrimonio como bien humano básico, pero requiere un mayor desarrollo académico de los elementos constitutivos (fides y procreación). El lenguaje jurídico es técnico, preciso y proyecta adecuada competencia profesional. La calidad formal es consistente, con errores de redacción menores que no afectan la claridad global del trabajo. En la segunda actividad, el estudiante identifica con precisión los principales mecanismos de participación de los NNA —audiencias adaptadas, obligación de fundamentar y la figura del curador ad litem—, vinculándolos de forma adecuada con la autonomía progresiva. La reflexión sobre desigualdades estructurales es correcta, destacando la reforma de los códigos civil y procesal y la incorporación explícita del interés superior del niño, junto con un lenguaje apropiado que integra tanto nociones procesales como constitucionales. No obstante, el análisis del enfoque de género carece de mayor profundidad normativa e interseccional: las referencias se limitan a menciones generales sobre corresponsabilidad parental sin desarrollarse en conexión con marcos internacionales ni con ejemplos específicos de medidas reforzadas.
A23: 20510143 | B23: 8 | C23: DIEGO BENJAMÍN ROJAS FLORES | D23: ROJAS | E23: FLORES | F23: DIEGO BENJAMÍN | G23: Avance curricular suficiente o adecuado para evaluar ciclo básico | H23: No aplica | I23: 45758 | J23: No aplica | S23: =SUM(K23:R23) -> 0 | T23: =S23/40 -> 0 | U23: =IF(H23="Rendida ",IF('Resultados Individuales'!T23<49.5%,"Por Mejorar",IF('Resultados Individuales'!T23<64.5%,"Base",IF('Resultados Individuales'!T23<84.5%,"Satisfactorio","Óptimo"))),"No rendida o no válida") -> No rendida o no válida
A24: 20550155 | B24: K | C24: JOSEFA MICHELLE JIMENEZ AROS | D24: JIMENEZ | E24: AROS | F24: JOSEFA MICHELLE | G24: Avance curricular suficiente o adecuado para evaluar ciclo básico | H24: Rendida | I24: 45758 | K24: 3 | L24: 3 | M24: 3 | N24: 3 | O24: 3 | P24: 4 | Q24: 3 | R24: 4 | S24: =SUM(K24:R24) -> 26 | T24: =S24/40 -> 0.65 | U24: =IF(H24="Rendida ",IF('Resultados Individuales'!T24<49.5%,"Por Mejorar",IF('Resultados Individuales'!T24<64.5%,"Base",IF('Resultados Individuales'!T24<84.5%,"Satisfactorio","Óptimo"))),"No rendida o no válida") -> Satisfactorio | V24: El desempeño en ambas actividades refleja un nivel competente y bien encaminado hacia la consolidación del perfil intermedio en Derecho, con un manejo adecuado del análisis normativo y ético, así como del lenguaje jurídico, aunque aún con oportunidades de profundización conceptual y técnica. En la primera actividad, el estudiante adopta posturas claras y consistentes frente a todas las preguntas, demostrando comprensión sólida de los elementos del precario al citar expresamente el art. 2195 del Código Civil. Se aprecia, además, un enfoque integral que incorpora consideraciones de género, derechos del niño y referencias normativas internacionales, como el Pacto de San José. Su análisis ético es apropiado, reconociendo aspectos de justicia social y estableciendo conexiones correctas entre la filosofía de Finnis y el razonamiento del tribunal en torno a los fines esenciales del matrimonio. El uso del lenguaje jurídico es adecuado y la calidad formal aceptable. Las áreas de mejora se concentran en profundizar el desarrollo técnico del análisis jurídico, incorporando explícitamente conceptos como interpretación extensiva, analogía y seguridad jurídica, así como en perfeccionar el uso de ciertas expresiones técnicas para proyectar un estilo más riguroso y sofisticado. En la segunda actividad, se observa un desempeño particularmente sólido en la dimensión social y contextual, destacando el análisis profundo de fenómenos relevantes (como la crisis del SENAME) y su conexión con la necesidad de reforma en materia de niñez y adolescencia. Se identifican medidas concretas con enfoque de género y se vinculan con tratados internacionales, lo que evidencia un manejo consciente de los estándares de derechos humanos. Asimismo, la reflexión interseccional es consistente, aunque podría ampliarse mediante la incorporación de más categorías sociales —como etnia o discapacidad— para alcanzar una mirada más completa. El uso del lenguaje jurídico es riguroso y proyecta un enfoque profesional claro.
A25: 20602647 | B25: 2 | C25: NATALIA ALEJANDRA ARAYA GARCÍA | D25: ARAYA | E25: GARCÍA | F25: NATALIA ALEJANDRA | S25: =SUM(K25:R25) -> 0 | T25: =S25/40 -> 0 | U25: =IF(H25="Rendida ",IF('Resultados Individuales'!T25<49.5%,"Por Mejorar",IF('Resultados Individuales'!T25<64.5%,"Base",IF('Resultados Individuales'!T25<84.5%,"Satisfactorio","Óptimo"))),"No rendida o no válida") -> No rendida o no válida
A26: 20678732 | B26: 5 | C26: RENATA LOBOS VILLANUEVA | D26: LOBOS | E26: VILLANUEVA | F26: RENATA | G26: Avance curricular suficiente o adecuado para evaluar ciclo básico | H26: No rendida | I26: no aplica | S26: =SUM(K26:R26) -> 0 | T26: =S26/40 -> 0 | U26: =IF(H26="Rendida ",IF('Resultados Individuales'!T26<49.5%,"Por Mejorar",IF('Resultados Individuales'!T26<64.5%,"Base",IF('Resultados Individuales'!T26<84.5%,"Satisfactorio","Óptimo"))),"No rendida o no válida") -> No rendida o no válida
A27: 20746309 | B27: 4 | C27: FELIPE IGNACIO NILO GUERRA | D27: NILO | E27: GUERRA | F27: FELIPE IGNACIO | G27: Avance curricular suficiente o adecuado para evaluar ciclo básico | H27: Rendida | I27: 45758 | K27: 3 | L27: 3 | M27: 3 | N27: 3 | O27: 1 | P27: 1 | Q27: 2 | R27: 3 | S27: =SUM(K27:R27) -> 19 | T27: =S27/40 -> 0.475 | U27: =IF(H27="Rendida ",IF('Resultados Individuales'!T27<49.5%,"Por Mejorar",IF('Resultados Individuales'!T27<64.5%,"Base",IF('Resultados Individuales'!T27<84.5%,"Satisfactorio","Óptimo"))),"No rendida o no válida") -> Por Mejorar | V27: El trabajo evidencia un desempeño heterogéneo entre las dos actividades, mostrando logros relevantes en el análisis del precario en la primera actividad, pero deficiencias críticas en la segunda, lo que refleja un nivel irregular frente a las competencias esperadas para el perfil intermedio de Derecho. En la primera actividad, el estudiante adopta posiciones claras y fundamentadas en todas las respuestas, identificando correctamente los tres requisitos copulativos del precario y argumentando de manera pertinente que entre demandante y demandada no existe vínculo jurídico, configurándose así el tercer requisito. El posicionamiento ético es coherente, valorando la protección familiar desde la dimensión constitucional (art. 1° inc. 2° de la Constitución) y reconociendo la importancia de la protección de Jeannette como usuaria del bien familiar. Se identifican apropiadamente las conexiones entre Finnis y el tribunal en torno al matrimonio como bien humano básico, relacionándolo de manera correcta con la protección constitucional. El lenguaje jurídico es básico pero adecuado, utilizando terminología pertinente y manteniendo una estructura clara con buena presentación formal. No obstante, las áreas de mejora se concentran en la falta de cita expresa del art. 2195 CC, la ausencia de desarrollo técnico más profundo de los conceptos, y en no haber incorporado nociones avanzadas solicitadas como interpretación extensiva, analogía y seguridad jurídica en el análisis ético-crítico, lo que limita el nivel de sofisticación conceptual del trabajo. En la segunda actividad, en cambio, se evidencian serias deficiencias en la comprensión del enfoque de género solicitado. La principal debilidad radica en la confusión conceptual entre el enfoque intersectorial (coordinación de organismos) y el enfoque de género (análisis de desigualdades estructurales que afectan a mujeres, niñas y adolescentes). Esta confusión impide un desarrollo adecuado de la reflexión, dejando sin abordar las desigualdades estructurales, sin incorporar perspectiva interseccional y con un análisis extremadamente limitado. Aunque el lenguaje jurídico empleado es básico pero apropiado, la brevedad y superficialidad de la respuesta reflejan una preparación insuficiente para el nivel de análisis crítico requerido en este tramo de la carrera.
A28: 20773727 | B28: 5 | C28: ALEJANDRA VICTORIA SANCHEZ JORQUERA | D28: SANCHEZ | E28: JORQUERA | F28: ALEJANDRA VICTORIA | G28: Avance curricular suficiente o adecuado para evaluar ciclo básico | H28: Rendida | I28: 45758 | K28: 3 | L28: 3 | M28: 3 | N28: 2 | O28: 1 | P28: 2 | Q28: 1 | R28: 3 | S28: =SUM(K28:R28) -> 18 | T28: =S28/40 -> 0.45 | U28: =IF(H28="Rendida ",IF('Resultados Individuales'!T28<49.5%,"Por Mejorar",IF('Resultados Individuales'!T28<64.5%,"Base",IF('Resultados Individuales'!T28<84.5%,"Satisfactorio","Óptimo"))),"No rendida o no válida") -> Por Mejorar | V28: El desempeño en las dos actividades presenta avances en la identificación de las instituciones jurídicas trabajadas, pero también limitaciones relevantes que dificultan un resultado sólido y consistente con el perfil intermedio de Derecho. En la primera actividad, el estudiante logra identificar correctamente los elementos básicos del precario, haciendo referencia apropiada al art. 2195 del Código Civil, y establece una conexión pertinente entre la filosofía de Finnis y el razonamiento del tribunal sobre los fundamentos del matrimonio. Además, su posicionamiento ético reconoce la complejidad del caso, diferenciando actuaciones de buena y mala fe. Sin embargo, se observan problemas conceptuales relevantes: la respuesta confunde la configuración con la procedencia del precario, llegando a argumentaciones contradictorias al reconocer derechos derivados del matrimonio pero al mismo tiempo concluir que procedería el precario. El análisis ético se mantiene en un nivel superficial, pues no incorpora los conceptos técnicos solicitados (como seguridad jurídica, analogía o interpretación extensiva). A esto se suman deficiencias en la precisión del lenguaje jurídico, con errores terminológicos, así como fallas en ortografía y redacción que restan formalidad y afectan la proyección profesional del texto. En la segunda actividad, el estudiante describe de manera adecuada los principales mecanismos de participación de los NNA (derecho a ser oído, audiencias adaptadas, fundamentación judicial y coordinación intersectorial), vinculándolos correctamente con principios como el interés superior del niño y la autonomía progresiva. No obstante, la respuesta omite por completo el análisis del enfoque de género y de la perspectiva interseccional, lo que limita el desarrollo crítico esperado. El tratamiento uniforme hacia los NNA invisibiliza desigualdades estructurales que afectan de manera diferenciada a niñas, adolescentes y mujeres. Asimismo, si bien el lenguaje jurídico es adecuado, la fundamentación se presenta incompleta al no recurrir a normas específicas ni a tratados internacionales. La incorporación de referencias expresas a la Ley 21.430, a la Convención sobre los Derechos del Niño y a artículos pertinentes del Código Civil y del Código de Procedimiento Civil habría robustecido de manera sustantiva la argumentación.
A29: 20778801 | B29: 5 | C29: FERNANDO ANDRÉS VERGARA BAEZA | D29: VERGARA | E29: BAEZA | F29: FERNANDO ANDRÉS | G29: Avance curricular suficiente o adecuado para evaluar ciclo básico | H29: Rendida | I29: 45758 | K29: 4 | L29: 4 | M29: 4 | N29: 4 | O29: 3 | P29: 3 | Q29: 2 | R29: 4 | S29: =SUM(K29:R29) -> 28 | T29: =S29/40 -> 0.7 | U29: =IF(H29="Rendida ",IF('Resultados Individuales'!T29<49.5%,"Por Mejorar",IF('Resultados Individuales'!T29<64.5%,"Base",IF('Resultados Individuales'!T29<84.5%,"Satisfactorio","Óptimo"))),"No rendida o no válida") -> Satisfactorio | V29: El trabajo presentado evidencia un nivel de excelencia en el manejo de las competencias del perfil intermedio de Derecho, con una sólida integración entre argumentación jurídica, análisis ético y reflexión social. En la primera actividad, el estudiante evalúa de manera sistemática todos los elementos del art. 2195 del Código Civil, construyendo una argumentación estructurada y pertinente sobre la procedencia del precario, en atención a la extinción del vínculo jurídico tras la compraventa del inmueble. Se aprecia una adecuada integración de nociones éticas, de justicia social y de garantías jurídicas, logrando una valoración equilibrada de la interpretación del tribunal. Destaca la profundidad con que se establece la conexión entre la filosofía de Finnis y el razonamiento judicial, lo que potencia el carácter académico de la reflexión. El uso del lenguaje jurídico es riguroso, preciso y profesional, y la expresión escrita resulta impecable, evidenciando claridad, coherencia y un estilo formal adecuado. Todo ello refleja un desempeño sobresaliente en el desarrollo de competencias analítico-jurídicas y de proyección profesional. En la segunda actividad, el estudiante describe con precisión los mecanismos de participación de NNA —audiencias adaptadas y obligación de fundamentar la consideración de su opinión—, articulándolos correctamente con los principios de autonomía progresiva e interés superior del niño. El análisis de género es pertinente, al destacar la protección reforzada en contextos de violencia intrafamiliar, junto con la importancia de la capacitación de operadores jurídicos y la coordinación intersectorial para abordar desigualdades. La reflexión sobre desigualdades estructurales es consistente, poniendo énfasis en el valor transformador de la motivación judicial y la efectiva ponderación de la voz de niños y adolescentes. Asimismo, aunque la perspectiva interseccional integra de manera correcta variables como edad y género, se recomienda ampliar este análisis incorporando otras categorías sociales, como clase, etnia o discapacidad, para robustecer la reflexión crítica. El lenguaje jurídico es riguroso, técnicamente fundamentado y apoyado en la Ley N° 21.430 y en estándares del debido proceso, lo que evidencia un claro nivel profesional.
A30: 20801460 | B30: 9 | C30: BENJAMÍN ENRIQUE JORQUERA LAGUNAS | D30: JORQUERA | E30: LAGUNAS | F30: BENJAMÍN ENRIQUE | G30: Avance curricular insuficiente para evaluar ciclo básico (no rinde EPI 2025) | H30: No aplica | I30: no aplica | S30: =SUM(K30:R30) -> 0 | T30: =S30/40 -> 0 | U30: =IF(H30="Rendida ",IF('Resultados Individuales'!T30<49.5%,"Por Mejorar",IF('Resultados Individuales'!T30<64.5%,"Base",IF('Resultados Individuales'!T30<84.5%,"Satisfactorio","Óptimo"))),"No rendida o no válida") -> No rendida o no válida
A31: 20824342 | B31: K | C31: JAVIERA BELÉN SÁNCHEZ PINILLA | D31: SÁNCHEZ | E31: PINILLA | F31: JAVIERA BELÉN | G31: Avance curricular suficiente o adecuado para evaluar ciclo básico | H31: No rendida | I31: no aplica | S31: =SUM(K31:R31) -> 0 | T31: =S31/40 -> 0 | U31: =IF(H31="Rendida ",IF('Resultados Individuales'!T31<49.5%,"Por Mejorar",IF('Resultados Individuales'!T31<64.5%,"Base",IF('Resultados Individuales'!T31<84.5%,"Satisfactorio","Óptimo"))),"No rendida o no válida") -> No rendida o no válida
A32: 20837817 | B32: 1 | C32: JAVIERA CAMILA AGUAYO OJEDA | D32: AGUAYO | E32: OJEDA | F32: JAVIERA CAMILA | G32: Avance curricular suficiente o adecuado para evaluar ciclo básico | H32: No rendida | I32: no aplica | S32: =SUM(K32:R32) -> 0 | T32: =S32/40 -> 0 | U32: =IF(H32="Rendida ",IF('Resultados Individuales'!T32<49.5%,"Por Mejorar",IF('Resultados Individuales'!T32<64.5%,"Base",IF('Resultados Individuales'!T32<84.5%,"Satisfactorio","Óptimo"))),"No rendida o no válida") -> No rendida o no válida
A33: 20844575 | B33: 8 | C33: MATÍAS IGNACIO FUENTES ÁVILA | D33: FUENTES | E33: ÁVILA | F33: MATÍAS IGNACIO | G33: Avance curricular suficiente o adecuado para evaluar ciclo básico | H33: Rendida | I33: 45882 | K33: 2 | L33: 2 | M33: 3 | N33: 2 | O33: 2 | P33: 3 | Q33: 2 | R33: 3 | S33: =SUM(K33:R33) -> 19 | T33: =S33/40 -> 0.475 | U33: =IF(H33="Rendida ",IF('Resultados Individuales'!T33<49.5%,"Por Mejorar",IF('Resultados Individuales'!T33<64.5%,"Base",IF('Resultados Individuales'!T33<84.5%,"Satisfactorio","Óptimo"))),"No rendida o no válida") -> Por Mejorar | V33: El desempeño evidenciado en las actividades refleja un progreso parcial, pero aún insuficiente para responder plenamente a las competencias del perfil intermedio en Derecho. Si bien se reconocen esfuerzos por abordar los contenidos, el trabajo requiere una mejora significativa en distintos planos.
A34: 20845895 | B34: 7 | C34: THIARE ISABEL LARA TRANGO | D34: LARA | E34: TRANGO | F34: THIARE ISABEL | G34: Avance curricular suficiente o adecuado para evaluar ciclo básico | H34: Rendida | I34: 45758 | K34: 3 | L34: 3 | M34: 4 | N34: 3 | O34: 1 | P34: 2 | Q34: 1 | R34: 3 | S34: =SUM(K34:R34) -> 20 | T34: =S34/40 -> 0.5 | U34: =IF(H34="Rendida ",IF('Resultados Individuales'!T34<49.5%,"Por Mejorar",IF('Resultados Individuales'!T34<64.5%,"Base",IF('Resultados Individuales'!T34<84.5%,"Satisfactorio","Óptimo"))),"No rendida o no válida") -> Base | V34: En la primera actividad, el análisis presentado carece de profundidad y se limita a enunciar aspectos generales sin llegar a un desarrollo técnico suficiente. La utilización de fuentes normativas resulta escasa y poco precisa, lo que afecta la solidez de la argumentación. Además, la falta de ejemplos o referencias jurisprudenciales debilita la capacidad de aplicar el conocimiento a situaciones concretas. A esto se suma la necesidad de trabajar en la organización del texto, ya que la exposición de ideas se percibe fragmentada y dificulta la comprensión.
A35: 20881046 | B35: 4 | C35: CHRISTOPHER CARLOS MANUEL OLIVERA JESÚS | D35: OLIVERA | E35: JESÚS | F35: CHRISTOPHER CARLOS MANUEL | G35: Avance curricular suficiente o adecuado para evaluar ciclo básico | H35: Rendida | I35: 45758 | K35: 4 | L35: 4 | M35: 4 | N35: 4 | O35: 4 | P35: 4 | Q35: 4 | R35: 4 | S35: =SUM(K35:R35) -> 32 | T35: =S35/40 -> 0.8 | U35: =IF(H35="Rendida ",IF('Resultados Individuales'!T35<49.5%,"Por Mejorar",IF('Resultados Individuales'!T35<64.5%,"Base",IF('Resultados Individuales'!T35<84.5%,"Satisfactorio","Óptimo"))),"No rendida o no válida") -> Satisfactorio | V35: En la segunda actividad, si bien se observa la intención de vincular el proyecto con principios jurídicos relevantes, el tratamiento de estos temas es superficial y no alcanza a proyectarse hacia un análisis crítico. El estudiante debe avanzar en el uso más riguroso de la terminología jurídica y en la diferenciación conceptual entre nociones cercanas, evitando confusiones que afectan el rigor académico. Igualmente, se recomienda profundizar en la perspectiva de género y en cómo las medidas normativas buscan corregir desigualdades estructurales, aspecto que en este caso aparece solo de manera enunciativa.
A36: 20946748 | B36: 8 | C36: FERNANDA JAVIERA ESCOBAR CONTRERAS | D36: ESCOBAR | E36: CONTRERAS | F36: FERNANDA JAVIERA | G36: Avance curricular suficiente o adecuado para evaluar ciclo básico | H36: No rendida | I36: no aplica | S36: =SUM(K36:R36) -> 0 | T36: =S36/40 -> 0 | U36: =IF(H36="Rendida ",IF('Resultados Individuales'!T36<49.5%,"Por Mejorar",IF('Resultados Individuales'!T36<64.5%,"Base",IF('Resultados Individuales'!T36<84.5%,"Satisfactorio","Óptimo"))),"No rendida o no válida") -> No rendida o no válida | V36: De manera general, se sugiere trabajar en la precisión del lenguaje, en el fortalecimiento de la argumentación mediante fundamentos normativos y doctrinarios, y en la capacidad de articular un análisis crítico y aplicado, que supere el nivel descriptivo y responda a las exigencias propias del estudio del Derecho
A37: 20965094 | B37: 0 | C37: JOSÉ DOMINGO BLANCO CASABONA | D37: BLANCO | E37: CASABONA | F37: JOSÉ DOMINGO | G37: Avance curricular suficiente o adecuado para evaluar ciclo básico | H37: Rendida | I37: 45758 | K37: 3 | L37: 3 | M37: 4 | N37: 3 | O37: 2 | P37: 2 | Q37: 2 | R37: 2 | S37: =SUM(K37:R37) -> 21 | T37: =S37/40 -> 0.525 | U37: =IF(H37="Rendida ",IF('Resultados Individuales'!T37<49.5%,"Por Mejorar",IF('Resultados Individuales'!T37<64.5%,"Base",IF('Resultados Individuales'!T37<84.5%,"Satisfactorio","Óptimo"))),"No rendida o no válida") -> Base | V37: El desempeño del estudiante en ambas actividades evidencia buen manejo conceptual y la capacidad de formular argumentos jurídicos pertinentes, aunque con diferencias de solidez entre la primera y la segunda actividad. En la primera actividad, se aprecia un dominio correcto de la institución del precario, desarrollando de manera sistemática los tres requisitos del art. 2195 CC y articulando coherentemente la argumentación respecto de su procedencia. El análisis ético es pertinente, con reflexiones interesantes acerca de la evolución del matrimonio como institución social, aunque podría enriquecerse con categorías jurídicas más específicas como seguridad jurídica o correcta aplicación del derecho. Destaca positivamente la correlación con Finnis, la cual se presenta con profundidad académica, al desarrollar los elementos constitutivos del matrimonio (fides y procreación) y proyectarlos en el considerando judicial. El uso del lenguaje jurídico es adecuado y emplea terminología técnica suficiente. No obstante, se recomienda perfeccionar la cita normativa (mención expresa del art. 2195 CC), mantener un registro formal más uniforme y atender a pequeños errores tipográficos que afectan la pulcritud formal del texto. En la segunda actividad, el análisis muestra avances en la identificación de elementos centrales del proyecto de ley, como el derecho a ser oído y la participación activa de los NNA, estableciendo vínculos con fenómenos sociales relevantes como los abusos en el sistema de protección infantil y el impacto del estallido social. También se reconoce un enfoque creativo al relacionar las “circunstancias particulares” con la necesidad de un análisis de género, lo que refleja capacidad crítica. Sin embargo, se evidencian limitaciones importantes: las respuestas son breves, el lenguaje utilizado se acerca a lo coloquial en lugar de mantener precisión técnica, se omite el desarrollo de nociones claves como la autonomía progresiva, y la perspectiva interseccional se aborda superficialmente. Esto reduce la solidez del trabajo a nivel normativo y crítico. Para mejorar, se sugiere fortalecer el uso del lenguaje jurídico especializado, ampliar el desarrollo analítico hasta cubrir la extensión exigida, integrar de manera más sistemática marcos teóricos como la interseccionalidad, e incorporar explicaciones apoyadas en la Ley N° 21.430, la Convención sobre los Derechos del Niño y marcos normativos conexos.
A38: 20972461 | B38: 8 | C38: PAULA FABIANA VILLEGAS RIQUELME | D38: VILLEGAS | E38: RIQUELME | F38: PAULA FABIANA | G38: Avance curricular suficiente o adecuado para evaluar ciclo básico | H38: Rendida | I38: 45758 | K38: 4 | L38: 3 | M38: 3 | N38: 4 | O38: 2 | P38: 2 | Q38: 2 | R38: 3 | S38: =SUM(K38:R38) -> 23 | T38: =S38/40 -> 0.575 | U38: =IF(H38="Rendida ",IF('Resultados Individuales'!T38<49.5%,"Por Mejorar",IF('Resultados Individuales'!T38<64.5%,"Base",IF('Resultados Individuales'!T38<84.5%,"Satisfactorio","Óptimo"))),"No rendida o no válida") -> Base | V38: El desempeño en ambas actividades refleja un avance consistente en el manejo de análisis jurídico y en la construcción de argumentos, destacando mayor solidez en la primera actividad que en la segunda. En la primera actividad, la estudiante demuestra un análisis jurídico sólido y bien estructurado, caracterizado por la precisión técnica y la claridad argumentativa. La evaluación de los elementos del precario se desarrolla de forma sistemática y convincente, particularmente al identificar la insuficiencia de supuestos no probados como fundamento para rechazar la acción. Se observa un dominio claro del lenguaje jurídico técnico y la capacidad de integrar consideraciones tanto procesales como sustantivas. Asimismo, la crítica a la decisión del tribunal se encuentra bien fundamentada, al incorporar instituciones relevantes como la del bien familiar. La relación establecida entre Finnis y el considerando judicial es correcta y pertinente, aunque podría haber alcanzado mayor desarrollo desde la perspectiva filosófica. En lo formal, la expresión escrita destaca por su claridad, orden y precisión, proyectando las competencias esperadas para el perfil intermedio con un desempeño claramente sobresaliente. En la segunda actividad, la estudiante identifica adecuadamente los mecanismos de participación de los NNA —derecho a ser oído en audiencias adaptadas y obligación de fundamentar su opinión— vinculándolos tanto al interés superior como a la autonomía progresiva. No obstante, el análisis de género resulta superficial, al no especificar medidas normativas concretas ni aludir a estándares internacionales relevantes. De igual manera, la reflexión sobre desigualdades estructurales y la perspectiva interseccional se presentan limitadas, reducidas a referencias de articulación interinstitucional, sin un análisis profundo sobre la interacción de variables sociales como género, clase, etnia o situación socioeconómica. El uso del lenguaje jurídico es correcto y pertinente, aunque el rigor del argumento se vería reforzado con citas expresas a artículos de la Ley 21.430, la Convención sobre los Derechos del Niño o el Código de Procedimiento Civil.
A39: 21003644 | B39: K | C39: NICOLÁS JESÚS CONTRERAS CONTRERAS | D39: CONTRERAS | E39: CONTRERAS | F39: NICOLÁS JESÚS | H39: No aplica | I39: no aplica | S39: =SUM(K39:R39) -> 0 | T39: =S39/40 -> 0 | U39: =IF(H39="Rendida ",IF('Resultados Individuales'!T39<49.5%,"Por Mejorar",IF('Resultados Individuales'!T39<64.5%,"Base",IF('Resultados Individuales'!T39<84.5%,"Satisfactorio","Óptimo"))),"No rendida o no válida") -> No rendida o no válida
A40: 21038875 | B40: 3 | C40: GONZALO CRISTÓBAL PEDRAZA CID | D40: PEDRAZA | E40: CID | F40: GONZALO CRISTÓBAL | G40: Avance curricular suficiente o adecuado para evaluar ciclo básico | H40: Rendida | I40: 45758 | K40: 4 | L40: 4 | M40: 4 | N40: 4 | O40: 3 | P40: 3 | Q40: 2 | R40: 3 | S40: =SUM(K40:R40) -> 27 | T40: =S40/40 -> 0.675 | U40: =IF(H40="Rendida ",IF('Resultados Individuales'!T40<49.5%,"Por Mejorar",IF('Resultados Individuales'!T40<64.5%,"Base",IF('Resultados Individuales'!T40<84.5%,"Satisfactorio","Óptimo"))),"No rendida o no válida") -> Satisfactorio | V40: El trabajo evidencia un nivel muy sólido de dominio técnico y argumentativo, con un desempeño particularmente consistente en la primera actividad y un desarrollo igualmente destacado en la segunda, aunque con algunos aspectos que aún pueden potenciarse. En la primera actividad, se observa un análisis exhaustivo y técnicamente riguroso de la acción de precario. La estudiante desarrolla con precisión los tres requisitos copulativos del art. 2195 CC y argumenta con claridad que la compra del inmueble en 2018 no incluyó acuerdos con la demandada, configurándose así una tenencia precaria. El razonamiento combina de manera acertada los elementos institucionales con las exigencias procesales, lo que refleja pleno dominio de la institución. Su posicionamiento ético es particularmente consistente, pues incorpora de manera explícita conceptos técnicos como seguridad jurídica, interpretación extensiva, analogía e incorrecta aplicación del derecho, concluyendo con fundamento que la sentencia constituye una incorrecta aplicación normativa dado que el art. 2195 no contempla excepciones basadas en vínculos familiares. Además, integra una correlación conceptual refinada con Finnis, distinguiendo con claridad que mientras este filósofo presenta el matrimonio como fundamento ético-filosófico de la realización humana, el tribunal lo utilizó como argumento jurídico, diferenciación que enriquece la proyección analítica. La presentación formal, organización lógica y precisión del lenguaje refuerzan una proyección profesional de alto nivel. En la segunda actividad, se describen con acierto los mecanismos de participación de los NNA —derecho a ser oídos, audiencias adaptadas y fundamentación obligatoria de la opinión—, vinculándolos a la autonomía progresiva y al interés superior del niño. El análisis de género también es adecuado, destacando medidas como la protección reforzada en casos de violencia intrafamiliar, la inclusión de curadores ad litem especializados y la coordinación interinstitucional con el Ministerio de la Mujer. La reflexión sobre desigualdades estructurales es consistente, proponiendo un rol transformador para los tribunales de familia. No obstante, la perspectiva interseccional podría profundizarse, incorporando explicitamente categorías como clase, etnia o discapacidad para ampliar el análisis crítico. El lenguaje jurídico es técnico, preciso y respaldado con referencias normativas internacionales, lo que refleja comprensión del rol del abogado/a en la defensa de los derechos de la niñez y adolescencia bajo estándares de debido proceso.
A41: 21051415 | B41: 5 | C41: FRANKO ALEXIS ROJAS BRAVO | D41: ROJAS | E41: BRAVO | F41: FRANKO ALEXIS | G41: Interrupción voluntaria (no rinde EPI 2025) | S41: =SUM(K41:R41) -> 0 | T41: =S41/40 -> 0 | U41: =IF(H41="Rendida ",IF('Resultados Individuales'!T41<49.5%,"Por Mejorar",IF('Resultados Individuales'!T41<64.5%,"Base",IF('Resultados Individuales'!T41<84.5%,"Satisfactorio","Óptimo"))),"No rendida o no válida") -> No rendida o no válida
A42: 21062201 | B42: 2 | C42: JUANA DANIELA CANIUMIL MARIPIL | D42: CANIUMIL | E42: MARIPIL | F42: JUANA DANIELA | G42: Avance curricular suficiente o adecuado para evaluar ciclo básico | H42: Rendida | I42: 45758 | K42: 4 | L42: 4 | M42: 4 | N42: 4 | O42: 3 | P42: 3 | Q42: 3 | R42: 3 | S42: =SUM(K42:R42) -> 28 | T42: =S42/40 -> 0.7 | U42: =IF(H42="Rendida ",IF('Resultados Individuales'!T42<49.5%,"Por Mejorar",IF('Resultados Individuales'!T42<64.5%,"Base",IF('Resultados Individuales'!T42<84.5%,"Satisfactorio","Óptimo"))),"No rendida o no válida") -> Satisfactorio | V42: El desempeño del estudiante refleja un dominio sólido del análisis jurídico y ético, con gran capacidad de argumentación normativa y de correlación teórica, especialmente en la primera actividad, así como un buen manejo de contextos sociales y normativos en la segunda. En la primera actividad, el análisis del precario es sistemático y riguroso, desarrollando meticulosamente los tres requisitos del art. 2195 del Código Civil con una fundamentación técnica clara que incorpora acertadamente nociones de títulos traslaticios de dominio y perfeccionamiento registral. El posicionamiento ético alcanza un nivel avanzado, al reflexionar sobre la tensión entre la interpretación judicial y el derecho positivo, integrando categorías centrales como seguridad jurídica y protección del derecho de propiedad. La correlación con Finnis es académicamente sobresaliente, al desarrollar de manera precisa los dos elementos constitutivos del matrimonio (fides y procreación) e incorporarlos de forma consistente al considerando quinto de la sentencia. El lenguaje es técnico, preciso y proyecta competencias profesionales en un nivel elevado. Como aspecto de mejora, se sugiere corregir erratas menores y perfeccionar la construcción sintáctica en ciertos pasajes, lo que contribuiría a una exposición aún más acabada. En la segunda actividad, se presenta un análisis sólido y comprehensivo del proyecto de ley, destacando la vinculación con fenómenos sociales recientes como la crisis del SENAME y los problemas relacionados con redes de trata de personas, lo que denota sensibilidad crítica frente a la realidad social. El uso del lenguaje jurídico es adecuado y preciso, con citas correctas de artículos constitucionales y conceptos procesales. El enfoque de género se aborda de forma apropiada, diferenciando necesidades de protección entre niñas y niños y subrayando la relevancia de la coordinación intersectorial. No obstante, para alcanzar un nivel óptimo de argumentación crítica, sería recomendable profundizar en normas internacionales vinculantes en materia de género, como la CEDAW y la Convención de Belém do Pará, además de desarrollar más el análisis sobre cómo ciertos esquemas del proceso judicial tradicional pueden reproducir desigualdades estructurales, en lugar de corregirlas.
A43: 21073491 | B43: 0 | C43: SOFIA VALENTINA MENESES ROMERO | D43: MENESES | E43: ROMERO | F43: SOFIA VALENTINA | G43: Avance curricular suficiente o adecuado para evaluar ciclo básico | H43: No rendida | I43: no aplica | J43: Justifica | S43: =SUM(K43:R43) -> 0 | T43: =S43/40 -> 0 | U43: =IF(H43="Rendida ",IF('Resultados Individuales'!T43<49.5%,"Por Mejorar",IF('Resultados Individuales'!T43<64.5%,"Base",IF('Resultados Individuales'!T43<84.5%,"Satisfactorio","Óptimo"))),"No rendida o no válida") -> No rendida o no válida
A44: 21081948 | B44: 7 | C44: VICENTE JAVIER PINO LOVERA | D44: PINO | E44: LOVERA | F44: VICENTE JAVIER | G44: Avance curricular suficiente o adecuado para evaluar ciclo básico | H44: Rendida | I44: 45758 | K44: 3 | L44: 3 | M44: 4 | N44: 3 | O44: 2 | P44: 2 | Q44: 2 | R44: 2 | S44: =SUM(K44:R44) -> 21 | T44: =S44/40 -> 0.525 | U44: =IF(H44="Rendida ",IF('Resultados Individuales'!T44<49.5%,"Por Mejorar",IF('Resultados Individuales'!T44<64.5%,"Base",IF('Resultados Individuales'!T44<84.5%,"Satisfactorio","Óptimo"))),"No rendida o no válida") -> Base | V44: El trabajo evidencia un desempeño heterogéneo: mientras la primera actividad alcanza un nivel avanzado en argumentación, precisión conceptual y correlación teórica, la segunda presenta desarrollos más básicos y con falta de rigor técnico. En la primera actividad, la estudiante adopta de manera clara una postura contraria a la interpretación del tribunal, citando expresamente el art. 2195 del Código Civil y argumentando con solidez la ausencia de vínculo jurídico vigente que impida configurar el precario. Su posicionamiento crítico es pertinente, al enfatizar que la decisión judicial “debilita la seguridad jurídica” y que debe prevalecer el respeto a las fuentes formales del derecho. El análisis ético-jurídico se integra con coherencia, mostrando reflexión sobre el rol del derecho positivo frente a apreciaciones valorativas. El lenguaje jurídico empleado es básico, pero correcto y pertinente, acompañado de una estructura clara y formalmente aceptable. El mayor aporte se observa en la tercera pregunta, donde la estudiante desarrolla un análisis profundo de la correlación entre Finnis y el tribunal, distinguiendo enfoques y destacando que ambos otorgan centralidad al vínculo matrimonial, aunque desde perspectivas distintas: el matrimonio como bien humano básico complejo (Finnis) frente a su definición como institución fundamental en la sociedad (tribunal). Esta correlación conceptual exhibe un nivel de análisis refinado y sofisticado, consolidando un desempeño de alto nivel en esta actividad. En la segunda actividad, se describen los mecanismos de participación de los NNA (derecho a ser oídos y motivación judicial), pero la explicación de su articulación con la autonomía progresiva carece de suficiente precisión técnica. El análisis de género reconoce la vulnerabilidad diferenciada de las niñas, pero queda en un plano descriptivo, sin profundizar en medidas normativas específicas contempladas en el proyecto. La reflexión sobre desigualdades estructurales es igualmente superficial, limitada a la coordinación intersectorial, sin problematizar el potencial transformador del proceso judicial en la reducción de dichas desigualdades. La perspectiva interseccional está apenas esbozada, sin un desarrollo integral que articule categorías como edad, género y condición socioeconómica. Además, el uso del lenguaje jurídico presenta imprecisiones y la argumentación carece de citas concretas a normas clave como la Ley 21.430, la Convención sobre los Derechos del Niño o estándares internacionales en derechos de la niñez.
A45: 21082081 | B45: 7 | C45: ÁLVARO ESTEBAN BÓRQUEZ ESPEJO | D45: BÓRQUEZ | E45: ESPEJO | F45: ÁLVARO ESTEBAN | G45: Avance curricular suficiente o adecuado para evaluar ciclo básico | H45: Rendida | I45: 45758 | K45: 2 | L45: 3 | M45: 2 | N45: 2 | O45: 2 | P45: 2 | Q45: 2 | R45: 1 | S45: =SUM(K45:R45) -> 16 | T45: =S45/40 -> 0.4 | U45: =IF(H45="Rendida ",IF('Resultados Individuales'!T45<49.5%,"Por Mejorar",IF('Resultados Individuales'!T45<64.5%,"Base",IF('Resultados Individuales'!T45<84.5%,"Satisfactorio","Óptimo"))),"No rendida o no válida") -> Por Mejorar | V45: El desempeño en ambas actividades refleja una comprensión inicial pero todavía limitada de las instituciones jurídicas en análisis, con algunos avances conceptuales pero con debilidades importantes en el rigor técnico, la profundidad crítica y el uso del lenguaje académico-jurídico. En la primera actividad, se aprecia que el estudiante adopta una posición clara desde una perspectiva positivista (cercana a un enfoque “kelseniano”), lo que constituye un punto de partida conceptualmente interesante. Además, reconoce elementos centrales de la figura del precario y la dimensión ética implícita en la sentencia. No obstante, el análisis carece de la sistematicidad necesaria: los requisitos del art. 2195 CC no se desarrollan de manera ordenada ni completa, la articulación de la argumentación es insuficiente y la correlación con Finnis resulta muy superficial, sin precisar los dos elementos estructurales de su visión del matrimonio (fides y procreación). Asimismo, el uso del lenguaje jurídico presenta múltiples imprecisiones y la calidad formal de la redacción se ve afectada por errores ortográficos y de construcción sintáctica. Para avanzar, resulta fundamental estructurar el análisis paso a paso en función de los requisitos del precario, enriquecer la dimensión ética con conceptos técnicos específicos (seguridad jurídica, correcta aplicación del derecho, analogía, interpretación extensiva), profundizar el diálogo con Finnis y utilizar un lenguaje más técnico y formal que proyecte profesionalismo. En la segunda actividad, las respuestas son demasiado breves y permanecen en un nivel superficial, sin llegar a desarrollar adecuadamente lo solicitado en la rúbrica. Aunque se identifican algunos conceptos básicos —como el derecho a ser oído o medidas de protección en violencia intrafamiliar—, no se explican en profundidad ni se vinculan sólidamente con principios como la autonomía progresiva, el enfoque de género o la interseccionalidad. El uso del lenguaje es informal e inapropiado para un contexto académico de Derecho, y no se logra proyectar comprensión sobre el rol profesional del abogado en la defensa de derechos. Para alcanzar el nivel esperado, se debe fortalecer la escritura académica, ampliar el vocabulario jurídico técnico, incorporar referencias expresas a normas relevantes (Ley 21.430, Convención sobre los Derechos del Niño, CEDAW, Belém do Pará) y desarrollar con mayor profundidad el análisis crítico sobre desigualdades estructurales y fenómenos sociales contemporáneos.
A46: 21122157 | B46: 7 | C46: SERGIO ALEJANDRO GONZÁLEZ DOMÍNGUEZ | D46: GONZÁLEZ | E46: DOMÍNGUEZ | F46: SERGIO ALEJANDRO | G46: Avance curricular suficiente o adecuado para evaluar ciclo básico | H46: Rendida | I46: 45758 | K46: 2 | L46: 2 | M46: 3 | N46: 2 | O46: 3 | P46: 2 | Q46: 3 | R46: 2 | S46: =SUM(K46:R46) -> 19 | T46: =S46/40 -> 0.475 | U46: =IF(H46="Rendida ",IF('Resultados Individuales'!T46<49.5%,"Por Mejorar",IF('Resultados Individuales'!T46<64.5%,"Base",IF('Resultados Individuales'!T46<84.5%,"Satisfactorio","Óptimo"))),"No rendida o no válida") -> Por Mejorar
A47: 21124590 | B47: 5 | C47: CAMILA SCARLETT GONZÁLEZ PEÑA | D47: GONZÁLEZ | E47: PEÑA | F47: CAMILA SCARLETT | G47: Avance curricular suficiente o adecuado para evaluar ciclo básico | H47: Rendida | I47: 45758 | K47: 2 | L47: 3 | M47: 3 | N47: 3 | O47: 2 | P47: 2 | Q47: 1 | R47: 3 | S47: =SUM(K47:R47) -> 19 | T47: =S47/40 -> 0.475 | U47: =IF(H47="Rendida ",IF('Resultados Individuales'!T47<49.5%,"Por Mejorar",IF('Resultados Individuales'!T47<64.5%,"Base",IF('Resultados Individuales'!T47<84.5%,"Satisfactorio","Óptimo"))),"No rendida o no válida") -> Por Mejorar | V47: El desempeño del estudiante evidencia avances relevantes en la toma de postura argumentativa y en el manejo básico del lenguaje jurídico, aunque persisten carencias importantes en la comprensión técnica y en la profundidad crítica que deben trabajarse de manera prioritaria. En la primera actividad, se valora positivamente la claridad al adoptar posiciones frente a las preguntas planteadas y el reconocimiento de la interpretación extensiva del tribunal, así como la identificación de la tensión existente entre criterios legales estrictos y consideraciones éticas o familiares. Del mismo modo, el análisis sobre la protección del matrimonio y la correlación con Finnis es correcto, estableciendo vínculos pertinentes entre el matrimonio como bien humano básico y como institución fundamental. El lenguaje jurídico utilizado es en general apropiado y la calidad formal del escrito resulta aceptable. Sin embargo, se evidencia debilidad técnica importante en la comprensión de los elementos del precario, especialmente en confusiones conceptuales notorias como equiparar "servicio particular" con ocupación familiar, y malinterpretar la noción de "tenencia", lo que afecta de forma sustancial la solidez de la argumentación. Para avanzar hacia niveles más altos, es necesario estudiar con mayor detenimiento los tres requisitos copulativos del art. 2195 CC y aplicarlos de forma sistemática, garantizando precisión conceptual y rigor jurídico en el análisis. En la segunda actividad, se observa un trabajo más consistente, describiendo adecuadamente los mecanismos de participación activa de los NNA y la obligación de motivación judicial, con un uso de lenguaje jurídico más riguroso. No obstante, el análisis en torno al enfoque de género y a las desigualdades estructurales queda limitado, pues no se detallan las medidas concretas propuestas ni se citan tratados o estándares internacionales relevantes. Asimismo, la reflexión sobre la perspectiva interseccional no se desarrolla de manera efectiva. Para perfeccionar este aspecto, es recomendable vincular el análisis con artículos específicos del proyecto, citar instrumentos internacionales como la CEDAW y la Convención sobre los Derechos del Niño, y explicar cómo interactúan distintas categorías sociales (género, edad, clase, etnia, discapacidad) en la práctica judicial.
A48: 21129198 | B48: 2 | C48: JUAN IGNACIO VARGAS HUERAO | D48: VARGAS | E48: HUERAO | F48: JUAN IGNACIO | G48: Avance curricular suficiente o adecuado para evaluar ciclo básico | H48: Rendida | I48: 45842 | K48: 2 | L48: 2 | M48: 3 | N48: 2 | O48: 3 | P48: 3 | Q48: 3 | R48: 4 | S48: =SUM(K48:R48) -> 22 | T48: =S48/40 -> 0.55 | U48: =IF(H48="Rendida ",IF('Resultados Individuales'!T48<49.5%,"Por Mejorar",IF('Resultados Individuales'!T48<64.5%,"Base",IF('Resultados Individuales'!T48<84.5%,"Satisfactorio","Óptimo"))),"No rendida o no válida") -> Base | V48: El desempeño del estudiante muestra un nivel dispar entre ambas actividades: mientras la primera refleja un conocimiento inicial pero con importantes deficiencias en desarrollo y forma, la segunda alcanza un estándar sólido, con argumentación clara y uso riguroso del lenguaje jurídico. En la primera actividad, el estudiante demuestra conocimiento de los conceptos básicos y cita correctamente el art. 2195 CC, además de establecer la relación entre Finnis y el considerando judicial. Sin embargo, el análisis carece de claridad y profundidad: la argumentación sobre la procedencia del precario resulta contradictoria y confusa, y el tratamiento de los aspectos éticos se mantiene en un nivel demasiado general. Las mayores debilidades se encuentran en la expresión escrita, con errores de redacción, gramática y construcción que dificultan la comprensión. Para avanzar, se recomienda fortalecer las habilidades de argumentación jurídica, organizar de forma sistemática los tres requisitos del precario, enriquecer el análisis ético con categorías técnicas (seguridad jurídica, correcta aplicación del derecho, etc.), y mejorar sustancialmente la redacción y el uso del lenguaje técnico-jurídico. En la segunda actividad, el trabajo alcanza un nivel mucho más consistente. Se detallan correctamente los mecanismos de participación de los NNA —derecho a ser oído, audiencias adaptadas y motivación fundada— vinculándolos con la autonomía progresiva y el interés superior del niño. El enfoque de género se desarrolla adecuadamente, destacando la coordinación intersectorial para enfrentar la violencia intrafamiliar y las desigualdades de género mediante el trabajo conjunto de instituciones como SENDA y el Ministerio de Desarrollo Social. Asimismo, la reflexión sobre desigualdades estructurales es pertinente, al subrayar la necesidad de que el tribunal articule respuestas frente a pobreza, exclusión y violencia. Se valora especialmente la incorporación de una perspectiva interseccional real, reconociendo la confluencia de género, edad y condición socioeconómica, y enfatizando un enfoque colaborativo. El lenguaje jurídico es riguroso y apoyado en normas relevantes, proyectando una buena comprensión del rol del abogado/a y de los estándares del debido proceso.
A49: 21132470 | B49: 8 | C49: CATTARI BELÉN SALOMÉ ARDATI PIZARRO | D49: ARDATI | E49: PIZARRO | F49: CATTARI BELÉN SALOMÉ | G49: Avance curricular suficiente o adecuado para evaluar ciclo básico | H49: Rendida | I49: 45758 | K49: 4 | L49: 4 | M49: 4 | N49: 4 | O49: 4 | P49: 4 | Q49: 4 | R49: 4 | S49: =SUM(K49:R49) -> 32 | T49: =S49/40 -> 0.8 | U49: =IF(H49="Rendida ",IF('Resultados Individuales'!T49<49.5%,"Por Mejorar",IF('Resultados Individuales'!T49<64.5%,"Base",IF('Resultados Individuales'!T49<84.5%,"Satisfactorio","Óptimo"))),"No rendida o no válida") -> Satisfactorio | V49: El desempeño del estudiante en ambas actividades es sobresaliente, evidenciando un dominio técnico, crítico y reflexivo que supera ampliamente lo esperado para el perfil intermedio de Derecho. En la primera actividad, se aprecia un conocimiento excelente de la institución del precario. El estudiante articula con precisión los tres requisitos del art. 2195 CC, fundamentando por qué procede la acción frente a la nueva dueña. El análisis es sólido y equilibrado, pues integra no solo el derecho positivo sino también nociones jurídicas avanzadas como justicia social, justicia material e interpretación extensiva, demostrando madurez en la argumentación ética y jurídica. La correlación con Finnis es académicamente rigurosa: identifica y desarrolla ambos elementos constitutivos del matrimonio (fides y procreación) y los vincula coherentemente con el considerando judicial, evidenciando gran capacidad de relación entre teoría y praxis. El lenguaje jurídico es preciso, técnico y profesional. La única área menor a perfeccionar se encuentra en aspectos formales de redacción, principalmente corrección de erratas y detalles ortográficos. En la segunda actividad, el nivel alcanzado es igualmente sobresaliente. Las respuestas reflejan un análisis crítico y transformador del proyecto de ley, que trasciende la mera descripción normativa y se adentra en reflexiones estructurales sobre el rol del proceso judicial en la sociedad. Destaca el desarrollo del enfoque de género e interseccional, donde el estudiante articula brillantemente que “las relaciones familiares no son neutrales al género” y reconoce los contextos reales de discriminación que buscan ser abordados. La perspectiva interseccional es auténtica y profunda, integrando variables como edad, género y dependencia económica/emocional, y vinculándolas con medidas normativas específicas del proyecto. El lenguaje jurídico utilizado es avanzado y técnico, empleando con maestría expresiones como “autonomía progresiva”, “participación efectiva”, “fundamentos jurídicos y fácticos” y “garantías procesales”, lo cual refleja un dominio superior. La contextualización histórica resulta precisa y pertinente, al identificar como motivaciones la crisis del SENAME y el estallido social de 2019. Asimismo, la vinculación con el debido proceso es modélica, citando expresamente el artículo 19 N°3 de la Constitución y la Convención sobre los Derechos del Niño, demostrando comprensión cabal del diálogo entre normas nacionales e internacionales.
A50: 21138217 | B50: 1 | C50: MARÍA JOSÉ CHUÑIL OJEDA | D50: CHUÑIL | E50: OJEDA | F50: MARÍA JOSÉ | G50: Avance curricular suficiente o adecuado para evaluar ciclo básico | H50: Rendida | I50: 45758 | K50: 4 | L50: 1 | M50: 1 | N50: 2 | O50: 2 | P50: 2 | Q50: 2 | R50: 3 | S50: =SUM(K50:R50) -> 17 | T50: =S50/40 -> 0.425 | U50: =IF(H50="Rendida ",IF('Resultados Individuales'!T50<49.5%,"Por Mejorar",IF('Resultados Individuales'!T50<64.5%,"Base",IF('Resultados Individuales'!T50<84.5%,"Satisfactorio","Óptimo"))),"No rendida o no válida") -> Por Mejorar | V50: El desempeño del estudiante muestra fortalezas técnicas importantes en ciertos aspectos, pero debilidades notorias en la dimensión ética y crítica, lo que genera un resultado desigual entre las dos actividades. En la primera actividad, se aprecia un dominio sólido de la institución del precario, con un desarrollo sistemático de los tres requisitos del art. 2195 del CC y una fundamentación rigurosa que se apoya en el análisis del caso concreto. Este es, sin duda, el punto más fuerte del trabajo. No obstante, se evidencian carencias significativas en la dimensión ética y académica: la reflexión sobre justicia social y la tensión entre interpretación judicial y derecho positivo queda en un nivel superficial, con menciones generales sin un desarrollo profundo. Asimismo, la correlación con Finnis es insuficiente, al limitarse a resaltar la importancia del matrimonio sin elaborar sobre sus elementos constitutivos ni establecer una conexión académica robusta con el razonamiento judicial. El uso del lenguaje jurídico es correcto, pero podría alcanzar mayor sofisticación mediante la incorporación de terminología más técnica. En la segunda actividad, el estudiante comprende adecuadamente los principales mecanismos de participación de niños, niñas y adolescentes y logra fundamentar su vinculación con el principio de autonomía progresiva. Sin embargo, el examen del enfoque de género es muy básico y sin referencia a estándares internacionales específicos (como la CEDAW o la Convención de Belém do Pará). La reflexión sobre desigualdades estructurales requiere mayor profundidad y vinculación con fenómenos sociales recientes como el estallido social de 2019 o la crisis del SENAME. La perspectiva interseccional aparece de forma inicial, pero debe enriquecerse incorporando otras categorías de vulnerabilidad, como etnia y discapacidad. El lenguaje jurídico es correcto y profesional, aunque podría ganar en sofisticación incorporando referencias doctrinales y jurisprudenciales.
A51: 21142414 | B51: 1 | C51: ANTONIA PAZ ESCOBAR GUTIÉRREZ | D51: ESCOBAR | E51: GUTIÉRREZ | F51: ANTONIA PAZ | G51: Avance curricular suficiente o adecuado para evaluar ciclo básico | H51: Rendida | I51: 45758 | K51: 4 | L51: 4 | M51: 3 | N51: 3 | O51: 2 | P51: 2 | Q51: 1 | R51: 3 | S51: =SUM(K51:R51) -> 22 | T51: =S51/40 -> 0.55 | U51: =IF(H51="Rendida ",IF('Resultados Individuales'!T51<49.5%,"Por Mejorar",IF('Resultados Individuales'!T51<64.5%,"Base",IF('Resultados Individuales'!T51<84.5%,"Satisfactorio","Óptimo"))),"No rendida o no válida") -> Base | V51: El estudiante demuestra un alto nivel de desempeño general, con un desarrollo excepcional en la primera actividad y un trabajo correcto, aunque con falencias críticas, en la segunda. En la primera actividad, el análisis del precario es sobresaliente: se desarrollan de manera sistemática los tres requisitos del art. 2195 CC, con fundamentación técnica rigurosa y una argumentación clara sobre la ausencia de nexo jurídico entre las partes. El posicionamiento ético destaca por su solidez, al plantear una crítica profunda frente a la incorrecta aplicación del derecho y cuestionar el excesivo valor que el tribunal otorga al matrimonio en comparación con la aplicación estricta del derecho positivo. Asimismo, la correlación con Finnis es apropiada, aunque todavía perfectible, pues si bien se plantea una crítica coherente a la sobrevaloración del matrimonio, debería profundizarse más en los elementos constitutivos específicos (fides y procreación). El lenguaje jurídico es adecuado y profesional, con proyección sólida al ejercicio de la abogacía. Desde el punto de vista formal, el texto mantiene calidad aceptable, aunque presenta errores menores de redacción y estilo. Para alcanzar una excelencia integral, se recomienda pulir esos aspectos formales, adoptar un registro más técnico en su redacción y profundizar en los elementos doctrinales de Finnis. En la segunda actividad, el trabajo cumple con la identificación de los mecanismos de participación de los NNA, acentuando la declaración directa en juicio y vinculándolos con su reconocimiento como sujetos de derecho. El lenguaje jurídico empleado es correcto y apropiado. Sin embargo, los aspectos más débiles se encuentran en el análisis de género y de desigualdades estructurales, los cuales se abordan de manera muy general y sin referencia a instrumentos normativos internacionales relevantes (CEDAW, Convención de Belém do Pará, Convención sobre los Derechos del Niño). La perspectiva interseccional no se desarrolla, lo que limita el potencial crítico del análisis. Para fortalecer su desempeño en esta dimensión, se recomienda incorporar ejemplos normativos de igualdad de género, explicar cómo el proyecto enfrenta desigualdades históricas en la práctica y enriquecer el análisis interseccional con categorías adicionales como condición económica, etnia o discapacidad.
A52: 21159801 | B52: 8 | C52: THAIS SOFIA CARVAJAL AGUILAR | D52: CARVAJAL | E52: AGUILAR | F52: THAIS SOFIA | G52: Avance curricular suficiente o adecuado para evaluar ciclo básico | H52: Rendida | I52: 45758 | K52: 3 | L52: 3 | M52: 2 | N52: 3 | O52: 2 | P52: 2 | Q52: 2 | R52: 3 | S52: =SUM(K52:R52) -> 20 | T52: =S52/40 -> 0.5 | U52: =IF(H52="Rendida ",IF('Resultados Individuales'!T52<49.5%,"Por Mejorar",IF('Resultados Individuales'!T52<64.5%,"Base",IF('Resultados Individuales'!T52<84.5%,"Satisfactorio","Óptimo"))),"No rendida o no válida") -> Base | V52: El estudiante demuestra un nivel competente en ambas actividades, con un dominio básico suficiente de las instituciones jurídicas analizadas y un correcto uso del lenguaje, aunque aún necesita avanzar en mayor rigor conceptual, profundidad crítica y sofisticación académica. En la primera actividad, se aprecia un buen dominio básico de la acción de precario, citando correctamente el art. 2195 CC y desarrollando una argumentación coherente sobre la procedencia de la acción. El posicionamiento ético es pertinente, al cuestionar la decisión del tribunal desde la justicia social y el derecho positivo. Asimismo, la correlación con Finnis es correcta, al identificar los elementos del matrimonio, aunque queda en un nivel superficial, sin profundizar la articulación filosófico-jurídica ni los elementos constitutivos en detalle. El lenguaje jurídico es adecuado y proyecta competencia, aunque podría ser más técnico y formal. La calidad formal de la redacción es aceptable, con errores menores, pero se recomienda mejorar la sintaxis y precisión conceptual. En la segunda actividad, el análisis es correcto en cuanto a los mecanismos de participación de los NNA y el deber del tribunal de justificar la incorporación o rechazo de su opinión, fundamentando incluso en la Constitución. Sin embargo, los aspectos más débiles aparecen en el enfoque de género y en la reflexión sobre desigualdades estructurales, que carecen de desarrollo normativo y conexión con fenómenos sociales contemporáneos como el estallido social de 2019 o la crisis del SENAME. La interseccionalidad está apenas esbozada y no articula múltiples variables de vulnerabilidad (como género, edad, etnia o discapacidad). El lenguaje jurídico es correcto y con referencias pertinentes, pero puede ganar en precisión técnica y rigor académico.
A53: 21171535 | B53: 9 | C53: TONKA FRANCISCA DONOSO CALDERÓN | D53: DONOSO | E53: CALDERÓN | F53: TONKA FRANCISCA | G53: Avance curricular suficiente o adecuado para evaluar ciclo básico | H53: Rendida | I53: 45758 | K53: 2 | L53: 4 | M53: 3 | N53: 3 | O53: 3 | P53: 3 | Q53: 3 | R53: 4 | S53: =SUM(K53:R53) -> 25 | T53: =S53/40 -> 0.625 | U53: =IF(H53="Rendida ",IF('Resultados Individuales'!T53<49.5%,"Por Mejorar",IF('Resultados Individuales'!T53<64.5%,"Base",IF('Resultados Individuales'!T53<84.5%,"Satisfactorio","Óptimo"))),"No rendida o no válida") -> Base | V53: El trabajo del estudiante evidencia un desempeño sólido en varias dimensiones, aunque con desajustes conceptuales importantes en la primera actividad que deben corregirse para alcanzar un nivel óptimo. En la primera actividad, se valora positivamente la cita expresa del art. 2195 del Código Civil y la capacidad de articular un posicionamiento ético profundo y original. El estudiante desarrolla una crítica sofisticada en torno a la primacía del derecho positivo y a la necesidad de que los principios éticos se adapten al marco normativo, constituyendo este su mayor logro académico en la actividad. También establece una correlación con la visión de Finnis, identificando valores comunes respecto del matrimonio, aunque sin profundizar sistemáticamente en los elementos constitutivos específicos de la filosofía del autor (fides y procreación). Sin embargo, el análisis jurídico presenta confusiones conceptuales graves sobre la interpretación del art. 2195 CC, al asumir erróneamente que los dos incisos enuncian requisitos alternativos, cuando en realidad describen situaciones diferentes de precario. Esta falencia genera un vacío en el desarrollo de los requisitos copulativos que exige la institución. El lenguaje jurídico es en general apropiado, aunque con algunas imprecisiones técnicas, y la estructura formal es satisfactoria, con errores menores de redacción. Para mejorar, el estudiante debe: (1) corregir la comprensión del art. 2195 CC y sistematizar los requisitos del precario; (2) profundizar la correlación académica con Finnis; y (3) depurar la expresión escrita y técnica del lenguaje jurídico. En la segunda actividad, el trabajo alcanza un nivel claramente más consistente y académico. El estudiante presenta un análisis bien estructurado de los mecanismos de participación de NNA, destacando la escucha activa, la obligación de motivación judicial y el principio de interés superior. Reconoce de manera adecuada la dimensión de género al incorporar organismos especializados y una perspectiva interseccional, integrando salud y coordinación administrativa como variables relevantes. Un aspecto destacable es la incorporación de casuística nacional (caso Nabila Rifo) para ilustrar la persistencia de desigualdades intrafamiliares, lo que vincula el análisis normativo con fenómenos sociales concretos. El uso del lenguaje jurídico es riguroso, académico y fundado en estándares del debido proceso, destacando la alusión al principio de legalidad. No obstante, para perfeccionar el nivel alcanzado, se recomienda incorporar normas internacionales relativas a igualdad y género (CEDAW, Convención de Belém do Pará) y expandir la mirada interseccional hacia otras categorías de vulnerabilidad como etnia y clase social.
A54: 21177034 | B54: 1 | C54: MONSERRAT ALEJANDRA ESTAY HENRIQUEZ | D54: ESTAY | E54: HENRIQUEZ | F54: MONSERRAT ALEJANDRA | G54: Avance curricular suficiente o adecuado para evaluar ciclo básico | H54: No rendida | I54: no aplica | S54: =SUM(K54:R54) -> 0 | T54: =S54/40 -> 0 | U54: =IF(H54="Rendida ",IF('Resultados Individuales'!T54<49.5%,"Por Mejorar",IF('Resultados Individuales'!T54<64.5%,"Base",IF('Resultados Individuales'!T54<84.5%,"Satisfactorio","Óptimo"))),"No rendida o no válida") -> No rendida o no válida
A55: 21179455 | B55: 0 | C55: BASTIÁN PATRICIO LEZANA CASTILLO | D55: LEZANA | E55: CASTILLO | F55: BASTIÁN PATRICIO | S55: =SUM(K55:R55) -> 0 | T55: =S55/40 -> 0 | U55: =IF(H55="Rendida ",IF('Resultados Individuales'!T55<49.5%,"Por Mejorar",IF('Resultados Individuales'!T55<64.5%,"Base",IF('Resultados Individuales'!T55<84.5%,"Satisfactorio","Óptimo"))),"No rendida o no válida") -> No rendida o no válida
A56: 21197234 | B56: 3 | C56: ELÍAS BERNABÉ ARENAS SERRANO | D56: ARENAS | E56: SERRANO | F56: ELÍAS BERNABÉ | G56: Avance curricular suficiente o adecuado para evaluar ciclo básico | H56: Rendida | I56: 45758 | K56: 2 | L56: 3 | M56: 3 | N56: 3 | O56: 2 | P56: 2 | Q56: 1 | R56: 3 | S56: =SUM(K56:R56) -> 19 | T56: =S56/40 -> 0.475 | U56: =IF(H56="Rendida ",IF('Resultados Individuales'!T56<49.5%,"Por Mejorar",IF('Resultados Individuales'!T56<64.5%,"Base",IF('Resultados Individuales'!T56<84.5%,"Satisfactorio","Óptimo"))),"No rendida o no válida") -> Por Mejorar | V56: El desempeño del estudiante refleja un avance notorio en el manejo de conceptos normativos y en el uso del lenguaje jurídico técnico, mostrando además una capacidad adecuada para vincular los problemas jurídicos con principios éticos y sociales. Sin embargo, persisten confusiones conceptuales y falencias críticas en la profundidad de análisis que deben ser atendidas para elevar su rendimiento a un nivel óptimo. En la primera actividad, el estudiante demuestra una comprensión general de la institución del precario, citando correctamente el art. 2195 CC y estableciendo con claridad su posición sobre la procedencia de la acción. Su análisis ético es pertinente, pues reconoce la dimensión humana del caso e introduce nociones como la justicia conmutativa, además de relacionar adecuadamente la teoría de Finnis con el considerando judicial. A pesar de estos aciertos, la respuesta presenta una carencia técnica en el desarrollo sistemático de los fundamentos del precario, lo que limita la solidez argumentativa. Asimismo, la correlación con Finnis es tratada en un nivel introductorio, sin profundizar en los dos elementos constitutivos del matrimonio que plantea el autor (amistad/fides y procreación). Para alcanzar un nivel superior, el estudiante debe precisar mejor los requisitos del precario, enriquecer el análisis ético con nociones de justicia social y seguridad jurídica, ampliar su vínculo con Finnis y mejorar la corrección formal del escrito para proyectar un estilo más académico y profesional. En la segunda actividad, se destacan fortalezas sobresalientes en el manejo del lenguaje jurídico técnico, empleando con propiedad conceptos como sujetos de derecho, autonomía progresiva, patria potestad, incapaces relativos y debido proceso. También se valora su excelente vinculación entre el proyecto de ley y los estándares del debido proceso, al explicar con claridad cómo el derecho a ser oído evita que la participación de los NNA sea meramente “simbólica o decorativa”. Identifica correctamente los mecanismos de participación (audiencias específicas, trato digno, no revictimización) y establece su conexión con la autonomía progresiva. Sin embargo, se observan deficiencias graves: la más relevante es la confusión entre “enfoque intersectorial” e “interseccionalidad”, lo que refleja incomprensión de un concepto clave en el análisis de género y vulnerabilidad. Además, su aproximación al enfoque de género es superficial, pues no identifica medidas concretas del proyecto ni profundiza en las desigualdades estructurales. De igual modo, la contextualización histórica resulta débil, debido a que se limita a generalidades en lugar de referirse a hechos políticos y sociales específicos de Chile de los últimos diez años (como el estallido social de 2019, la crisis del SENAME o la tramitación de la Ley 21.430). Para mejorar, será indispensable clarificar conceptualmente la diferencia entre coordinación intersectorial e interseccionalidad, profundizar el análisis de género y desigualdades estructurales con normas y medidas concretas, y fortalecer el contexto histórico con referencias a eventos específicos y fechados.
A57: 21228748 | B57: 2 | C57: DANIEL ALONSO SALVO OLMOS | D57: SALVO | E57: OLMOS | F57: DANIEL ALONSO | S57: =SUM(K57:R57) -> 0 | T57: =S57/40 -> 0 | U57: =IF(H57="Rendida ",IF('Resultados Individuales'!T57<49.5%,"Por Mejorar",IF('Resultados Individuales'!T57<64.5%,"Base",IF('Resultados Individuales'!T57<84.5%,"Satisfactorio","Óptimo"))),"No rendida o no válida") -> No rendida o no válida
A58: 21229788 | B58: 7 | C58: FRANCISCO DE BORJA DAHMEN VALENZUELA | D58: DAHMEN | E58: VALENZUELA | F58: FRANCISCO DE BORJA | S58: =SUM(K58:R58) -> 0 | T58: =S58/40 -> 0 | U58: =IF(H58="Rendida ",IF('Resultados Individuales'!T58<49.5%,"Por Mejorar",IF('Resultados Individuales'!T58<64.5%,"Base",IF('Resultados Individuales'!T58<84.5%,"Satisfactorio","Óptimo"))),"No rendida o no válida") -> No rendida o no válida
A59: 21230123 | B59: K | C59: MARTINA IGNACIA DÍAZ PÉREZ | D59: DÍAZ | E59: PÉREZ | F59: MARTINA IGNACIA | G59: Avance curricular suficiente o adecuado para evaluar ciclo básico | H59: Rendida | I59: 45758 | K59: 3 | L59: 4 | M59: 4 | N59: 4 | O59: 3 | P59: 3 | Q59: 3 | R59: 3 | S59: =SUM(K59:R59) -> 27 | T59: =S59/40 -> 0.675 | U59: =IF(H59="Rendida ",IF('Resultados Individuales'!T59<49.5%,"Por Mejorar",IF('Resultados Individuales'!T59<64.5%,"Base",IF('Resultados Individuales'!T59<84.5%,"Satisfactorio","Óptimo"))),"No rendida o no válida") -> Satisfactorio | V59: El trabajo revela un alto nivel de competencia jurídica, analítica y ética, con un desempeño destacado en ambas actividades. Se evidencia manejo sólido del lenguaje especializado, argumentación madura y capacidad de integrar derecho positivo, principios éticos y fenómenos sociales en sus respuestas. En la primera actividad, el análisis del precario es coherente y bien estructurado, desarrollando argumentos válidos sobre la extinción de títulos y la ausencia de nexo jurídico. El posicionamiento ético es sobresaliente, ya que plantea con madurez académica la tensión entre ética, moral y derecho positivo, incorporando nociones avanzadas como seguridad jurídica, principio de legalidad y primacía de la norma positivizada. La correlación con Finnis es académicamente brillante, distinguiendo entre el enfoque individual del filósofo (matrimonio como bien humano básico en sentido personal) y el enfoque social del tribunal (protección de la familia como institución), lo que demuestra comprensión profunda de ambas perspectivas. El lenguaje jurídico es técnico, preciso y especializado, proyectando claramente una competencia profesional sólida. Desde el punto de vista formal, la calidad es buena, con solo errores menores. Para alcanzar una excelencia integral, se recomienda citar de manera explícita el art. 2195 CC, desarrollar de forma sistemática los tres requisitos copulativos del precario y pulir detalles de redacción y forma. En la segunda actividad, el desempeño se mantiene a un nivel muy alto. El estudiante expone con claridad los mecanismos de participación de niños, niñas y adolescentes (derecho a ser oídos, audiencias adaptadas y obligación de motivación), vinculándolos adecuadamente con el principio de autonomía progresiva. El análisis de género es sólido, al subrayar la protección reforzada en contextos de violencia intrafamiliar y la importancia de un trato digno y no revictimizante. La reflexión conecta con fenómenos sociales relevantes y actuales, como el estallido social de 2019 y la pandemia, lo que muestra un excelente manejo del contexto. Asimismo, incorpora una perspectiva interseccional inicial, considerando género y edad y destacando la coordinación interinstitucional para la protección integral. El lenguaje jurídico es nuevamente sólido y profesional. Para perfeccionar este nivel y alcanzar la excelencia, se sugiere profundizar en la referencia a normas internacionales (CEDAW, Belém do Pará), integrar otras categorías de vulnerabilidad como etnia o clase social y ejemplificar de manera concreta cómo las reformas propuestas se orientan a transformar desigualdades estructurales en la práctica judicial.
A60: 21244055 | B60: 8 | C60: ALVARO FELIPE FUENTES FUENZALIDA | D60: FUENTES | E60: FUENZALIDA | F60: ALVARO FELIPE | G60: Avance curricular suficiente o adecuado para evaluar ciclo básico | H60: Rendida | I60: 45758 | K60: 2 | L60: 2 | M60: 2 | N60: 2 | O60: 2 | P60: 1 | Q60: 1 | R60: 2 | S60: =SUM(K60:R60) -> 14 | T60: =S60/40 -> 0.35 | U60: =IF(H60="Rendida ",IF('Resultados Individuales'!T60<49.5%,"Por Mejorar",IF('Resultados Individuales'!T60<64.5%,"Base",IF('Resultados Individuales'!T60<84.5%,"Satisfactorio","Óptimo"))),"No rendida o no válida") -> Por Mejorar | V60: El desempeño del estudiante evidencia dificultades significativas en ambas actividades, que comprometen la coherencia argumentativa, el uso del lenguaje jurídico y el nivel de análisis esperado en el perfil intermedio de la carrera de Derecho. En la primera actividad, aunque reconoce la tensión entre la protección constitucional de la familia y la aplicación rigurosa de la institución del precario, la respuesta presenta confusiones conceptuales graves, definiendo incorrectamente el precario como “ocupación o enajenación”. A esto se suma un posicionamiento contradictorio, oscilando entre criticar y apoyar al tribunal sin sostener una tesis clara. La argumentación carece de coherencia lógica y no desarrolla de manera sistemática los elementos copulativos del art. 2195 CC, quedando el análisis en un plano superficial y sin conceptos técnicos relevantes. Los múltiples errores ortográficos y gramaticales afectan la comunicación profesional y proyectan un déficit en la precisión del lenguaje jurídico. Para mejorar, el estudiante debe: (1) consolidar la comprensión de los conceptos básicos de Derecho Civil, (2) ejercitar habilidades de argumentación para sostener posturas claras, (3) profundizar en los requisitos del precario con rigor técnico, y (4) corregir con urgencia las deficiencias ortográficas, gramaticales y formales. En la segunda actividad, el estudiante alcanza un nivel algo más organizado, describiendo los principios de participación y autonomía progresiva, y mencionando normas conexas. Sin embargo, la respuesta sigue siendo excesivamente general y carece de conexión directa con las disposiciones específicas del proyecto de ley, lo que reduce la fuerza jurídica del análisis. El examen del enfoque de género es superficial, sin identificar las modificaciones procesales orientadas a reducir desigualdades estructurales. Del mismo modo, la perspectiva interseccional está ausente, y no se integra una reflexión crítica sobre fenómenos sociales concretos relevantes para contextualizar la reforma. El lenguaje jurídico es correcto en rasgos generales, pero todavía insuficiente en precisión técnica y proyección profesional. Para mejorar, se recomienda: (1) citar artículos concretos del proyecto con argumentos aplicados, (2) vincularlos a ejemplos claros de desigualdad de género y reformas procesales específicas, (3) incorporar categorías interseccionales como edad, clase o etnia, y (4) adoptar un lenguaje técnico más riguroso.
A61: 21244559 | B61: 2 | C61: SAYEN ANTONIA VEGA SILVA | D61: VEGA | E61: SILVA | F61: SAYEN ANTONIA | G61: Avance curricular suficiente o adecuado para evaluar ciclo básico | H61: Rendida | I61: 45758 | K61: 3 | L61: 3 | M61: 3 | N61: 3 | O61: 2 | P61: 2 | Q61: 1 | R61: 2 | S61: =SUM(K61:R61) -> 19 | T61: =S61/40 -> 0.475 | U61: =IF(H61="Rendida ",IF('Resultados Individuales'!T61<49.5%,"Por Mejorar",IF('Resultados Individuales'!T61<64.5%,"Base",IF('Resultados Individuales'!T61<84.5%,"Satisfactorio","Óptimo"))),"No rendida o no válida") -> Por Mejorar | V61: El desempeño del estudiante muestra una base sólida en ambas actividades, con un manejo correcto de los conceptos jurídicos fundamentales y un uso apropiado del lenguaje técnico, aunque aún requiere avanzar en profundidad de análisis normativo y crítico para alcanzar un nivel plenamente óptimo. En la primera actividad, se aprecia una comprensión adecuada de la institución del precario, estableciendo una posición clara y coherente que defiende la procedencia de la acción con fundamento en el principio de primacía del derecho positivo y el título inscrito. Destaca el equilibrio logrado entre la dimensión ética y el análisis jurídico técnico, reconociendo tanto los aspectos emocionales y familiares del caso como el deber de prevalencia de las reglas jurídicas aplicables. La conexión entre los planteamientos de John Finnis y el considerando judicial es pertinente, aunque todavía se presenta de manera breve y no lo suficientemente desarrollada en cuanto a los elementos constitutivos del matrimonio. El lenguaje jurídico empleado es claro y preciso, y la redacción, si bien contiene errores menores, no compromete la adecuada comunicación de las ideas. Para perfeccionar el nivel alcanzado, se recomienda profundizar en el análisis de los tres requisitos copulativos del precario, desarrollar más exhaustivamente la relevancia de la justicia social y la seguridad jurídica en la decisión judicial y afinar la correlación con la teoría de Finnis. En la segunda actividad, el estudiante identifica correctamente los mecanismos de participación de los NNA (derecho a ser oído, audiencias adaptadas y obligación de motivación), y los vincula de forma coherente con los principios de interés superior y autonomía progresiva. Asimismo, reconoce la necesidad de medidas de protección reforzada en contextos de violencia intrafamiliar, aunque lo hace sin un anclaje normativo concreto. El análisis de desigualdades estructurales se aborda de manera superficial, y la perspectiva interseccional queda apenas esbozada, sin explorar cómo se cruzan categorías sociales relevantes (género, edad, etnia, condición socioeconómica). El lenguaje jurídico utilizado resulta funcional y pertinente, pero para robustecer la argumentación es necesario referenciar de manera expresa artículos de la Ley 21.430, la Convención sobre los Derechos del Niño y normas procesales específicas.
A62: 21245563 | B62: 6 | C62: ROCIO CHARLOTT DONAIRE BARRÍA | D62: DONAIRE | E62: BARRÍA | F62: ROCIO CHARLOTT | S62: =SUM(K62:R62) -> 0 | T62: =S62/40 -> 0 | U62: =IF(H62="Rendida ",IF('Resultados Individuales'!T62<49.5%,"Por Mejorar",IF('Resultados Individuales'!T62<64.5%,"Base",IF('Resultados Individuales'!T62<84.5%,"Satisfactorio","Óptimo"))),"No rendida o no válida") -> No rendida o no válida
A63: 21245675 | B63: 6 | C63: MARTIN BENJAMIN ELIAS ROMERO FUENTEALBA | D63: ROMERO | E63: FUENTEALBA | F63: MARTIN BENJAMIN ELIAS | S63: =SUM(K63:R63) -> 0 | T63: =S63/40 -> 0 | U63: =IF(H63="Rendida ",IF('Resultados Individuales'!T63<49.5%,"Por Mejorar",IF('Resultados Individuales'!T63<64.5%,"Base",IF('Resultados Individuales'!T63<84.5%,"Satisfactorio","Óptimo"))),"No rendida o no válida") -> No rendida o no válida
A64: 21259032 | B64: 0 | C64: MARTINA ANDREA TOBAR ARANCIBIA | D64: TOBAR | E64: ARANCIBIA | F64: MARTINA ANDREA | G64: Avance curricular suficiente o adecuado para evaluar ciclo básico | H64: Rendida | I64: 45842 | K64: 4 | L64: 4 | M64: 4 | N64: 4 | O64: 3 | P64: 4 | Q64: 3 | R64: 3 | S64: =SUM(K64:R64) -> 29 | T64: =S64/40 -> 0.725 | U64: =IF(H64="Rendida ",IF('Resultados Individuales'!T64<49.5%,"Por Mejorar",IF('Resultados Individuales'!T64<64.5%,"Base",IF('Resultados Individuales'!T64<84.5%,"Satisfactorio","Óptimo"))),"No rendida o no válida") -> Satisfactorio | V64: Comentarios actividad uno: Desarrolla incluyen un análisis técnico magistral del precario que distingue sofisticadamente entre derechos reales y personales, estableciendo que el "vínculo matrimonial con el anterior dueño no genera un derecho real o personal oponible a la nueva propietaria" y que la "institución del precario busca proteger el derecho de dominio"; un posicionamiento ético crítico excepcional que incorpora múltiples conceptos técnicos solicitados desarrollando equilibradamente la tensión entre aplicación literal del derecho positivo versus consideraciones de justicia social, identificando apropiadamente "interpretación extensiva" y "incertidumbre jurídica"; una correlación conceptual excepcional entre Finnis y el tribunal que demuestra síntesis filosófico-jurídica magistral estableciendo que el "tribunal implícitamente considera los valores expresados por Finnis como contenidos relevantes para la interpretación y aplicación del derecho"; dominio excepcional del lenguaje jurídico especializado con terminología de altísima precisión técnica. Trabajo dos por correo
A65: 21277377 | B65: 8 | C65: SOULYN YURISSIK AGUILAR CRUZ | D65: AGUILAR | E65: CRUZ | F65: SOULYN YURISSIK | G65: Avance curricular suficiente o adecuado para evaluar ciclo básico | H65: Rendida | I65: 45758 | K65: 2 | L65: 3 | M65: 3 | N65: 2 | O65: 2 | P65: 2 | Q65: 2 | R65: 2 | S65: =SUM(K65:R65) -> 18 | T65: =S65/40 -> 0.45 | U65: =IF(H65="Rendida ",IF('Resultados Individuales'!T65<49.5%,"Por Mejorar",IF('Resultados Individuales'!T65<64.5%,"Base",IF('Resultados Individuales'!T65<84.5%,"Satisfactorio","Óptimo"))),"No rendida o no válida") -> Por Mejorar | V65: El desempeño del estudiante en ambas actividades refleja una aproximación inicial a los temas tratados y algunas fortalezas destacables, pero también deficiencias técnicas y conceptuales significativas que deben ser abordadas para alcanzar el nivel esperado en el perfil intermedio de la carrera de Derecho. En la primera actividad, se valora positivamente la intención de responder a las tres preguntas planteadas, la incorporación de una perspectiva ética en el análisis y el reconocimiento de la protección constitucional de la familia, así como la identificación de la conexión general entre los planteamientos de Finnis y el considerando quinto de la sentencia. Sin embargo, el trabajo presenta errores de fondo y forma que comprometen su calidad académica: no se referencia expresamente el artículo 2195 del Código Civil, ni se desarrolla sistemáticamente los tres requisitos copulativos del precario. Se observan confusiones conceptuales graves como la de equiparar bienes muebles e inmuebles, un análisis ético que no incorpora conceptos técnicos solicitados (como seguridad jurídica, incorrecta aplicación del derecho o interpretación extensiva), además de una correlación superficial con Finnis, sin desarrollo de los elementos constitutivos del matrimonio (fides y procreación) ni uso de terminología académica precisa. El lenguaje jurídico empleado es insuficientemente técnico y la expresión escrita presenta problemas de construcción sintáctica que afectan la claridad del razonamiento. Para mejorar, la estudiante debe reforzar conocimientos jurídicos básicos, corregir errores conceptuales, y profundizar tanto en el plano técnico (norma del art. 2195 CC, requisitos del precario) como en el ético‑académico (conceptos avanzados, relación filosófico‑jurídica con Finnis). En la segunda actividad, se identifican como fortalezas la capacidad de contextualización sociopolítica, evidenciada en la referencia a la “revolución feminista” desde 2018 y a la crisis del SENAME, así como la correcta vinculación con el debido proceso constitucional citando expresamente el art. 19 N° 3 de la Constitución. También se reconoce una aproximación inicial al enfoque de género al mencionar la situación desigual en el cuidado de los NNA y el rol de la coordinación intersectorial. No obstante, persisten deficiencias críticas: confusión conceptual (por ejemplo, al definir incorrectamente a los curadores ad litem como “partes de los tribunales”), ausencia de un desarrollo profundo sobre cómo el proceso judicial puede transformar desigualdades estructurales, y un abordaje superficial de la interseccionalidad, al mencionar categorías como género y edad pero sin explicar cómo se entrecruzan ni sus efectos en el acceso a la justicia. El lenguaje jurídico es limitado y ambiguo, reduciendo la claridad técnica del análisis. Para alcanzar un nivel superior, resulta indispensable fortalecer la precisión conceptual procesal, profundizar el análisis crítico de desigualdades con ejemplos normativos concretos del proyecto y articular una perspectiva genuinamente interseccional que integre diversas categorías sociales (género, edad, clase, etnia, discapacidad).
A66: 21281061 | B66: 4 | C66: VICENTE ANDRES LAGOS RAMIREZ | D66: LAGOS | E66: RAMIREZ | F66: VICENTE ANDRES | G66: Avance curricular suficiente o adecuado para evaluar ciclo básico | H66: Rendida | I66: 45758 | K66: 3 | L66: 3 | M66: 3 | N66: 3 | O66: 2 | P66: 3 | Q66: 2 | R66: 3 | S66: =SUM(K66:R66) -> 22 | T66: =S66/40 -> 0.55 | U66: =IF(H66="Rendida ",IF('Resultados Individuales'!T66<49.5%,"Por Mejorar",IF('Resultados Individuales'!T66<64.5%,"Base",IF('Resultados Individuales'!T66<84.5%,"Satisfactorio","Óptimo"))),"No rendida o no válida") -> Base | V66: El estudiante demuestra en ambas actividades un desempeño suficiente y acorde al perfil intermedio, logrando dar cumplimiento a los estándares básicos exigidos y mostrando comprensión adecuada de los conceptos jurídicos centrales, aunque aún existen áreas de mejora importantes para alcanzar mayor solidez académica. En la primera actividad, se aprecia un trabajo correcto, con posturas claras y consistentes en todas las respuestas, comprensión adecuada de los elementos del precario y cita apropiada del artículo 2195 del Código Civil. Se valora el uso de conceptos técnicos relevantes (título y modo, Conservador de Bienes Raíces, ordenamiento jurídico), así como un posicionamiento ético pertinente, al reconocer la tensión entre el valor sentimental y familiar de la vivienda y la aplicación rigurosa del derecho positivo. La correlación entre la filosofía de Finnis y el razonamiento del tribunal es desarrollada en términos apropiados, destacando la visión del matrimonio como institución fundamental. No obstante, el trabajo presenta debilidades en la calidad formal del texto, con errores de ortografía, puntuación y concordancia que afectan la presentación profesional. Asimismo, el análisis jurídico, aunque correcto, requiere mayor profundidad técnica en el desarrollo de ciertos conceptos solicitados y en la precisión del lenguaje especializado. En la segunda actividad, el desempeño es igualmente satisfactorio: el estudiante describe con claridad los mecanismos de participación de NNA (derecho a ser oídos, audiencias adaptadas, obligación de motivación y protección reforzada), empleando un lenguaje jurídico adecuado. Reconoce la incorporación del enfoque de género y la relevancia de la coordinación intersectorial en el proyecto. Sin embargo, el análisis de género permanece general y poco detallado, al no precisar medidas procesales concretas ni conectarlas con tratados internacionales relevantes (como la CEDAW o la Convención de Belém do Pará). De igual modo, la perspectiva interseccional no se desarrolla plenamente, pues no se examina cómo interactúan categorías sociales como género, edad, clase u origen étnico en el acceso a la justicia. Para consolidar el análisis, será necesario citar disposiciones específicas del proyecto, vincular el enfoque de género con estándares internacionales y profundizar en las variables de vulnerabilidad desde una perspectiva interseccional.
A67: 21289094 | B67: 4 | C67: SARA DEL ROSARIO SALAS BARRAZA | D67: SALAS | E67: BARRAZA | F67: SARA DEL ROSARIO | G67: Avance curricular suficiente o adecuado para evaluar ciclo básico | H67: Rendida | I67: 45758 | K67: 4 | L67: 4 | M67: 4 | N67: 4 | O67: 3 | P67: 3 | Q67: 3 | R67: 4 | S67: =SUM(K67:R67) -> 29 | T67: =S67/40 -> 0.725 | U67: =IF(H67="Rendida ",IF('Resultados Individuales'!T67<49.5%,"Por Mejorar",IF('Resultados Individuales'!T67<64.5%,"Base",IF('Resultados Individuales'!T67<84.5%,"Satisfactorio","Óptimo"))),"No rendida o no válida") -> Satisfactorio | V67: El trabajo del estudiante en ambas actividades revela un nivel de excelencia académica que supera los estándares del perfil intermedio en la carrera de Derecho. La producción se caracteriza por la precisión técnica, profundidad ética y madurez argumentativa, proyectando un dominio avanzado tanto del derecho positivo como de su relación con la filosofía y la justicia social. En la primera actividad, se desarrolla un análisis técnico excepcional de la institución del precario, integrando de manera sofisticada conceptos como derechos reales, oponibilidad y efectos de la transferencia de dominio, con plena comprensión de la interacción entre vínculos matrimoniales y títulos jurídicos eficaces. El posicionamiento ético alcanza un nivel sobresaliente, pues articula rigurosamente nociones como interpretación extensiva, seguridad jurídica, incorrecta aplicación del derecho y justicia social, incorporando con maestría la inevitable relación entre derecho y moral. La correlación conceptual con la filosofía de John Finnis es magistral, al vincular el valor básico del matrimonio como “razón fundamental para la acción humana” con la operacionalización que hace el tribunal en su razonamiento. El lenguaje jurídico usado es de altísima precisión técnica, y la calidad formal de la redacción supera estándares superiores, proyectando un estilo plenamente profesional. En la segunda actividad, el desempeño mantiene la misma solidez técnica. El estudiante expone con precisión los mecanismos de participación de NNA —derecho a ser oído en audiencias adaptadas y obligación de motivación judicial— vinculándolos con la autonomía progresiva y el interés superior del niño. El análisis de género es sólido, al destacar la reforma de reglas de guarda hacia corresponsabilidad y la capacitación de jueces en perspectiva interseccional. También resalta la reflexión crítica sobre desigualdades estructurales, subrayando el rol transformador de los tribunales en la protección de derechos. Además, se incorpora una perspectiva interseccional pertinente, al cruzar categorías como género y edad, evidenciando sensibilidad hacia los enfoques contemporáneos de derechos humanos, con referencias correctas a la Convención sobre los Derechos del Niño y la Ley 21.430. No obstante, aunque el rendimiento es sobresaliente, se detecta que aún falta mayor profundidad en el desarrollo del enfoque de género y de la perspectiva interseccional. Estas dimensiones se enuncian adecuadamente, pero requieren un análisis más exhaustivo de medidas procesales específicas, normas internacionales vinculadas (CEDAW, Belém do Pará) y de cómo interactúan diversas categorías sociales (género, edad, clase, etnia, condición socioeconómica, discapacidad) en el acceso a la justicia. Esto explica por qué en esas áreas el estudiante no alcanzó el puntaje máximo, quedando espacio de mejora en el plano crítico-normativo.
A68: 21294362 | B68: 2 | C68: FERNANDA BELÉN FIGUEROA OYARZO | D68: FIGUEROA | E68: OYARZO | F68: FERNANDA BELÉN | G68: Avance curricular suficiente o adecuado para evaluar ciclo básico | H68: Rendida | I68: 45758 | K68: 2 | L68: 3 | M68: 3 | N68: 2 | O68: 2 | P68: 2 | Q68: 1 | R68: 3 | S68: =SUM(K68:R68) -> 18 | T68: =S68/40 -> 0.45 | U68: =IF(H68="Rendida ",IF('Resultados Individuales'!T68<49.5%,"Por Mejorar",IF('Resultados Individuales'!T68<64.5%,"Base",IF('Resultados Individuales'!T68<84.5%,"Satisfactorio","Óptimo"))),"No rendida o no válida") -> Por Mejorar | V68: El trabajo del estudiante refleja una comprensión inicial adecuada de los problemas jurídicos planteados y cierta capacidad para identificar elementos éticos y normativos relevantes, pero aún presenta deficiencias significativas de fondo y forma que limitan el desarrollo argumentativo y la proyección profesional del escrito. En la primera actividad, se destaca positivamente la capacidad de reconocer la tensión entre derechos de propiedad y consideraciones matrimoniales, así como la correcta identificación de la conexión entre el pensamiento de John Finnis y el razonamiento del tribunal. Además, se observa la intención de incorporar una mirada ética en el análisis jurídico. No obstante, el desempeño es insuficiente en aspectos centrales: el estudiante no adopta claramente la postura opuesta al tribunal solicitada en la pregunta 1, lo que debilita la pertinencia de la respuesta; presenta confusión conceptual al mezclar argumentos sin coherencia lógica y omitir el desarrollo de conceptos fundamentales como seguridad jurídica o interpretación extensiva. A ello se suman múltiples errores de redacción, ortografía y expresión técnica (por ejemplo, “parees” en lugar de “partes”), que comprometen la claridad y la formalidad de la comunicación profesional. Para mejorar, es imprescindible fortalecer la comprensión conceptual del precario y su regulación en el art. 2195 del Código Civil, desarrollar con mayor rigor el análisis crítico de principios jurídicos, y pulir intensivamente las habilidades de redacción y precisión terminológica, aspectos esenciales en la formación jurídica. En la segunda actividad, el estudiante logra un planteamiento correcto en lo básico, al reconocer la incorporación de derechos de los NNA y la mención de criterios de igualdad, utilizando un lenguaje formal en términos generales. Sin embargo, el análisis es superficial y declarativo: el enfoque de género se limita a una visión formal de igualdad de trato, sin relacionar las reformas con la reducción de desigualdades estructurales concretas ni con su respaldo en instrumentos internacionales relevantes (CEDAW, Belém do Pará, Convención sobre los Derechos del Niño). Asimismo, se omite una reflexión crítica sobre la función del proceso judicial en perpetuar o transformar dichas desigualdades y no se articula una perspectiva interseccional que aborde la interacción de género con edad, clase social u otros factores determinantes en el acceso a la justicia. Para mejorar, el estudiante debe incorporar ejemplos concretos de modificaciones normativas, vincularlas con tratados internacionales de derechos humanos y analizar en mayor profundidad cómo cada medida contribuye a superar desigualdades estructurales desde una óptica interseccional.
A69: 21335967 | B69: 3 | C69: NICOLE ELBA MAGDALENA SÁNCHEZ ACUÑA | D69: SÁNCHEZ | E69: ACUÑA | F69: NICOLE ELBA MAGDALENA | G69: Avance curricular suficiente o adecuado para evaluar ciclo básico | H69: Rendida | I69: 45758 | K69: 4 | L69: 4 | M69: 4 | N69: 4 | O69: 2 | P69: 2 | Q69: 2 | R69: 3 | S69: =SUM(K69:R69) -> 25 | T69: =S69/40 -> 0.625 | U69: =IF(H69="Rendida ",IF('Resultados Individuales'!T69<49.5%,"Por Mejorar",IF('Resultados Individuales'!T69<64.5%,"Base",IF('Resultados Individuales'!T69<84.5%,"Satisfactorio","Óptimo"))),"No rendida o no válida") -> Base | V69: El desempeño del estudiante refleja un nivel muy sólido en ambas actividades, con un dominio técnico y ético sobresaliente en la primera y un desarrollo adecuado pero aún perfectible en la segunda. En la primera actividad, el estudiante presenta un análisis técnico impecable de la institución del precario, demostrando comprensión sofisticada de la extinción de vínculos jurídicos y de los efectos de la transmisión de dominio. El posicionamiento ético-crítico alcanza un nivel excepcional, al integrar los conceptos técnicos solicitados —interpretación extensiva, seguridad jurídica e incorrecta aplicación del derecho— y mantener un equilibrio adecuado entre la justicia social y la riguridad normativa. La correlación conceptual entre el pensamiento de Finnis y el razonamiento del tribunal se desarrolla a un nivel superior, mostrando comprensión profunda de la tensión entre protección del derecho de propiedad y consideración de vínculos humanos y familiares. El uso del lenguaje jurídico es avanzado, especializado y preciso, proyectando un perfil profesional destacado. En la segunda actividad, el estudiante resuelve correctamente lo esencial, al identificar los mecanismos de participación de NNA (derecho a ser oído directamente, audiencias adaptadas y motivación judicial de la opinión), articulándolos con principios claves como el interés superior del niño y la autonomía progresiva, lo que evidencia comprensión normativa correcta. Sin embargo, los puntos débiles se concentran en el análisis de género y desigualdades estructurales, que aparecen tratados de manera demasiado general al no precisar disposiciones normativas concretas ni vincularse con estándares internacionales (como CEDAW, Belém do Pará o la Convención sobre los Derechos del Niño). Asimismo, la perspectiva interseccional se limita a mencionar la coordinación interinstitucional, sin un desarrollo más profundo del cruce entre género, edad, clase u otras categorías sociales. El lenguaje jurídico empleado es adecuado y claro, pero la fundamentación alcanzaría un nivel superior con citas directas a artículos de la Ley N° 21.430, la Convención de los Derechos del Niño y el Código Civil.
A70: 21343449 | B70: 7 | C70: MARIA FERNANDA LUERA PUMA | D70: LUERA | E70: PUMA | F70: MARIA FERNANDA | G70: Avance curricular suficiente o adecuado para evaluar ciclo básico | H70: Rendida | I70: 45758 | K70: 3 | L70: 4 | M70: 4 | N70: 3 | O70: 2 | P70: 2 | Q70: 1 | R70: 3 | S70: =SUM(K70:R70) -> 22 | T70: =S70/40 -> 0.55 | U70: =IF(H70="Rendida ",IF('Resultados Individuales'!T70<49.5%,"Por Mejorar",IF('Resultados Individuales'!T70<64.5%,"Base",IF('Resultados Individuales'!T70<84.5%,"Satisfactorio","Óptimo"))),"No rendida o no válida") -> Base | V70: El trabajo del estudiante refleja un desempeño sólido y avanzado, destacando especialmente en el análisis ético y filosófico‑jurídico, con un nivel profesional en el uso del lenguaje y la forma de exposición. Sin embargo, se observan áreas de mejora en la profundidad técnica del análisis normativo y en el tratamiento crítico del enfoque de género y la interseccionalidad. En la primera actividad, se aprecia un posicionamiento ético excepcional, donde el estudiante evalúa con madurez la tensión entre las consideraciones morales y la aplicación estricta del derecho positivo, evidenciando comprensión avanzada de cómo el tribunal prioriza aspectos emocionales vinculados al matrimonio por sobre derechos de propiedad formalmente inscritos. Se valoran especialmente las conexiones conceptuales entre la filosofía de John Finnis y el razonamiento del tribunal, explicando en detalle cómo ambos abordan el matrimonio como institución fundamental y bien humano básico. Además, logra integrar los dos fines matrimoniales descritos por Finnis (amistad y procreación) y relacionarlos de manera sofisticada con el inmueble como símbolo tangible de la vida en común. El cuestionamiento crítico a la prevalencia de lo sentimental sobre lo jurídico es sólido, mostrando capacidad analítica madura. El uso del lenguaje jurídico es apropiado y la calidad formal del texto es profesional. Como áreas de mejora, sería recomendable profundizar más exhaustivamente en los aspectos normativos del precario (art. 2195 CC) y perfeccionar algunas expresiones técnicas para mayor precisión jurídica. En la segunda actividad, el estudiante describe correctamente los mecanismos de participación y obligación de motivación judicial, destacando la incorporación de audiencias adaptadas y unidades técnicas especializadas, lo que demuestra comprensión de la importancia de la protección de derechos de NNA y el enfoque de autonomía progresiva. No obstante, el tratamiento del enfoque de género y de las desigualdades estructurales se presenta superficial, pues no se detallan medidas procesales concretas ni se refuerza con estándares internacionales pertinentes. Tampoco se desarrolla una perspectiva interseccional auténtica, limitándose a un enfoque general. Para consolidar un nivel superior, sería necesario referenciar artículos específicos del proyecto de ley, además de tratados internacionales como la Convención sobre la Eliminación de Todas las Formas de Discriminación contra la Mujer (CEDAW) y la Convención sobre los Derechos del Niño, articulando con mayor fuerza cómo distintas categorías sociales (género, edad, clase, etnia) se cruzan en el acceso a la justicia y cómo el proceso judicial puede contribuir ya sea a reproducir o a transformar desigualdades.
A71: 21352833 | B71: 5 | C71: FRANCISCA JAVIERA PAZ GANA SOTO | D71: GANA | E71: SOTO | F71: FRANCISCA JAVIERA PAZ | G71: Avance curricular suficiente o adecuado para evaluar ciclo básico | H71: Rendida | I71: 45758 | K71: 3 | L71: 3 | M71: 2 | N71: 2 | O71: 2 | P71: 2 | Q71: 1 | R71: 3 | S71: =SUM(K71:R71) -> 18 | T71: =S71/40 -> 0.45 | U71: =IF(H71="Rendida ",IF('Resultados Individuales'!T71<49.5%,"Por Mejorar",IF('Resultados Individuales'!T71<64.5%,"Base",IF('Resultados Individuales'!T71<84.5%,"Satisfactorio","Óptimo"))),"No rendida o no válida") -> Por Mejorar | V71: El trabajo del estudiante refleja un desempeño satisfactorio, con fortalezas relevantes en la identificación de los temas centrales y en la adopción de posturas consistentes, pero también con áreas de mejora significativas en la profundidad técnica, el uso del lenguaje jurídico y la calidad formal del texto. En la primera actividad, se valora la adopción de posturas claras en todas las preguntas planteadas, así como la comprensión básica de los elementos del precario, reconociendo la tensión entre consideraciones éticas y el principio de seguridad jurídica. El análisis sobre la protección de terceros adquirentes resulta pertinente, y se aprecian conexiones correctas entre la filosofía de John Finnis y el razonamiento del tribunal respecto a la concepción del matrimonio como institución fundamental. Sin embargo, el análisis se mantiene en un nivel general: se necesita un desarrollo más profundo y técnico, en particular en la fundamentación de todos los elementos del artículo 2195 del Código Civil, y en la incorporación precisa de conceptos como analogía e incorrecta aplicación del derecho, solicitados en la pauta. Asimismo, convendría perfeccionar el uso del lenguaje jurídico, buscando mayor precisión técnica, y mejorar la calidad formal del escrito corrigiendo errores de ortografía, puntuación y concordancia gramatical, que afectan la presentación profesional del trabajo. En la segunda actividad, el estudiante describe con acierto los mecanismos de participación y destaca innovaciones centrales como las audiencias adaptadas y la obligación de motivación judicial, utilizando un lenguaje jurídico adecuado. Aun así, el análisis crítico sobre enfoque de género y desigualdades estructurales es superficial, ya que no detalla protocolos ni hace referencia a estándares internacionales aplicables. Tampoco se desarrolla una auténtica perspectiva interseccional que considere la interacción de múltiples variables sociales (género, edad, clase, etnia, etc.). Para consolidar esta dimensión, sería recomendable referenciar artículos específicos del proyecto, vincular las medidas a tratados internacionales relevantes como la CEDAW y la Convención sobre los Derechos del Niño, y explicar cómo las diferentes categorías sociales interactúan en la práctica judicial, reproduciendo o transformando las desigualdades.
A72: 21367625 | B72: 3 | C72: FRANCISCA BELÉN MELLA OSSES | D72: MELLA | E72: OSSES | F72: FRANCISCA BELÉN | G72: Avance curricular suficiente o adecuado para evaluar ciclo básico | H72: No rendida | I72: No aplica | S72: =SUM(K72:R72) -> 0 | T72: =S72/40 -> 0 | U72: =IF(H72="Rendida ",IF('Resultados Individuales'!T72<49.5%,"Por Mejorar",IF('Resultados Individuales'!T72<64.5%,"Base",IF('Resultados Individuales'!T72<84.5%,"Satisfactorio","Óptimo"))),"No rendida o no válida") -> No rendida o no válida
A73: 21371518 | B73: 6 | C73: RENATA ISIDORA MANSILLA RODRÍGUEZ | D73: MANSILLA | E73: RODRÍGUEZ | F73: RENATA ISIDORA | G73: Avance curricular suficiente o adecuado para evaluar ciclo básico | H73: Rendida | I73: 45758 | K73: 2 | L73: 1 | M73: 3 | N73: 2 | O73: 3 | P73: 2 | Q73: 2 | R73: 2 | S73: =SUM(K73:R73) -> 17 | T73: =S73/40 -> 0.425 | U73: =IF(H73="Rendida ",IF('Resultados Individuales'!T73<49.5%,"Por Mejorar",IF('Resultados Individuales'!T73<64.5%,"Base",IF('Resultados Individuales'!T73<84.5%,"Satisfactorio","Óptimo"))),"No rendida o no válida") -> Por Mejorar | V73: El trabajo evidencia una comprensión inicial de los problemas planteados y algunas fortalezas destacables, pero aún presenta deficiencias críticas que limitan su solidez académica y técnica en el marco de los estándares del perfil intermedio en Derecho. En la primera actividad, se reconoce como logro la correcta identificación de la conexión entre la filosofía de John Finnis y el razonamiento del tribunal, vinculando los elementos constitutivos del matrimonio (amistad/fides y procreación) con la valoración judicial del hogar común como institución fundamental. La respuesta mantiene además una estructura formal aceptable y comprensible. Sin embargo, los déficits son importantes: se observa una confusión conceptual grave sobre la procedencia del precario, pues se llega a afirmar la falta de valor de la acción en contradicción con la consigna de argumentar precisamente a favor de su idoneidad. A ello se suma la omisión expresa del artículo 2195 del Código Civil y la ausencia del desarrollo de sus elementos copulativos técnicos. Tampoco se responde la pregunta relativa al posicionamiento ético-crítico, omitiendo conceptos fundamentales como interpretación extensiva, seguridad jurídica e incorrecta aplicación del derecho. Finalmente, el uso del lenguaje jurídico es impreciso y con confusiones conceptuales relevantes, lo que afecta la claridad y el rigor profesional de la argumentación. Para avanzar, es urgente reforzar la comprensión de instituciones jurídicas básicas mediante estudio exhaustivo del precario y su regulación, así como mejorar la capacidad de análisis crítico con apoyo en conceptos doctrinarios y normativos solicitados, perfeccionar la precisión terminológica y cumplir íntegramente con los requerimientos de cada pregunta. En la segunda actividad, el desempeño es de nivel básico‑satisfactorio. La fortaleza principal radica en la identificación de medidas concretas del proyecto de ley, como la protección reforzada en casos de violencia intrafamiliar, lo que demuestra comprensión apropiada del enfoque de género en un aspecto puntual. No obstante, el análisis mantiene un carácter superficial: la perspectiva interseccional se limita a una mención nominal, sin articular cómo interactúan variables como género, edad, clase social u origen étnico en el acceso a la justicia. Asimismo, faltan referencias normativas específicas (artículos del proyecto de ley, de la Ley N° 21.430, del Código Civil o de la Convención sobre los Derechos del Niño), lo que debilita la fundamentación técnica. El lenguaje jurídico es adecuado en lo básico, pero se requiere mayor precisión expresiva y rigor profesional. Para mejorar, el/la estudiante debe citar normas y tratados internacionales específicos (CEDAW, Convención sobre los Derechos del Niño), profundizar en el análisis de desigualdades estructurales y desarrollar de manera real una perspectiva interseccional aplicada al proceso judicial de familia.
A74: 21378796 | B74: 9 | C74: BENJAMÍN TOMÁS CASTRO URREA | D74: CASTRO | E74: URREA | F74: BENJAMÍN TOMÁS | G74: Avance curricular suficiente o adecuado para evaluar ciclo básico | H74: Rendida | I74: 45758 | K74: 3 | L74: 4 | M74: 4 | N74: 2 | O74: 2 | P74: 2 | Q74: 3 | S74: =SUM(K74:R74) -> 20 | T74: =S74/40 -> 0.5 | U74: =IF(H74="Rendida ",IF('Resultados Individuales'!T74<49.5%,"Por Mejorar",IF('Resultados Individuales'!T74<64.5%,"Base",IF('Resultados Individuales'!T74<84.5%,"Satisfactorio","Óptimo"))),"No rendida o no válida") -> Base | V74: El desempeño refleja un nivel avanzado, con claras fortalezas en su capacidad de argumentación, manejo conceptual y uso del lenguaje jurídico, aunque aún existen aspectos específicos que deben fortalecerse para alcanzar la excelencia completa en el estándar del perfil intermedio. En la primera actividad, el análisis del precario es coherente y bien fundamentado, mostrando dominio de la institución, aunque se detecta la necesidad de mayor precisión técnica en ciertos conceptos y de incluir la cita expresa al art. 2195 del Código Civil, indispensable en este tipo de reflexiones. El posicionamiento ético es sobresaliente, pues desarrolla una crítica profunda y original en torno a la “des‑positivización” del derecho, integrando con solvencia principios como la autonomía de la voluntad y la libertad de contratación. La correlación entre la filosofía de Finnis y el razonamiento judicial es académicamente rigurosa, logrando conexiones precisas entre la teoría del bien humano básico del matrimonio y la valoración jurisprudencial del hogar común. El uso del lenguaje jurídico es técnico y sofisticado, reflejando sólida competencia y proyección profesional; además, la calidad formal es impecable en cuanto a redacción y estilo. Para un rendimiento de excelencia plena, es necesario citar de manera expresa el art. 2195 CC, corregir pequeñas imprecisiones conceptuales y desarrollar más sistemáticamente los requisitos copulativos del precario. En la segunda actividad, reconoce e identifica correctamente el nuevo paradigma de participación activa de niños, niñas y adolescentes (NNA) y la obligación de los tribunales de justificar su voz, vinculando el análisis con la autonomía progresiva, lo que constituye un aporte significativo. Sin embargo, el enfoque de género y de intersectorialidad se desarrolla de manera superficial, sin precisar protocolos normativos concretos ni referencias explícitas a fenómenos sociales recientes (ej., estallido social o crisis del SENAME), lo cual limita la fuerza crítica del análisis. El lenguaje jurídico es adecuado, pero el estilo es excesivamente abstracto, lo que difumina la claridad académica requerida. Para avanzar a un nivel superior, se recomienda enriquecer el análisis con referencias a estándares internacionales, como la CEDAW y la Convención sobre los Derechos del Niño, y profundizar la perspectiva interseccional, articulando cómo género, clase y etnia se cruzan y condicionan el real acceso a la justicia familiar.
A75: 21385693 | B75: 6 | C75: BENJAMIN IGNACIO VIERA GAMBOA | D75: VIERA | E75: GAMBOA | F75: BENJAMIN IGNACIO | G75: Avance curricular suficiente o adecuado para evaluar ciclo básico | H75: Rendida | I75: 45758 | K75: 3 | L75: 3 | M75: 2 | N75: 2 | O75: 2 | P75: 2 | Q75: 2 | R75: 3 | S75: =SUM(K75:R75) -> 19 | T75: =S75/40 -> 0.475 | U75: =IF(H75="Rendida ",IF('Resultados Individuales'!T75<49.5%,"Por Mejorar",IF('Resultados Individuales'!T75<64.5%,"Base",IF('Resultados Individuales'!T75<84.5%,"Satisfactorio","Óptimo"))),"No rendida o no válida") -> Por Mejorar | V75: El trabajo refleja un desempeño suficiente con aspectos destacables, pero también con áreas críticas de mejora necesarias para consolidar un nivel intermedio sólido en el perfil de la carrera de Derecho. En la primera actividad, se valora la comprensión de los conceptos fundamentales del caso, así como la adopción de posturas claras respecto a la procedencia del precario y la valoración ética de la sentencia. El/la estudiante logra identificar elementos relevantes como la seguridad jurídica y la justicia social, lo que denota atención al vínculo entre derecho positivo y consideraciones éticas. También establece la conexión entre el pensamiento de Finnis y el considerando judicial, aunque de manera superficial, sin explorar del todo las implicaciones filosóficas en juego. Los problemas más significativos se encuentran en el plano formal y técnico: la expresión escrita presenta errores gramaticales y de construcción que afectan la claridad, y el uso del lenguaje jurídico carece de precisión técnica, lo que reduce el rigor profesional del análisis. Para mejorar en esta área, se recomienda fortalecer la estructura argumentativa, perfeccionar la terminología jurídica y profundizar la articulación entre teoría filosófica y razonamiento judicial. En la segunda actividad, el desempeño es algo más sólido en lo descriptivo: se identifican adecuadamente los mecanismos de participación de NNA (derecho a ser oído directamente, audiencias adaptadas y obligación de motivación), vinculándolos con principios claves como el interés superior del niño y la autonomía progresiva. Sin embargo, el análisis pierde profundidad en su dimensión crítica: el enfoque de género y la consideración de desigualdades estructurales aparecen solo de manera general, sin precisar medidas procesales o referencias normativas concretas. A ello se suma que la perspectiva interseccional queda reducida a una mención de coordinación institucional, sin problematizar cómo se cruzan variables sociales como género, edad, clase u origen étnico en el acceso a la justicia. Aunque el lenguaje jurídico es correcto, la fundamentación se vería potenciada con citas concretas a artículos de la Ley N° 21.430, la Convención sobre los Derechos del Niño y el Código Civil.
A76: 21391140 | B76: 6 | C76: CRISTIAN MIGUEL BELTRÁN FLORES | D76: BELTRÁN | E76: FLORES | F76: CRISTIAN MIGUEL | G76: Avance curricular suficiente o adecuado para evaluar ciclo básico | H76: Rendida | I76: 45758 | K76: 4 | L76: 4 | M76: 3 | N76: 3 | O76: 3 | P76: 3 | Q76: 3 | R76: 2 | S76: =SUM(K76:R76) -> 25 | T76: =S76/40 -> 0.625 | U76: =IF(H76="Rendida ",IF('Resultados Individuales'!T76<49.5%,"Por Mejorar",IF('Resultados Individuales'!T76<64.5%,"Base",IF('Resultados Individuales'!T76<84.5%,"Satisfactorio","Óptimo"))),"No rendida o no válida") -> Base | V76: El trabajo evidencia un buen dominio conceptual y una comprensión sólida de los problemas jurídicos y sociolegales planteados en ambas actividades, aunque las virtudes en el plano argumentativo se ven matizadas por deb debilidades en la redacción formal, el estilo jurídico y la profundidad de ciertos análisis críticos. En la primera actividad, se aprecia un manejo sistemático de la institución del precario, pues se desarrollan con claridad los tres requisitos del art. 2195 del Código Civil y se fundamenta de forma coherente la procedencia de la acción. El análisis ético es muy completo, al incorporar conceptos avanzados como seguridad jurídica, distinción entre derechos reales y personales, y al reflexionar críticamente sobre la función judicial en la resolución de conflictos. Destaca especialmente la precisión al diferenciar derechos reales y personales, lo cual revela un nivel conceptual valioso. Asimismo, la correlación con John Finnis es pertinente al identificar los dos elementos constitutivos del matrimonio (amistad/fides y procreación), aunque este punto pudo desarrollarse con mayor profundidad académica y filosófica. Para perfeccionar, convendría mejorar el registro formal de la escritura de manera consistente y corregir detalles menores de redacción, además de ampliar el análisis filosófico de Finnis en conexión con el razonamiento judicial. En la segunda actividad, el/la estudiante muestra honestidad intelectual, al reconocer que el proyecto no utiliza explícitamente el término “género” pero sí logra identificar medidas específicas relevantes, como la protección reforzada en casos de violencia intrafamiliar, conectándola con un impacto diferenciado en mujeres, niñas y adolescentes. De particular valor es la conexión establecida entre el estallido social de 2019 y la crisis de confianza institucional, lo que demuestra comprensión del contexto político y social chileno actual. Sin embargo, las fortalezas conceptuales se ven debilitadas por problemas de redacción, errores ortográficos y limitaciones en el uso del lenguaje jurídico técnico, lo que compromete la claridad y el profesionalismo de la comunicación. Aunque las respuestas son conceptualmente correctas, carecen de precisión terminológica y profundidad analítica suficiente para alcanzar un nivel superior. Para mejorar, se hace necesario fortalecer las habilidades de redacción académica, ampliar el vocabulario técnico jurídico y profundizar en el análisis crítico, especialmente en torno a las implicancias normativas y sociales del proyecto de ley y su vinculación con estándares internacionales.
A77: 21392244 | B77: 0 | C77: JOSEFINA IGNACIA PALACIOS BASTÍAS | D77: PALACIOS | E77: BASTÍAS | F77: JOSEFINA IGNACIA | G77: Avance curricular suficiente o adecuado para evaluar ciclo básico | H77: Rendida | I77: 45758 | K77: 2 | L77: 3 | M77: 3 | N77: 3 | O77: 2 | P77: 3 | Q77: 2 | R77: 3 | S77: =SUM(K77:R77) -> 21 | T77: =S77/40 -> 0.525 | U77: =IF(H77="Rendida ",IF('Resultados Individuales'!T77<49.5%,"Por Mejorar",IF('Resultados Individuales'!T77<64.5%,"Base",IF('Resultados Individuales'!T77<84.5%,"Satisfactorio","Óptimo"))),"No rendida o no válida") -> Base | V77: El desempeño refleja una comprensión inicial adecuada de las instituciones analizadas y un esfuerzo por adoptar posturas éticas y jurídicas claras, aunque persisten deficiencias técnicas y de profundidad analítica que limitan el nivel de logro alcanzado en el perfil intermedio de la formación en Derecho. En la primera actividad, se valora el posicionamiento ético crítico adoptado, cuestionando la interpretación del tribunal bajo el principio de seguridad jurídica y reconociendo la tensión entre valores ético‑morales y derecho positivo. Se aprecia además la identificación correcta de la conexión entre Finnis y el tribunal, subrayando el matrimonio como institución basada en compromiso y confianza y señalando que la resolución judicial refleja la ideología filosófica de Finnis sobre la necesidad de una protección más allá del marco legal. El trabajo utiliza un lenguaje jurídico básico apropiado y mantiene una estructura coherente y de calidad formal aceptable. Sin embargo, se constatan problemas técnicos significativos: existe confusión sobre los elementos del precario, al interpretar erróneamente la relación de la ocupación con el contrato de compraventa; no se desarrollan de manera sistemática los tres requisitos copulativos del art. 2195 del Código Civil; y no se incorporan de modo específico ni ordenado conceptos solicitados como la interpretación extensiva o la analogía. Para mejorar, es indispensable corregir las bases técnicas del análisis del precario, sistematizar el desarrollo de los tres requisitos institucionales, e integrar conceptos técnicos de manera rigurosa y explícita dentro del razonamiento ético‑jurídico. En la segunda actividad, describe con claridad los mecanismos de participación de NNA (derecho a ser oído, obligación de motivación y audiencias adaptadas), vinculándolos correctamente con la autonomía progresiva y los estándares internacionales de derechos de la infancia. Asimismo, destaca apropiadamente la función transformadora del tribunal en la protección de mujeres, niñas y adolescentes en contextos de violencia, señalando su rol estructural frente a desigualdades. No obstante, el análisis presenta limitaciones relevantes: el enfoque de género se mantiene en un plano general, sin citar disposiciones normativas concretas, y la perspectiva interseccional es débil, al no integrar cómo variables como género, clase, edad o etnia se articulan en el acceso a la justicia. Aunque el uso del lenguaje jurídico es sólido, la fundamentación requiere mayor fuerza mediante citas directas a artículos de la Ley N° 21.430, la Convención sobre los Derechos del Niño y la Constitución Política de la República.
A78: 21396299 | B78: K | C78: ISIDORA ANTONIA ARAYA GÓMEZ | D78: ARAYA | E78: GÓMEZ | F78: ISIDORA ANTONIA | G78: Avance curricular suficiente o adecuado para evaluar ciclo básico | H78: Rendida | I78: 45758 | K78: 4 | L78: 3 | M78: 3 | N78: 3 | O78: 2 | P78: 2 | Q78: 3 | R78: 3 | S78: =SUM(K78:R78) -> 23 | T78: =S78/40 -> 0.575 | U78: =IF(H78="Rendida ",IF('Resultados Individuales'!T78<49.5%,"Por Mejorar",IF('Resultados Individuales'!T78<64.5%,"Base",IF('Resultados Individuales'!T78<84.5%,"Satisfactorio","Óptimo"))),"No rendida o no válida") -> Base | V78: El desempeño en ambas actividades muestra solidez conceptual y manejo adecuado del lenguaje jurídico, lo que refleja un dominio formativo importante. Sin embargo, persisten limitaciones analíticas y de profundidad crítica que es necesario corregir para avanzar hacia un nivel plenamente competente dentro del perfil intermedio de Derecho. En la primera actividad, se observa un conocimiento claro y correcto del artículo 2195 del Código Civil, aplicándolo textualmente para fundamentar la procedencia del precario y distinguiendo con precisión que el matrimonio no genera título sobre bienes adquiridos por un tercero después del cambio de dominio. El análisis ético resalta la importancia de la seguridad jurídica y el principio de legalidad, advirtiendo los riesgos de anteponer motivaciones morales a la norma, lo que muestra criterio técnico y crítico bien orientado. Asimismo, la conexión con John Finnis es pertinente al reconocer el matrimonio como bien humano básico. También se destaca el lenguaje jurídico formal y claro, acompañado de una redacción que cumple estándares académicos. No obstante, el trabajo presenta vacíos analíticos: no desarrolla conceptos sugeridos por la consigna como interpretación extensiva, analogía e incorrecta aplicación del derecho, y la relación con Finnis, si bien correcta en lo general, carece de profundidad académica, al no explicitar los dos elementos constitutivos centrales (fides y procreación). En la segunda actividad, se aprecia un uso adecuado del lenguaje técnico, con aplicación correcta de categorías como sujetos de derechos, autonomía progresiva, debido proceso e interés superior del niño, reflejando comprensión sólida del marco normativo. Se identifican de forma precisa los mecanismos de participación de NNA, vinculándolos correctamente con el debido proceso y la capacitación permanente del sistema judicial. Es un acierto notable su contextualización histórica, al mencionar la crisis del ex‑SENAME y las propuestas constitucionales recientes como motivaciones legislativas concretas. Además, se reconoce pensamiento crítico en la observación acerca de la ausencia de una referencia explícita a la desigualdad de género en el proyecto, señalando la contingencia de su interpretación judicial. Sin embargo, el análisis de género e interseccionalidad es limitado y más declarativo que analítico: aunque se reconoce la existencia de desigualdades estructurales y “complejas relaciones de género”, no se profundiza en cómo el proceso judicial podría contribuir a transformarlas estructuralmente, ni se conecta estas medidas con estándares internacionales como la CEDAW o la Convención sobre los Derechos del Niño.
A79: 21402399 | B79: 7 | C79: MARTÍN EDUARDO MOREIRA BASCUR | D79: MOREIRA | E79: BASCUR | F79: MARTÍN EDUARDO | G79: Avance curricular suficiente o adecuado para evaluar ciclo básico | H79: Rendida | I79: 45758 | K79: 4 | L79: 4 | M79: 4 | N79: 4 | O79: 2 | P79: 2 | Q79: 1 | R79: 3 | S79: =SUM(K79:R79) -> 24 | T79: =S79/40 -> 0.6 | U79: =IF(H79="Rendida ",IF('Resultados Individuales'!T79<49.5%,"Por Mejorar",IF('Resultados Individuales'!T79<64.5%,"Base",IF('Resultados Individuales'!T79<84.5%,"Satisfactorio","Óptimo"))),"No rendida o no válida") -> Base | V79: El desempeño presenta un contraste significativo entre ambas actividades: mientras en la primera evidencia un nivel de excelencia académica y profesional sobresaliente, en la segunda el análisis resulta básico y con carencias críticas en el enfoque requerido. En la primera actividad, el análisis destaca por su dominio técnico jurídico impecable, con cita expresa del art. 2195 del Código Civil y desarrollo exhaustivo de los tres requisitos copulativos del precario, argumentando con precisión que el vínculo matrimonial, al extinguirse patrimonialmente con la enajenación del bien, no confiere título o derecho perpetuo frente a terceros adquirentes, configurándose así la institución del precario de manera técnicamente correcta. El posicionamiento ético‑crítico es excepcional, al identificar con solvencia tensiones entre justicia social/material y derecho positivo, analizando conceptos complejos como la interpretación extensiva, la incorrecta aplicación del derecho y la vulneración de la seguridad jurídica. Este análisis reconoce que consideraciones morales o de equidad no deben desplazar normas claras cuando ello compromete la certeza jurídica de terceros. Además, se observa una correlación conceptual magistral con Finnis, integrando el matrimonio como bien humano básico y conectándolo con el razonamiento judicial, que trasciende lo patrimonial para incorporar dimensiones éticas y relacionales. El uso del lenguaje jurídico especializado es de alta precisión técnica, confirmando un desempeño que proyecta plena madurez académica y profesional. En la segunda actividad, sin embargo, el nivel de logro es básico. Si bien, maneja adecuadamente el lenguaje jurídico y logra identificar elementos relevantes del proyecto de ley —como la protección reforzada en casos de violencia intrafamiliar—, se evidencia una comprensión insuficiente del enfoque de género, al confundir la neutralidad terminológica (empleo de “NNA”) con la perspectiva de género propiamente dicha. Asimismo, no se desarrolla un análisis crítico de las desigualdades estructurales que afectan a mujeres, niñas y adolescentes en contextos de familia, ni se incorpora una auténtica perspectiva interseccional que integre variables sociales como género, edad, clase y etnia en el acceso a la justicia. La debilidad más relevante radica en la interpretación errónea de que la mera terminología inclusiva equivale, por sí sola, a un enfoque de género, lo que reduce la profundidad del análisis.
A80: 21408019 | B80: 2 | C80: ANGEL BENJAMÍN BASTÍAS CARRILLO | D80: BASTÍAS | E80: CARRILLO | F80: ANGEL BENJAMÍN | G80: Avance curricular suficiente o adecuado para evaluar ciclo básico | H80: Rendida | I80: 45758 | K80: 2 | L80: 3 | M80: 2 | N80: 3 | O80: 2 | P80: 3 | Q80: 1 | R80: 3 | S80: =SUM(K80:R80) -> 19 | T80: =S80/40 -> 0.475 | U80: =IF(H80="Rendida ",IF('Resultados Individuales'!T80<49.5%,"Por Mejorar",IF('Resultados Individuales'!T80<64.5%,"Base",IF('Resultados Individuales'!T80<84.5%,"Satisfactorio","Óptimo"))),"No rendida o no válida") -> Por Mejorar | V80: Correo
A81: 21410311 | B81: 7 | C81: CATALINA BELÉN CARRILLO GUTIÉRREZ | D81: CARRILLO | E81: GUTIÉRREZ | F81: CATALINA BELÉN | G81: Avance curricular suficiente o adecuado para evaluar ciclo básico | H81: Rendida | I81: 45758 | K81: 4 | L81: 4 | M81: 4 | N81: 4 | O81: 4 | P81: 2 | Q81: 3 | R81: 2 | S81: 27 | T81: =S81/40 -> 0.675 | U81: =IF(H81="Rendida ",IF('Resultados Individuales'!T81<49.5%,"Por Mejorar",IF('Resultados Individuales'!T81<64.5%,"Base",IF('Resultados Individuales'!T81<84.5%,"Satisfactorio","Óptimo"))),"No rendida o no válida") -> Satisfactorio | V81: El desempeño refleja un nivel avanzado y sólido de formación jurídica, con un dominio sobresaliente en el análisis técnico y una escritura académica clara y precisa. Sin embargo, persisten aspectos por fortalecer en la dimensión crítica vinculada al enfoque de género e interseccionalidad, necesarios para alcanzar un rendimiento de excelencia integral dentro del perfil intermedio de la carrera. En la primera actividad, demuestra un manejo técnico sobresaliente de la institución del precario, desarrollando de manera sistemática los tres requisitos copulativos del art. 2195 del CC y fundamentando con rigor la procedencia de la acción tras la extinción del vínculo jurídico patrimonial derivado de la enajenación del inmueble. Su análisis ético es de alto nivel, integrando conceptos avanzados como la seguridad jurídica, la interpretación extensiva y la certeza normativa, para reflexionar sobre la tensión entre derecho positivo y principios éticos. El abordaje del pensamiento de John Finnis es académicamente brillante, al establecer conexiones precisas entre la filosofía del derecho y el razonamiento judicial, aportando profundidad conceptual sin caer en meros formalismos. El lenguaje jurídico es técnico, preciso y apropiado, y la calidad formal del escrito es impecable, proyectando plena competencia profesional. En la segunda actividad, también muestra un manejo adecuado de los mecanismos procesales, describiendo con precisión el derecho a ser oído, la obligación judicial de motivación y el principio de la autonomía progresiva, así como la función del abogado/a defensor/a de derechos en el marco del interés superior del niño. Esto evidencia un dominio claro del debido proceso y del lenguaje jurídico técnico. Sin embargo, el análisis del enfoque de género se queda en un nivel general, sin referencia normativa específica a medidas diferenciadas tales como protocolos o capacitaciones obligatorias en perspectiva de género. Asimismo, el trabajo no articula de manera suficiente los instrumentos internacionales pertinentes (ej. Convención de Belém do Pará, CEDAW), lo que habría enriquecido notablemente la fundamentación. La mención interseccional resulta aislada, sin ejemplificar cómo las categorías de género, edad, etnia o condición socioeconómica se cruzan en la práctica judicial ni cómo el proyecto busca abordarlas conjuntamente.
A82: 21414944 | B82: 3 | C82: CATALINA IGNACIA MORENO ACEVEDO | D82: MORENO | E82: ACEVEDO | F82: CATALINA IGNACIA | S82: =SUM(K82:R82) -> 0 | T82: =S82/40 -> 0 | U82: =IF(H82="Rendida ",IF('Resultados Individuales'!T82<49.5%,"Por Mejorar",IF('Resultados Individuales'!T82<64.5%,"Base",IF('Resultados Individuales'!T82<84.5%,"Satisfactorio","Óptimo"))),"No rendida o no válida") -> No rendida o no válida
A83: 21415871 | B83: K | C83: MILLARAY ALEN GÓMEZ ORTEGA | D83: GÓMEZ | E83: ORTEGA | F83: MILLARAY ALEN | G83: Avance curricular suficiente o adecuado para evaluar ciclo básico | H83: Rendida | I83: 45758 | K83: 4 | L83: 4 | M83: 4 | N83: 4 | O83: 3 | P83: 3 | Q83: 3 | R83: 4 | S83: =SUM(K83:R83) -> 29 | T83: =S83/40 -> 0.725 | U83: =IF(H83="Rendida ",IF('Resultados Individuales'!T83<49.5%,"Por Mejorar",IF('Resultados Individuales'!T83<64.5%,"Base",IF('Resultados Individuales'!T83<84.5%,"Satisfactorio","Óptimo"))),"No rendida o no válida") -> Satisfactorio | V83: El desempeño evidencia un nivel sobresaliente de dominio técnico y analítico en la primera actividad, acompañado de un desempeño sólido y riguroso en la segunda, aunque con posibilidades de profundización normativa y práctica para alcanzar la excelencia en todas las dimensiones. En la primera actividad, se observa una argumentación jurídica impecable, al distinguir de manera magistral los efectos del matrimonio entre cónyuges y frente a terceros adquirentes, cuestión particularmente compleja del derecho civil. El análisis ético‑crítico es de un nivel excepcionalmente sofisticado, evaluando con rigor la tensión entre justicia material y coherencia del sistema jurídico, e integrando conceptos avanzados como la interpretación extensiva, la seguridad jurídica y la analogía. Asimismo, se establece una conexión conceptual perfecta con la filosofía de Finnis, explicando con profundidad cómo la concepción del matrimonio como “bien humano básico” se expresa en la protección judicial, con proyección ética y social. El lenguaje jurídico empleado es técnico y especializado, reflejando pleno dominio de la terminología avanzada, y la calidad formal del escrito es impecable, cumpliendo con los más altos estándares académicos. En la segunda actividad, desarrolla un análisis igualmente coherente, explicando con claridad los mecanismos de participación de NNA, el enfoque de género y la vinculación con el debido proceso, todo ello en un registro de lenguaje jurídico riguroso y pertinente. Destaca la fundamentación adecuada de las decisiones judiciales y la articulación explícita con estándares internacionales, como la Convención Americana sobre Derechos Humanos. Sin embargo, para consolidar un nivel óptimo integral, se recomienda incorporar citas directas a artículos específicos del proyecto de ley y de los tratados internacionales más directamente aplicables (ej. CEDAW o Convención sobre los Derechos del Niño), así como enriquecer la reflexión con ejemplos prácticos que ilustren el impacto de las medidas en realidades concretas, como casos de violencia intrafamiliar o contextos de exclusión social.
A84: 21417793 | B84: 5 | C84: ROMINA BELÉN MUÑOZ ALVIAL | D84: MUÑOZ | E84: ALVIAL | F84: ROMINA BELÉN | G84: Avance curricular suficiente o adecuado para evaluar ciclo básico | H84: Rendida | I84: 45758 | K84: 4 | L84: 4 | M84: 4 | N84: 4 | O84: 2 | P84: 2 | Q84: 3 | R84: 3 | S84: =SUM(K84:R84) -> 26 | T84: =S84/40 -> 0.65 | U84: =IF(H84="Rendida ",IF('Resultados Individuales'!T84<49.5%,"Por Mejorar",IF('Resultados Individuales'!T84<64.5%,"Base",IF('Resultados Individuales'!T84<84.5%,"Satisfactorio","Óptimo"))),"No rendida o no válida") -> Satisfactorio | V84: El desempeño de la estudiante refleja un nivel altamente competente y avanzado en la primera actividad, con un manejo jurídico excepcional, y un rendimiento intermedio en la segunda, donde si bien existen fortalezas notables, aún persisten limitaciones en la profundidad analítica respecto del enfoque de género y las desigualdades estructurales. En la primera actividad, la estudiante demuestra un dominio absoluto de análisis técnico jurídico, evaluando de manera impecable la idoneidad del precario con cita explícita al art. 2195 del Código Civil (primer inciso). Desarrolla una argumentación técnicamente sólida sobre los tres elementos fundamentales: la ausencia de justificación válida y razonable, la no existencia de tiempo específico para restitución, y un razonamiento sofisticado según el cual el conocimiento previo de la condición de bien familiar no impide la configuración del precario. El posicionamiento ético es excepcional, al identificar la incorrecta aplicación del derecho y examinar con profundidad la vulneración de facultades de dominio y seguridad jurídica, integrando los conceptos técnicos solicitados en la consigna de manera desarrollada y clara. Además, establece una correlación conceptual magistral con John Finnis, relacionando el matrimonio como bien humano básico para la realización plena con la justificación judicial utilizada para privilegiar los derechos conyugales frente a las facultades dominicales de la propietaria. Su lenguaje jurídico es de alta precisión técnica, con un uso especializado de la terminología, estructura metodológica sofisticada, sistema de citas bibliográficas profesional y calidad formal impecable, lo que refleja un pensamiento jurídico avanzado de nivel superior. En la segunda actividad, la estudiante alcanza un nivel intermedio de logro. Entre sus fortalezas destaca el uso sólido del lenguaje jurídico y el reconocimiento explícito de la perspectiva interseccional, siendo relevante que es la única que emplea este concepto clave. Ello demuestra sensibilidad hacia la complejidad social del derecho y proyección a un análisis multidimensional de acceso a la justicia. Sin embargo, el tratamiento del enfoque de género y las desigualdades estructurales se mantiene en un plano más descriptivo que crítico. Pese a que su comprensión procesal es adecuada y la terminología técnica se maneja correctamente, falta mayor articulación sobre cómo las medidas del proyecto de ley impactan específica y concretamente en mujeres, niñas y adolescentes en contextos familiares. La ausencia de ejemplos prácticos y de referencias normativas específicas (ej. CEDAW, Belém do Pará, Convención sobre los Derechos del Niño) limita la profundidad del análisis y la evaluación integral de la propuesta legislativa.
A85: 21432883 | B85: 6 | C85: SOFÍA ANTONIA PACHECO PARRA | D85: PACHECO | E85: PARRA | F85: SOFÍA ANTONIA | G85: Avance curricular suficiente o adecuado para evaluar ciclo básico | H85: Rendida | I85: 45758 | K85: 3 | L85: 2 | M85: 3 | N85: 3 | O85: 2 | P85: 3 | Q85: 2 | R85: 3 | S85: =SUM(K85:R85) -> 21 | T85: =S85/40 -> 0.525 | U85: =IF(H85="Rendida ",IF('Resultados Individuales'!T85<49.5%,"Por Mejorar",IF('Resultados Individuales'!T85<64.5%,"Base",IF('Resultados Individuales'!T85<84.5%,"Satisfactorio","Óptimo"))),"No rendida o no válida") -> Base | V85: El desempeño de la estudiante evidencia comprensión de los fundamentos centrales de las instituciones abordadas y un uso adecuado de lenguaje jurídico básico, pero aún presenta deficiencias técnicas, analíticas y formales que afectan la claridad y solidez del trabajo presentado. En la primera actividad, se valora positivamente la citación expresa al art. 2195 del Código Civil y la conclusión técnica coherente de que “se configuran los tres casos que debe tener el precario: dominio, ocupación y ausencia de un nexo jurídico”. También se aprecia la incorporación de la reflexión de Finnis sobre el matrimonio como bien humano básico y el reconocimiento de que el hogar compartido trasciende lo meramente patrimonial. El uso de terminología jurídica básica es correcto y demuestra comprensión conceptual general de la institución. Sin embargo, el análisis presenta deficiencias significativas: se observan contradicciones internas al calificar en un momento la interpretación del tribunal como “acertada” y después como “errónea”, lo que genera un posicionamiento ético‑jurídico confuso. Asimismo, no se integran conceptos técnicos solicitados (interpretación extensiva, analogía, incorrecta aplicación del derecho) de manera sistemática, y la correlación conceptual con Finnis queda en un nivel muy básico y sin profundidad académica. Además, los errores de redacción y concordancia (“na aplicación del derecho”, “jurídicamente aplicare el precario”) comprometen seriedad y profesionalismo del texto. Para mejorar, se requiere: coherencia argumentativa eliminando contradicciones, inclusión ordenada de los conceptos técnicos, profundización analítica y un mejoramiento sustancial de la formalidad y corrección redaccional. En la segunda actividad, el desempeño es más sólido. La estudiante describe con claridad los mecanismos de participación de NNA —derecho a ser oído, obligación de motivación y audiencias adaptadas—, vinculándolos correctamente con la autonomía progresiva y con estándares internacionales de derechos del niño. Se destaca la identificación del rol transformador del tribunal en la protección de mujeres, niñas y adolescentes en contextos de violencia, reconociendo su función estructural correctora. Sin embargo, el análisis de género es insuficiente, ya que no se citan disposiciones normativas concretas ni instrumentos especializados (CEDAW, Convención de Belém do Pará). A su vez, la perspectiva interseccional se presenta de manera superficial, sin examinar cómo interactúan otras variables sociales como género, clase, edad o etnia. Si bien el uso del lenguaje jurídico es correcto, la fundamentación se beneficiaría de citas específicas a artículos de la Ley N° 21.430, la Convención sobre los Derechos del Niño y la Constitución.
A86: 21444392 | B86: 9 | C86: ISIDORA EMMA IBÁÑEZ CAMPUSANO | D86: IBÁÑEZ | E86: CAMPUSANO | F86: ISIDORA EMMA | G86: Avance curricular suficiente o adecuado para evaluar ciclo básico | H86: Rendida | I86: 45758 | K86: 4 | L86: 4 | M86: 4 | N86: 3 | O86: 2 | P86: 2 | Q86: 1 | R86: 3 | S86: =SUM(K86:R86) -> 23 | T86: =S86/40 -> 0.575 | U86: =IF(H86="Rendida ",IF('Resultados Individuales'!T86<49.5%,"Por Mejorar",IF('Resultados Individuales'!T86<64.5%,"Base",IF('Resultados Individuales'!T86<84.5%,"Satisfactorio","Óptimo"))),"No rendida o no válida") -> Base | V86: El trabajo refleja un alto nivel de dominio técnico-jurídico y capacidad analítica avanzada en la primera actividad, mientras que en la segunda evidencia un buen manejo conceptual, pero con limitaciones en la profundidad crítica y en la aplicación de marcos normativos internacionales que resultan claves para alcanzar un desempeño superior. En la primera actividad, el análisis merece una evaluación muy destacada. Desarrolla una argumentación jurídica impecable, distinguiendo de forma clara y magistral entre vínculos personales y derechos reales, distinción esencial en el derecho civil. Su análisis crítico es excepcionalmente sofisticado, demostrando plena conciencia de la confusión entre moral y derecho y de los efectos que dicha confusión provoca sobre principios fundamentales como la certeza jurídica, la legalidad y el derecho de propiedad. Asimismo, logra establecer conexiones conceptuales precisas entre la filosofía de John Finnis y el razonamiento del tribunal, explicando con profundidad cómo esta filosofía se aplica al caso concreto y cómo el matrimonio como bien humano básico puede ser interpretado en clave jurídica y ética. El uso del lenguaje jurídico es técnico y avanzado, y la estructura argumentativa refleja un pensamiento maduro y coherente. La única área de mejora corresponde a aspectos formales menores de ortografía, que no comprometen de forma alguna la excelencia y profesionalismo del contenido. En la segunda actividad, demuestra un manejo claro de los mecanismos de participación (derecho a ser oído, obligación de motivación y audiencias adaptadas), utilizando un lenguaje jurídico adecuado y vinculando su explicación con la Convención sobre los Derechos del Niño. Sin embargo, el análisis del enfoque de género y de las desigualdades estructurales resulta superficial, al no detallar medidas procesales específicas ni articular su relación con protocolos de género o con estándares internacionales como la CEDAW. Del mismo modo, la perspectiva interseccional no se desarrolla plenamente, quedando en un plano declarativo. Para consolidar un nivel óptimo en toda la rúbrica, sería necesario articular cómo diversas categorías sociales (género, clase, edad, etnia, etc.) se intersectan en la práctica judicial y reforzar la fundamentación mediante citas específicas al proyecto de ley y a tratados internacionales relevantes.
A87: 21446302 | B87: 4 | C87: JOSEFA ANTONIA LEAL CASTRO | D87: LEAL | E87: CASTRO | F87: JOSEFA ANTONIA | G87: Avance curricular suficiente o adecuado para evaluar ciclo básico | H87: Rendida | I87: 45758 | K87: 3 | L87: 3 | M87: 4 | N87: 3 | O87: 1 | P87: 2 | Q87: 1 | R87: 3 | S87: =SUM(K87:R87) -> 20 | T87: =S87/40 -> 0.5 | U87: =IF(H87="Rendida ",IF('Resultados Individuales'!T87<49.5%,"Por Mejorar",IF('Resultados Individuales'!T87<64.5%,"Base",IF('Resultados Individuales'!T87<84.5%,"Satisfactorio","Óptimo"))),"No rendida o no válida") -> Base | V87: El desempeño revela altas competencias jurídicas y analíticas en la primera actividad, con un nivel de madurez conceptual notable, mientras que en la segunda muestra comprensión procesal suficiente pero aún con limitaciones en materia de género, desigualdad estructural e interseccionalidad que requieren reforzamiento para alcanzar un desempeño integral de excelencia. En la primera actividad, desarrolla un análisis excepcional, identificando y relacionando con precisión las motivaciones de Finnis como contenidos implícitos en el razonamiento del tribunal. Esta conexión entre filosofía del derecho y jurisprudencia ilustra de manera ejemplar cómo el matrimonio como bien humano básico se materializa en la protección del inmueble como símbolo tangible de la vida compartida y la procreación, integrando correctamente razón filosófica y contexto jurídico. Entre las grandes fortalezas se encuentran: la adopción de posturas claras y fundamentadas en torno a la procedencia del precario, con referencia normativa adecuada, la correcta incorporación de conceptos técnicos avanzados como error de derecho e ineficacia en la valoración de la prueba, y el acertado reconocimiento de la tensión entre la protección familiar y los nexos jurídicos formales. Las áreas de mejora se concentran en: (i) perfeccionar la precisión técnica en la argumentación sobre precario, evitando confusiones conceptuales menores; (ii) profundizar aún más en el análisis ético incorporando de manera explícita nociones como interpretación extensiva y seguridad jurídica; y (iii) refinar ciertas expresiones técnicas para garantizar precisión terminológica superior. En la segunda actividad, comprende de manera clara los mecanismos principales de participación procesal de NNA y las obligaciones de fundamentación judicial, utilizando un lenguaje técnico apropiado. Sin embargo, su análisis en materia de enfoque de género y desigualdades estructurales resulta muy superficial, sin articularse adecuadamente con estándares internacionales ni con protocolos concretos de género. Tampoco se desarrolla una auténtica perspectiva interseccional, quedándose en un nivel descriptivo. Para mejorar, se recomienda: (i) incorporar protocolos normativos específicos de perspectiva de género en sede judicial, (ii) citar instrumentos internacionales aplicables como la CEDAW y la Convención sobre los Derechos del Niño, y (iii) explicar cómo distintas categorías sociales (género, edad, clase, etnia, etc.) se cruzan en la práctica judicial, afectando directamente la experiencia procesal de niños, niñas y adolescentes.
A88: 21449321 | B88: 7 | C88: MACARENA ALEJANDRA ALARCÓN HERRERA | D88: ALARCÓN | E88: HERRERA | F88: MACARENA ALEJANDRA | G88: Avance curricular suficiente o adecuado para evaluar ciclo básico | H88: Rendida | I88: 45758 | K88: 4 | L88: 3 | M88: 3 | N88: 3 | O88: 1 | P88: 1 | Q88: 1 | R88: 2 | S88: =SUM(K88:R88) -> 18 | T88: =S88/40 -> 0.45 | U88: =IF(H88="Rendida ",IF('Resultados Individuales'!T88<49.5%,"Por Mejorar",IF('Resultados Individuales'!T88<64.5%,"Base",IF('Resultados Individuales'!T88<84.5%,"Satisfactorio","Óptimo"))),"No rendida o no válida") -> Por Mejorar | V88: El desempeño refleja diferencias notables entre ambas actividades: mientras en la primera actividad se logra un análisis sólido y técnicamente correcto, en la segunda se evidencian deficiencias graves de comprensión conceptual y de expresión escrita que comprometen la calidad general del trabajo. En la primera actividad, aplica con rigor el artículo 2195 del Código Civil, fundamentando de manera clara la procedencia del precario. El análisis ético es pertinente, pues subraya que no deben anteponerse motivaciones morales a la norma positiva, defendiendo así el principio de seguridad jurídica. Además, la conexión con Finnis resulta adecuada al reconocer el matrimonio como bien humano básico, y la calidad formal del texto —en lenguaje y presentación— se considera sobresaliente. Sin embargo, se detectan áreas de mejora relevantes: el análisis omite nociones técnicas sugeridas por la consigna (interpretación extensiva, analogía, incorrecta aplicación del derecho) que habrían enriquecido el posicionamiento crítico. Asimismo, la relación con Finnis es superficial, pues no desarrolla los elementos constitutivos del matrimonio (fides y procreación), ni los refleja explícitamente en su conexión con el quinto considerando de la sentencia. Para avanzar, es indispensable incorporar ejemplos aplicados al precario al usar conceptos técnicos, y profundizar en la filosofía matrimonial de Finnis estableciendo claramente cómo se conecta con la justificación judicial. En la segunda actividad, si bien demuestra cierta comprensión básica de los mecanismos procesales, identificando correctamente las audiencias específicas para NNA y la obligación de fundamentación judicial, además de reconocer la crisis del SENAME como motivación legislativa pertinente, las limitaciones son severas. La parte más crítica es la confusión conceptual en la pregunta 2, donde erróneamente afirma que el proyecto “garantiza una desigualdad estructural”, lo que contradice el propósito de la normativa y evidencia una falta de comprensión básica sobre enfoque de género y desigualdades estructurales. Tampoco se identifican las medidas específicas del proyecto en favor de mujeres, niñas y adolescentes, y la referencia a la interseccionalidad carece de desarrollo y aplicación práctica. A lo anterior se suman serias dificultades de expresión escrita, con frases ambiguas y redacción confusa (“generarse ambientes”, “una ayuda legítima”) que afectan la claridad comunicativa.
A89: 21452810 | B89: K | C89: GERALDINE ESPERANZA SALAS CASTILLO | D89: SALAS | E89: CASTILLO | F89: GERALDINE ESPERANZA | G89: Avance curricular suficiente o adecuado para evaluar ciclo básico | H89: Rendida | I89: 45758 | K89: 2 | L89: 2 | M89: 3 | N89: 2 | O89: 2 | P89: 2 | Q89: 2 | R89: 3 | S89: =SUM(K89:R89) -> 18 | T89: =S89/40 -> 0.45 | U89: =IF(H89="Rendida ",IF('Resultados Individuales'!T89<49.5%,"Por Mejorar",IF('Resultados Individuales'!T89<64.5%,"Base",IF('Resultados Individuales'!T89<84.5%,"Satisfactorio","Óptimo"))),"No rendida o no válida") -> Por Mejorar | V89: El desempeño muestra un contraste importante entre las dos actividades: la primera evidencia graves deficiencias conceptuales, formales y técnicas, mientras que la segunda, aunque correcta en algunos aspectos básicos, carece de la profundidad crítica y normativa necesaria para alcanzar un nivel óptimo. En la primera actividad, se constata una confusión conceptual seria sobre la institución del precario, al definir incorrectamente la exigencia de “sin previo contrato”. El desarrollo argumentativo es superficial y limitado, ya que no incorpora de forma sistemática los conceptos técnicos solicitados como interpretación extensiva, analogía, seguridad jurídica o incorrecta aplicación del derecho. Además, se observa un uso impreciso del lenguaje jurídico, empleando terminología básica de manera errada. La calidad formal del escrito es deficiente, con múltiples errores de puntuación, concordancia y redacción que comprometen la claridad y la profesionalidad del trabajo. La única fortaleza relativa se encuentra en la conexión básica establecida entre la filosofía de Finnis y el razonamiento del tribunal, aunque de manera muy incipiente. Para mejorar, será imprescindible: (i) un estudio sistemático de la institución del precario y sus requisitos; (ii) la incorporación de conceptos técnicos avanzados en la argumentación; (iii) la precisión en el uso de terminología jurídica; y (iv) una revisión integral de la escritura académica para eliminar errores graves de forma. En la segunda actividad, se observa un desempeño más sólido en lo conceptual, ya que identifica correctamente los mecanismos de participación de NNA —derecho a ser oído, audiencias adaptadas y obligación de motivación de su opinión—, estableciendo la vinculación con la autonomía progresiva y el interés superior del niño. Sin embargo, el análisis del enfoque de género y de las desigualdades estructurales es excesivamente genérico, pues no cita ni desarrolla disposiciones normativas concretas ni recurre a estándares internacionales (CEDAW, Convención de Belém do Pará, Convención sobre los Derechos del Niño). La perspectiva interseccional apenas se menciona sin elaborar los cruces relevantes entre género, clase, edad o etnia en el acceso a la justicia de NNA. El lenguaje jurídico utilizado es en general adecuado, pero la fundamentación sería más robusta con referencias explícitas a artículos de la Ley N° 21.430, del Código Civil o de instrumentos internacionales en derechos de infancia.
A90: 21452919 | B90: K | C90: EVELYN CRISSNA ANCAVIL HUENTEMILLA | D90: ANCAVIL | E90: HUENTEMILLA | F90: EVELYN CRISSNA | G90: Avance curricular suficiente o adecuado para evaluar ciclo básico | H90: Rendida | I90: 45758 | K90: 4 | L90: 4 | M90: 4 | N90: 4 | O90: 4 | P90: 4 | Q90: 4 | R90: 4 | S90: =SUM(K90:R90) -> 32 | T90: =S90/40 -> 0.8 | U90: =IF(H90="Rendida ",IF('Resultados Individuales'!T90<49.5%,"Por Mejorar",IF('Resultados Individuales'!T90<64.5%,"Base",IF('Resultados Individuales'!T90<84.5%,"Satisfactorio","Óptimo"))),"No rendida o no válida") -> Satisfactorio | V90: El desempeño en ambas actividades refleja un nivel avanzado de análisis jurídico y madurez académica, destacando tanto en el manejo técnico de las instituciones del derecho civil como en la reflexión crítica sobre reformas legislativas en materia de infancia y familia. En la primera actividad, se observa una excelente comprensión de la institución del precario y de sus elementos conforme al artículo 2195 del Código Civil. La estudiante desarrolla una argumentación jurídica sólida y rigurosa, adoptando la posición opuesta al tribunal con fundamentación completa y coherente. Destaca especialmente la conexión específica y detallada con la teoría de John Finnis, reconociendo cómo el matrimonio como bien humano básico se articula con la protección judicial, proyectando así un razonamiento que une teoría académica y práctica jurisdiccional. El uso del lenguaje jurídico técnico es preciso y apropiado, lo que refleja dominio conceptual. El nivel de análisis es avanzado, pues identifica cada elemento del precario y logra integrarlos en el debate doctrinal y jurisprudencial. Como áreas de mejora, se recomienda: (i) profundizar la reflexión ética sobre la justicia de la sentencia, incorporando con mayor amplitud el debate entre derecho positivo, equidad y justicia social; y (ii) perfeccionar aspectos formales de redacción y puntuación para asegurar la máxima claridad comunicativa. En la segunda actividad, alcanza un rendimiento sobresaliente, con un análisis profundo y crítico que trasciende la mera descripción normativa hacia una visión estructural transformadora del rol de los tribunales de familia. Destaca el manejo magistral del enfoque de género e interseccionalidad, al identificar medidas específicas del proyecto como las unidades técnicas especializadas y los curadores ad litem capacitados en derechos de infancia, y al articular con claridad que el proceso judicial debe corregir, y no reproducir, desigualdades estructurales. La perspectiva interseccional es auténtica y sofisticada, considerando explícitamente múltiples variables —género, edad, pobreza, origen étnico— y explicando cómo se entrecruzan para agravar vulnerabilidades. Su manejo del lenguaje jurídico es avanzado, preciso y técnico, con plena conciencia del rol profesional de las/los abogados como agentes de transformación social. La respuesta está, además, enriquecida con una excelente contextualización histórica, vinculando el estallido social de 2019 y la dictación de la Ley N° 21.430 de 2022 como motivaciones legislativas claves
A91: 21454723 | B91: 6 | C91: ESTEBAN NICOLAS MÉNDEZ MUÑOZ | D91: MÉNDEZ | E91: MUÑOZ | F91: ESTEBAN NICOLAS | G91: Avance curricular suficiente o adecuado para evaluar ciclo básico | H91: Rendida | I91: 45758 | K91: 3 | L91: 2 | M91: 3 | N91: 2 | O91: 2 | P91: 2 | Q91: 1 | R91: 2 | S91: =SUM(K91:R91) -> 17 | T91: =S91/40 -> 0.425 | U91: =IF(H91="Rendida ",IF('Resultados Individuales'!T91<49.5%,"Por Mejorar",IF('Resultados Individuales'!T91<64.5%,"Base",IF('Resultados Individuales'!T91<84.5%,"Satisfactorio","Óptimo"))),"No rendida o no válida") -> Por Mejorar | V91: El desempeño del estudiante en ambas actividades evidencia avances parciales en la comprensión de instituciones jurídicas y en el manejo del derecho positivo, pero también deficiencias conceptuales, técnicas y formales relevantes que deben ser corregidas con urgencia para consolidar las competencias propias del perfil intermedio en Derecho. En la primera actividad, se reconoce como fortaleza la adopción de posiciones claras respecto de la procedencia del precario, citando el art. 2195 CC e identificando adecuadamente algunos de sus elementos básicos. También destaca la argumentación sobre la pérdida de facultades tras la venta del inmueble, así como la conexión —aunque inicial y parcial— entre la filosofía de Finnis y el razonamiento del tribunal, reconociendo la importancia del matrimonio desde perspectivas jurídicas y filosóficas. Sin embargo, estas virtudes se ven opacadas por deficiencias conceptuales importantes: se caracteriza erróneamente la ocupación como “por mera tolerancia”, lo que contradice la argumentación necesaria para fundamentar un verdadero caso de precario. El análisis ético es superficial, pues no incorpora conceptos técnicos solicitados (interpretación extensiva, seguridad jurídica, analogía, incorrecta aplicación del derecho), y la terminología jurídica se utiliza de manera imprecisa, lo que compromete la claridad técnica. A lo anterior se suma una calidad formal deficiente, con múltiples errores de puntuación, concordancia y expresiones inadecuadas que afectan el nivel académico del escrito. Para mejorar, el estudiante debe: (i) corregir confusiones conceptuales mediante estudio sistemático de las instituciones básicas; (ii) profundizar en el análisis crítico incorporando conceptos técnicos avanzados; (iii) perfeccionar el uso de la terminología jurídica y la estructura argumentativa; y (iv) elevar sustancialmente la calidad formal y redaccional de la entrega. En la segunda actividad, el desempeño resulta insuficiente para el nivel esperado. Si bien se identifican algunos mecanismos contemplados en el proyecto —como la protección reforzada en violencia intrafamiliar (VIF) y los curadores ad litem especializados en derechos de infancia—, el análisis es superficial y carece de profundidad crítica. No se logra articular de manera coherente el enfoque de género del proyecto de ley, ni se identifican medidas específicas relacionadas con la protección de mujeres, niñas y adolescentes en contextos familiares. La ausencia total de perspectiva interseccional y el tratamiento superficial de las desigualdades estructurales constituyen debilidades significativas que limitan la proyección profesional del análisis. Además, aunque se emplean algunos términos técnicos adecuados, el lenguaje jurídico en general carece de rigor y precisión profesional, quedando por debajo de los estándares académicos de la evaluación.
A92: 21462616 | B92: 0 | C92: ANAÍS POLIETT CASTILLO PUGA | D92: CASTILLO | E92: PUGA | F92: ANAÍS POLIETT | G92: Avance curricular suficiente o adecuado para evaluar ciclo básico | H92: Rendida | I92: 45758 | K92: 2 | L92: 3 | M92: 3 | N92: 2 | O92: 2 | P92: 2 | Q92: 2 | R92: 2 | S92: =SUM(K92:R92) -> 18 | T92: =S92/40 -> 0.45 | U92: =IF(H92="Rendida ",IF('Resultados Individuales'!T92<49.5%,"Por Mejorar",IF('Resultados Individuales'!T92<64.5%,"Base",IF('Resultados Individuales'!T92<84.5%,"Satisfactorio","Óptimo"))),"No rendida o no válida") -> Por Mejorar | V92: El desempeño del estudiante evidencia una comprensión incipiente de los contenidos jurídicos y sociales, pero presenta deficiencias técnicas, conceptuales y formales importantes que comprometen la calidad general de las respuestas. En la primera actividad, se aprecia un esfuerzo por comprender el caso y tomar posición ética al valorar la protección del matrimonio, lo cual refleja cierta coherencia y sensibilidad moral. Asimismo, la correlación con la filosofía de John Finnis es pertinente al reconocer la relevancia del matrimonio como bien humano básico. Sin embargo, el análisis jurídico resulta confuso y carece de sistematicidad: no se desarrollan de manera ordenada los requisitos legales del precario según el art. 2195 del Código Civil, y la argumentación se limita a aspectos narrativos sin profundizar en la estructura normativa. El posicionamiento ético carece de conceptos jurídicos específicos (como seguridad jurídica, interpretación extensiva o analogía) y la relación con Finnis solo aborda parcialmente los elementos constitutivos de fides y procreación. Además, el lenguaje jurídico presenta múltiples imprecisiones, adoptando un registro demasiado informal, y la calidad formal es deficiente, con numerosos errores ortográficos, sintácticos y de construcción que afectan la claridad expositiva. Para mejorar, el estudiante debe: (i) desarrollar sistemáticamente los requisitos del precario con cita expresa al art. 2195 CC, (ii) enriquecer el análisis ético con categorías técnico-jurídicas, (iii) profundizar la aplicación de los elementos de Finnis al considerando quinto, (iv) adoptar un registro más técnico y formal, y (v) corregir errores ortográficos y sintácticos para ajustarse a un estándar académico. En la segunda actividad, se valoran la identificación correcta de fenómenos sociales relevantes, como la violencia intrafamiliar y el maltrato institucional hacia NNA, lo que demuestra sensibilidad hacia los contextos en los que opera el derecho de familia. No obstante, el desarrollo es superficial y carece de profundidad normativa y crítica. Tanto el enfoque de género como la perspectiva interseccional se abordan de manera vaga, sin mencionar medidas concretas ni articular cómo diversas categorías de vulnerabilidad (género, clase, edad, etnia) se cruzan en la práctica procesal. El lenguaje jurídico es limitado y a veces coloquial, reduciendo el rigor profesional esperado. Para mejorar, se recomienda: (i) fortalecer la argumentación con referencias normativas específicas (Ley N° 21.430, CEDAW, Convención sobre los Derechos del Niño), (ii) estructurar un análisis crítico profundo sobre género e interseccionalidad, demostrando cómo el proyecto de ley busca transformar desigualdades estructurales, y (iii) mejorar la precisión terminológica y la formalidad del registro académico.
A93: 21463234 | B93: 9 | C93: GUSTAVO DANIEL ILAN QUEZADA GONZÁLEZ | D93: QUEZADA | E93: GONZÁLEZ | F93: GUSTAVO DANIEL ILAN | S93: =SUM(K93:R93) -> 0 | T93: =S93/40 -> 0 | U93: =IF(H93="Rendida ",IF('Resultados Individuales'!T93<49.5%,"Por Mejorar",IF('Resultados Individuales'!T93<64.5%,"Base",IF('Resultados Individuales'!T93<84.5%,"Satisfactorio","Óptimo"))),"No rendida o no válida") -> No rendida o no válida
A94: 21467178 | B94: 6 | C94: DANIA BELÉN ROJAS SAN MARTÍN | D94: ROJAS | E94: SAN MARTÍN | F94: DANIA BELÉN | G94: Avance curricular suficiente o adecuado para evaluar ciclo básico | H94: Rendida | I94: 45758 | K94: 3 | L94: 3 | M94: 4 | N94: 4 | O94: 2 | P94: 2 | Q94: 2 | R94: 3 | S94: =SUM(K94:R94) -> 23 | T94: =S94/40 -> 0.575 | U94: =IF(H94="Rendida ",IF('Resultados Individuales'!T94<49.5%,"Por Mejorar",IF('Resultados Individuales'!T94<64.5%,"Base",IF('Resultados Individuales'!T94<84.5%,"Satisfactorio","Óptimo"))),"No rendida o no válida") -> Base | V94: El trabajo revela un dominio sólido y avanzado en la primera actividad, con un manejo conceptual y formal notable, mientras que en la segunda actividad, si bien hay claridad en aspectos básicos, el análisis aún requiere mayor profundidad normativa, crítica e interseccional para alcanzar un nivel óptimo en todos los criterios de evaluación. En la primera actividad, destaca la correlación conceptual superior entre la filosofía de Finnis y el razonamiento del tribunal, al establecer que ambas visiones coinciden en otorgar al matrimonio un valor ético y jurídico que trasciende lo contractual o formal. Este enfoque demuestra capacidad analítica avanzada y una adecuada integración entre teoría académica y razonamiento jurisdiccional. El lenguaje jurídico especializado empleado es técnico, riguroso y preciso, y la calidad formal del texto es profesional, sin errores significativos que comprometan claridad o coherencia. Asimismo, la estudiante adopta posturas coherentes sobre la idoneidad del precario y valora de manera equilibrada la interpretación del tribunal como una síntesis entre derecho positivo y justicia social. Como aspecto de mejora, se sugiere: (i) realizar la citación explícita al art. 2195 del Código Civil, desarrollando exhaustivamente cada uno de sus requisitos; y (ii) incorporar de manera sistemática los conceptos técnicos solicitados por la consigna (interpretación extensiva, analogía, seguridad jurídica), lo que elevaría aún más el nivel de solidez jurídica y ética del análisis. En la segunda actividad, cumple correctamente con la identificación de los mecanismos de participación del NNA —derecho a ser oído, audiencias específicas y obligación de motivación judicial—, vinculándolos adecuadamente con la autonomía progresiva y el interés superior del niño. No obstante, el análisis de género y de desigualdades estructurales resulta demasiado genérico, al no precisar disposiciones normativas concretas ni articular con estándares internacionales relevantes (CEDAW, Convención de Belém do Pará, Convención sobre los Derechos del Niño). De igual manera, la perspectiva interseccional es limitada, reducida a la mera mención de organismos intervinientes, sin desarrollar cómo factores sociales como género, edad, pobreza u origen étnico se cruzan en la experiencia judicial. El lenguaje jurídico empleado es adecuado, aunque el análisis se beneficiaría con referencias específicas a artículos de la Ley N° 21.430, el Código Civil o tratados internacionales, para reforzar la fundamentación normativa y elevar la solidez profesional
A95: 21471174 | B95: 5 | C95: CLAUDIO IGNACIO ARANCIBIA VARAS | D95: ARANCIBIA | E95: VARAS | F95: CLAUDIO IGNACIO | G95: Avance curricular suficiente o adecuado para evaluar ciclo básico | H95: Rendida | I95: 45758 | K95: 3 | L95: 3 | M95: 3 | N95: 3 | O95: 2 | P95: 2 | Q95: 1 | R95: 3 | S95: =SUM(K95:R95) -> 20 | T95: =S95/40 -> 0.5 | U95: =IF(H95="Rendida ",IF('Resultados Individuales'!T95<49.5%,"Por Mejorar",IF('Resultados Individuales'!T95<64.5%,"Base",IF('Resultados Individuales'!T95<84.5%,"Satisfactorio","Óptimo"))),"No rendida o no válida") -> Base | V95: El trabajo evidencia un desempeño desigual entre ambas actividades: en la primera demuestra comprensión sólida y argumentación consistente, mientras que en la segunda, a pesar de un buen manejo terminológico y normativo básico, persisten debilidades analíticas críticas que limitan el alcance de la evaluación. En la primera actividad, demuestra un buen dominio de la institución del precario, articulando de forma adecuada los requisitos legales del art. 2195 del Código Civil, y oponiéndose de manera pertinente a la postura del tribunal al criticar su incorrecta aplicación del derecho por privilegiar consideraciones matrimoniales sobre los elementos normativos. Se valora también la conexión conceptual con John Finnis, al reconocer el matrimonio como bien humano básico y relacionarlo con la valoración ética y jurídica de la casa común. El uso del lenguaje jurídico es claro y con rigor técnico. Sin embargo, para alcanzar un nivel óptimo, resulta fundamental (i) precisar con más claridad la operatividad de la “mera tolerancia” como elemento del precario, (ii) enriquecer la reflexión ética con conceptos técnicos específicos como seguridad jurídica y analogía, y (iii) profundizar en la correlación académica entre los dos fines propuestos por Finnis (fides y procreación) y el considerando quinto de la sentencia, a fin de robustecer la integración entre filosofía y derecho positivo. En la segunda actividad, se evidencian fortalezas en el uso del lenguaje jurídico técnico, empleando de forma adecuada expresiones como “sujetos de derecho”, “hechos fácticos y jurídicos”, “interés superior del niño” y “principio rector procedimental”. Asimismo, identifica correctamente los mecanismos de participación de los NNA y los vincula con el debido proceso, en particular con el derecho a ser oído. Estas respuestas son concisas y van al punto, abordando los elementos básicos requeridos. No obstante, presenta serias deficiencias analíticas: el enfoque de género es extremadamente superficial, limitado a mencionar “las particularidades de ser mujer” sin un desarrollo estructural; no incorpora perspectiva interseccional, ni profundiza en cómo el proceso judicial podría reproducir o transformar desigualdades estructurales; y el desarrollo contextual —aunque menciona el estallido social— es general y carente de vinculación con acontecimientos políticos específicos recientes. Para mejorar sustancialmente, el estudiante debe: (i) ampliar su capacidad de análisis crítico, integrando una auténtica perspectiva de género e interseccional, (ii) reforzar el desarrollo conceptual y normativo con citas a la Ley N° 21.430, el Código Civil y tratados internacionales; y (iii) evolucionar hacia respuestas más profundas y comprehensivas, superando el estilo telegráfico a fin de demostrar madurez en el razonamiento jurídico-social.
A96: 21477568 | B96: 9 | C96: ALEXANDRA TRINIDAD MENARES PÉREZ | D96: MENARES | E96: PÉREZ | F96: ALEXANDRA TRINIDAD | S96: =SUM(K96:R96) -> 0 | T96: =S96/40 -> 0 | U96: =IF(H96="Rendida ",IF('Resultados Individuales'!T96<49.5%,"Por Mejorar",IF('Resultados Individuales'!T96<64.5%,"Base",IF('Resultados Individuales'!T96<84.5%,"Satisfactorio","Óptimo"))),"No rendida o no válida") -> No rendida o no válida
